Workbook
Name concepto.1087: #REF!
Name concepto.1087: #REF!
Name concepto.1087: #REF!
Name concepto.1087: #REF!
Name concepto.1087: #REF!
Name concepto.1087: #REF!
Name concepto.1087: #REF!
Name concepto.1087: #REF!
Name concepto.1087: #REF!
Name concepto.1087: #REF!
Name concepto.1087: #REF!
Name concepto1004: #REF!
Name concepto1004: #REF!
Name concepto1004: #REF!
Name concepto1004: #REF!
Name concepto1004: #REF!
Name concepto1004: #REF!
Name concepto1004: #REF!
Name concepto1004: #REF!
Name concepto1004: #REF!
Name concepto1004: #REF!
Name concepto1004: #REF!
Name concepto1004.casillero: #REF!
Name concepto1004.casillero: #REF!
Name concepto1004.casillero: #REF!
Name concepto1004.casillero: #REF!
Name concepto1004.casillero: #REF!
Name concepto1004.casillero: #REF!
Name concepto1004.casillero: #REF!
Name concepto1004.casillero: #REF!
Name concepto1004.casillero: #REF!
Name concepto1004.casillero: #REF!
Name concepto1004.casillero: #REF!
Name concepto1004.error1: #REF!
Name concepto1004.error1: #REF!
Name concepto1004.error1: #REF!
Name concepto1004.error1: #REF!
Name concepto1004.error1: #REF!
Name concepto1004.error1: #REF!
Name concepto1004.error1: #REF!
Name concepto1004.error1: #REF!
Name concepto1004.error1: #REF!
Name concepto1004.error1: #REF!
Name concepto1004.error1: #REF!
Name concepto1004.error2: #REF!
Name concepto1004.error2: #REF!
Name concepto1004.error2: #REF!
Name concepto1004.error2: #REF!
Name concepto1004.error2: #REF!
Name concepto1004.error2: #REF!
Name concepto1004.error2: #REF!
Name concepto1004.error2: #REF!
Name concepto1004.error2: #REF!
Name concepto1004.error2: #REF!
Name concepto1004.error2: #REF!
Name concepto1004.validacion1: #REF!
Name concepto1004.validacion1: #REF!
Name concepto1004.validacion1: #REF!
Name concepto1004.validacion1: #REF!
Name concepto1004.validacion1: #REF!

Sheet REVEPYMES 11,12.23,27,29,34,33 
B3: Sección 27
B4: Deterioro del Valor de los Activos
B6: Información a revelar
B7: 27.32 Una entidad revelará, para cada clase de activos indicada en el párrafo 27.33, la
B8: siguiente información:
B9: (a) El importe de las pérdidas por deterioro del valor reconocidas en resultados
B10: durante el periodo y la partida o partidas del estado del resultado integral
B11: (y del estado de resultados, si se presenta) en las que esas pérdidas por
B12: deterioro del valor estén incluidas.
B13: (b) El importe de las reversiones de pérdidas por deterioro del valor
B14: reconocidas en resultados durante el periodo y la partida o partidas del
B15: estado del resultado integral (y del estado de resultados, si se presenta) en
... B457: todos las obligaciones con relacionadas deben tener la confirmaciones

Sheet EXPLICACION MARCA
A1: EXPLICACION DE MARCA
A2: √= Verificado y está conforme con la revisión, Cotejado con documento (físico)
A5: = verificado y no está conforme, revisar 1 error
A7: X= error, No cumple con todos los requisitos
A9: Ø= Información incorrecta
A11: = Falta información
A13: S= Solicitud de confirmación enviada
A15: SI= Solicitud de confirmación recibida inconforme
A17: SIA= Solicitud de confirmación recibida inconforme pero aclarada
A19: SC= Solicitud de confirmación recibida conforme
A21: ∑= Sumatoria, totalizado
A23: €= Conciliado
... A47: V = Ver hoja

Sheet 12RATIOS FINANCIEROS 
A6: MATRIZ DE REVISION ANALITICA
A8: CLIENTE: | H8: RATIOS
A9: PERIODO:
A10: CUESTIONARIO:
A11: REVISADO: | D11: ANTERIOR | E11: ACTUAL
A12: Elaborado por: | C12: ACTIVO CORRIENTE | D12: =SUM('4 BG101'!D11:D14) -> 21075.33 | E12: =SUM('4 BG101'!M11:M13) -> 0
C13: PASIVO CORRIENTE | D13: =SUM('4 BG101'!D30:D36) -> 502.05 | E13: =SUM('4 BG101'!M30:M36) -> 0
A14: DENOMINACION DEL RATIO | B14: FORMULA | C14: INTERPRETACIÓN | D14: RATIOS RESULTADOS DEL PERIODO | F14: COMENTARIOS | G14: EVALUACION DEL RIESGO
D15: AÑO ANTERIOR | E15: AÑO ACTUAL | G15: ALTO | H15: MODERADO | I15: BAJO
A16: Corriente | B16: Activo corriente/ pasivo coriente | C16: La empresa cuenta por cada | D16: =+D12/D13 -> 41.978548 | E16: =+E12/E13 -> #DIV/0!
A17: Prueba acida | B17: Activo corriente - nventaios / Pasivo corriente | C17: La empresa cuenta por cada S/ 1.00 de deuda corriente | D17: =+(D12-'4 BG101'!D14)/D13 -> 41.978548 | E17: =+(E12-'4 BG101'!M14)/E13 -> #DIV/0!
A18: Liquidez inmediata | B18: Efectivo y equivalente de efectivo / Pasivo corriente | C18: La empresa cuenta por cada S/ 1.00 de deuda corriente | D18: =+'4 BG101'!D11/'12RATIOS FINANCIEROS '!D13 -> 41.978548 | E18: =+'4 BG101'!M11/'12RATIOS FINANCIEROS '!E13 -> #DIV/0!
A19: capital de trabajo | B19: Activo corriente - pasivo corriente | C19: La empresa cuenta con como capital de trabajo, para poder operar, en el sector comercial monto no razonable ya que si comparamos con el capital invertido por los socios , existe una desproporción entre la inversión destinado al capital de trabajo y la inversión en activos de propiedad planta y equipo | D19: =+D12-D13 -> 20573.28 | E19: =+E12-E13 -> 0
A20: Periodo pro medio de cobranza | B20: Cuentas por cobrar (x) 360 Días/ Ventas anuales | C20: El tiempo que tarda en convertirse en efectivo las cuentas por cobrar es de 50 días | D20: =(+'4 BG101'!D12*360)/'5 PG101'!D19 -> 0 | E20: =(+'4 BG101'!M12*360)/'5 PG101'!L19 -> #DIV/0!
A21: Rotación de cuentas por cobrar | B21: Ventas/ Cuentas por cobrar | C21: La cuentas por cobrar circulan 7 veces durante el año comercial, o lo que significa que, se convierten en efectivo en promedio de 7 veces al año, estándar ideal en empresas comercial la rotación debe ser mensual | D21: =+'5 PG101'!D19/'4 BG101'!D12 -> #DIV/0! | E21: =+'5 PG101'!L19/'4 BG101'!M12 -> #DIV/0!
A22: Rotación de inventario | B22: Inventario promedio * 360 dias / costo de ventas | C22: Esto quiere decir que los inventarios se venden cada 172 días, lo que de muestra una baja o lenta rotación de los inventarios, en nuestro caso 2.28 veces al año. A mayor rotación mayor movilidad del capital de trabajo invertido en nventarios y más rápida es la generación de utilidades | E22: =((+'4 BG101'!D14+'4 BG101'!M14)/2)/360 -> 0
B23: 2,398.500 X 360 / 5,47 4,000 = 157.7 Días 360 Días / 157,7 = 2.28 veces al año
B24: (Costo de ventas / inventario promedio) x 2 (5,474,000 / 4,797,000) X 2 =1.14 X 2=2.28 veces | E24: =SUM('5 PG101'!L22:L28)/((+'4 BG101'!D14+'4 BG101'!M14)/2) -> #DIV/0!
A25: Período promedio de pago a proveedores | B25: Cuentas por pagar (promeio) x 360 días/ compras a proveedores 3,025,952 X 360 / 9,552,000 = 114.04 Días 360 / 114.04 = 3.16 Veces al año | E25: =(+'4 BG101'!D30+'4 BG101'!M30)/2*360/'5 PG101'!L22 -> #DIV/0!

Sheet 11Materialidad SUM
D1: PAPELES DE TRABAJO 3ANG ADMINISTRACIÓN DE NEGOCIOS GERENCIALES CÍA. LTDA.
D3: =+'4 BG101'!B2 -> TABACALERA MENHURSA S.A.
D5: A/T 31 DICIEMBRE DEL 2023
D7: CÁLCULO DE LA MATERIALIDAD PLANEADA
C10: ELABORADO POR: | D10: =+'28 Certif del equipo (2)'!C22 -> Ing. Maria Elizabeth Palacios | J10: FECHA: | L10: 44768
C11: SUPERVISADO POR: | D11: Roy Cisneros | J11: FECHA: | L11: =+L10+2 -> 44770
A13: AAA | C13: Objetivo: | D13: Tener una seguridad alta, aunque no absoluta de que los estados financieros no contengan errores o irregularidades importantes.
A15: AAAA | C15: Naturaleza | D15: La materialidad se refiere a la magnitud o a la naturaleza de un error, que a la luz de las circunstancias prevalecientes, podría cambiar o influenciar en el juicio de un usuario razonable de los estados financieros.
A16: AAAA | D16: La materialidad es una función no sólo de la magnitud de un error, sino también de la naturaleza del error. Dependiendo de las circunstancias los errores de las cantidades relativamente pequeñas pueden tener un impacto material o importante en los estados financieros.
A17: AAAA | D17: Nuestra apreciación de lo que es material es crucial para todo el proceso de auditoria, desde el principio hasta el final.
B19: 1 | C19: Materialidad Sobre los Activos | I19: 3 | J19: Materialidad Sobre los Ingresos | L19: =+'5 PG101'!L19 -> 0
D20: Total Activos | F20: =+'4 BG101'!M27 -> 0 | J20: % | L20: 0.01
D21: % | F21: 0.01 | L21: =+L20*L19 -> 0
F22: =+F20*F21 -> 0
B23: 2 | C23: Materialidad Sobre los pasivos | I23: 4 | J23: Materialidad Sobre los Gastos | L23: =+'5 PG101'!L41 -> 0
D24: Total Pasivos | F24: =+'4 BG101'!M46 -> 0 | J24: % | L24: 0.01
D25: % | F25: 0.01 | L25: =+L23*L24 -> 0
F26: =+F25*F24 -> 0
I27: 1 | J27: =+C19 -> Materialidad Sobre los Activos | L27: =+F22 -> 0
B28: 5 | C28: Materialidad Sobre Capital de Trabajo | I28: 2 | J28: =+C23 -> Materialidad Sobre los pasivos | L28: =+F26 -> 0
D29: Activo Corriente | F29: =SUM('4 BG101'!M11:M14) -> 0 | I29: 3 | J29: =+J19 -> Materialidad Sobre los Ingresos | L29: =+L21 -> 0
D30: (-) Pasivo Corriente | F30: =SUM('4 BG101'!M30:M36) -> 0 | I30: 4 | J30: =+J23 -> Materialidad Sobre los Gastos | L30: =+L25 -> 0
D31: Cap. Trab | F31: =+F29-F30 -> 0 | I31: 5 | J31: =+C28 -> Materialidad Sobre Capital de Trabajo | L31: =+F33 -> 0
D32: % | F32: 0.01
F33: =+F31*F32 -> 0 | J33: Materialidad Planeada | L33: =SUM(L27:L31) -> 0
B35: 6 | C35: Resultados antes de impuestos | F35: =+'5 PG101'!L42 -> 0 | K35: Sobre el Activo | L35: 0.03
J38: Activo | K38: =+F20 -> 0 | L38: =+K38*L35 -> 0
D42: Abreviatura
C43: MP: | D43: Materialidad de Planeación | G43: Emi: | H43: Error Mínimo
C44: ET: | D44: Error Tolerable o Importancia Relativa del Desempeño | G44: RDA: | H44: Resumen de Diferencias de Auditoría
C47: BENCHMARKING O BASE DE REFERENCIA | D47: PORCENTAJE PARA DETERMINAR EL NIVEL DE MATERIALIDAD
D48: FIRMA 1 | E48: FIRMA 2 | F48: FIRMA 3 | G48: FIRMA 4 | H48: FIRMA 5 | I48: FIRMA 6
C49: Resultados antes de impuestos Listados en bolsa | D49: 5% a 10% | E49: 5% a 10% | F49: 3% a 10% | G49: 3% a 10% | H49: 5% a 8% | I49: 5% a 10%
C50: Resultados antes de impuestos No listados en bolsa | D50: 5% a 10% | E50: 5% a 10% | F50: 3% a 10% | G50: 3% a 10% | H50: 5% a 10% | I50: Hasta 10%
C51: Utilidad bruta Listados en bolsa | D51: Hasta2.5% | E51: 0 | F51: 0 | G51: 3% a 10% | H51: 1 a2% | I51: Juicio del Auditor
C52: Utilidad bruta No listados en bolsa | D52: Hasta3.5% | E52: 0 | F52: 0 | G52: 3% a 10% | H52: 1%a4% | I52: Juicio del Auditor
C53: Activos netos Listados en bolsa | D53: 0.5%a 1% | E53: 0.5%a 1% | F53: 2%a5% | G53: 3% a 10% | H53: 1%a2% | I53: Hasta3%
C54: Activos netos No Listados en bolsa | D54: 1.75a2% | E54: 0.5% a 1% | F54: 2% a 5% | G54: 3% to 10% | H54: 1% a 5% | I54: Hasta3%
C55: Ingresos Listados en bolsa | D55: Hasta 1% | E55: 0.5%a2% | F55: 0.5%a 2% | G55: 0.5%a3% | H55: 0.5% a 1% | I55: 0.8%a5% En escala móvil
C56: Ingresos No istados en bolsa | D56: Hasta2% | E56: 0.5%a2% | F56: 0.5%a 2% | G56: 0.5%a3% | H56: 0.5%a2% | I56: 0.8%a5% En escala móvil
C57: Total activos Listados en bolsa | D57: Hasta 0.5% | E57: 0.5% a2% | F57: 1%a2% | G57: 0.5%a3% | H57: 0.5% a 1% | I57: 0
C58: Total activos No listados en bolsa | D58: Hasta2% | E58: 0.5%a2% | F58: 1%a2% | G58: 0.5%a3% | H58: 0.5%a2% | I58: 0
B60: Paso 3 Determinar la materialidad, el error tolerancia y el error mínimo, tomando en consideración las distintas bases de referencias.
C62: BASE DE REFERENCIA (NO COTIZADOS EN BOLSA) | D62: IMPORTE | E62: % | F62: ERROR MATERIAL LA MP ES IGUAL AL % DE LA BASE DE REFERENCIA | G62: EL ERROR.TOLERABLE (ET) PUEDE SER: | I62: ERROR MÍNIMO (EMI)
G63: AL 50% DE LA MP | H63: Ó AL 75% DE LA MP | I63: AL 50% EMI ES GUAL AL 5% DEL ET | J63: AL 75% EMI ES GUAL AL 3% DEL ET
C64: Resultados antes de Impuestos | D64: =+F35 -> 0 | E64: 0.05 | F64: =+D64*E64 -> 0 | G64: =+F64*50% -> 0 | H64: =+F64*75% -> 0 | I64: =+G64*5% -> 0 | J64: =+H64*3% -> 0
C65: Resultados antes de Impuestos | D65: =+F35 -> 0 | E65: 0.1 | F65: =+D65*E65 -> 0 | G65: =+F65*50% -> 0 | H65: =+F65*75% -> 0 | I65: =+G65*5% -> 0 | J65: =+H65*3% -> 0
C66: Total activos | D66: =+F20 -> 0 | E66: 0.02 | F66: =+D66*E66 -> 0 | G66: =+F66*50% -> 0 | H66: =+F66*75% -> 0 | I66: =+G66*5% -> 0 | J66: =+H66*3% -> 0
C67: Total ingresos | D67: =+L19 -> 0 | E67: 0.02 | F67: =+D67*E67 -> 0 | G67: =+F67*50% -> 0 | H67: =+F67*75% -> 0 | I67: =+G67*5% -> 0 | J67: =+H67*3% -> 0
B69: NOTAS | C69: (1) El ET puede determinarse al 50% de a MP o puede ser al 75% de la MP depende de a evaluación de los controles y riesgos inherentes, si os riesgos tanto inherentes y de control son altos, se escogerá para el ET, la tasa de50%.
C70: (2) Si los riesgos inherente y de control son bajos o moderados se deberá escoger para el ET, el 75% de a MP
C71: (3) Para determinar el error mínimo se calculará bajo cualquiera de las dos opciones. Al 5% si el ET se estimo al 50% de la MP o al 3 % si el ET se estimo al 75 % de la MP
C73: INSTRUCCIONES
B74: 1 | C74: Para determinar la materialidad de la planeación se debe seleccionar una de las siguientes bases:
B75: 2 | C75: Incluir el importe de la base a utilizar
D77: Importe | E77: Marque con X | G77: % | H77: Importe de la base en $$
B78: a) | C78: TOTAL INGRESOS | D78: =+L19 -> 0
B79: b) | C79: TOTAL ACTIVOS | D79: =+F20 -> 0 | E79: x | G79: 0.005 | H79: =+D79*G79 -> 0
A80: ??? | B80: c) | C80: TOTAL PATRIMONIO | D80: =SUM('4 BG101'!M48:M50) -> 0
A81: ??? | B81: d) | C81: UTILIDAD ANTES DE IMPUESTOS | D81: =+F35 -> 0
C83: Si seleccionó otra base distinta a las mencionadas, exponga razones y documente la decisión por la cual se utilizó la base diferente:
B85: 3 | C85: Multiplicar el porcentaje de la base seleccionada | G85: $
B87: a) | C87: Total Activos | E87: 0.005 | G87: =+H79 -> 0
C88: Materialidad de planeación o importancia relativa como un todo | E88: (MP) | G88: =+G87 -> 0
C90: NOTA: | D90: El p.A7 de la NIA 320 recomienda que, el Auditor puede considerar apropiado el 1% de los ingresos totales para la entidad no orientada a utilidades (en este caso consideramos el 0.5% del total de activos porque es una empresa orientada a utilidades.
C92: ERROR TOREABLE O IMPORTANCIA RELATIVA DE DESEMPEÑO
A94: ???? | B94: 4 | C94: Determinar el Error Tolerable ET o importancia relativa del desempeño, multiplicando la materialidad de planeación (MP) por el 50% o el 75%. Dependiendo de los riesgos de control y riesgos en las aseveraciones. En este caso se tomó como base el 50%
I95: $
C96: Para mejorar el ET se multiplica la MP por el 50% | F96: (MP) X50% | G96: 0.5 | H96: ET | I96: =+G88*G96 -> 0
A98: ¿¿¿ | C98: El error tolerable es el límite máximo de aceptación de errores con el que el auditor pueda concluir que el resultado de las pruebas debe lograr su objetivo. Este error tolerable ha de ser mayor que la materialidad o importancia relativa fijada en la fase de planificación, y por tanto será una fracción de aquella.
A100: ¿¿¿ | C100: El P.11 de la NIA 320 señala que, el auditor deberá determinar la importancia relativa del desempeño (ET) para fines de evaluar los riesgos de error material y determinar la naturaleza, oportunidad y extensión de los procedimientos adicionales de auditoría.
A102: ¿¿¿¿ | C102: A su vez el P. A12 de la NIA 320 indica que, la materialidad de desempeño (ET) a nivel global o de los Estados Financieros o para una clase particular de transacciones, saldos de cuentas o revelaciones se fija para determinar el error material y para reducir a un nivel apropiadamente bajo la probabilidad de que el agregado de errores sin corregir y sin detectar en los estados financieros exceda la materialidad planeada para los estados financieros como un todo.
A104: ¿¿¿¿ | C104: Notas: El monto determinado como error tolerable servirá para calificar o clasificar las partidas del ESF y el Estado de Resultados integral en partidas significativas y no significativas, en el ejemplo propuesto el ET alcanza $ 38.250, por lo tanto todas las partidas que sean iguales o superen, este monto clasificarán como partidas significativas.
B106: 5 | C106: Determinar el error mínimo multiplicando el error tolerable bajo dos opciones.
B108: a) | C108: Si el ET se ha establecido al 50% de la MP se multiplica por el 5%
B109: b) | C109: Si el ET se ha establecido al 75% de la MP se multiplica por el 3%
A111: ¿¿¿ | C111: Referencia: numeral 4.3 de la Guía de Auditoría capítulo determinación de los montos nominales de materialidad.
C114: Para determinar el error mínimo se multiplica el ET por el 5% | G114: 0.05 | H114: de (ET) = | I114: =+I96*G114 -> 0
C116: Error mínimo se incluye en el resumen de Diferencias de Auditoría (RDA) | H116: = | I116: =+I114 -> 0
C118: El importe de $ | D118: =+I116 -> 0 | E118: es el monto mínimo para acumular errores que serán revelados en la cédula de errores de auditoría.
B120: NOTAS | C120: EL P.12 de la NIA 320 señala que, el error mínimo (Emi) se fija para reducir el nivel apropiadamente bajo la probabilidad de que el agregado de errores exceda la materialidad para los estados financieros.
C122: Por otro lado el P.A2 NIA 450 señala que el auditor puede designar un monto por debajo del ET, del cual los errores serían claramente triviales (RDA) (que no tiene importancia, trascendencia o interés): y no necesitarían acumularse porque el auditor espera que la acumulación de estos montos no tuviera un efecto significativo sobre los estados financieros.
C124: Materialidad Real | D124: Preliminar | G124: Materialidad Real | I124: Final
C125: Total Activo | D125: =+'4 BG101'!F27 -> 0 | G125: Total Activo | I125: =+'4 BG101'!M27 -> 0
C126: (MP) 0.5% del total de activos | D126: =+D125*0.005 -> 0 | G126: (MP) 0.5% del total de activos | I126: =+I125*0.005 -> 0
C127: (ET) 50% de la MP | D127: =+D126*50% -> 0 | G127: (ET) 50% de la MP | I127: =+I126*50% -> 0
C128: RDA 5% del ET | D128: =+D127*5% -> 0 | G128: RDA 5% del ET | I128: =+I127*5% -> 0
A131: ¿¿¿¿¿¿ | C131: En razón a que se supone que la comisión de auditoría antes de realizar la auditoría debe realizar una primera visita a la entidad a auditar en los últimos meses del ejercicio, octubre, noviembre. Etc. Que se está concluyendo los estados financieros, para ello solicitará los últimos estados financieros cerrados del tercer trimestre que corresponde al mes de septiembre, en cambio si la auditoría se realizara después del mes de diciembre, se tomará el importe total y definitivo del activo.

Sheet 31 lavado  de activos 
A2: ¿¿¿¿ | C2: ASUNTOS REQUERIDOS POR LA LEY ORGÁNICA DE PREVENCIÓN, DETECCIÓN Y ERRADICACIÓN DEL DELITO DE LAVADO DE ACTIVOS Y DEL FINANCIAMIENTO DE DELITOS.
C4: A los Accionistas de:
C5: INMCAMPSA S.A.
C7: Santo Domingo, Ecuador
S8: =+'OPINION pymes con anexo '!I72 -> Agosto, 18 del 2023
A9: ¿¿¿¿¿¿¿¿¿ | C9: Hemos auditado los Estados Financieros por el período terminado al 31 de diciembre del 2021 y con fecha 18 de abril del 2022 emitimos el informe de auditoría de la compañía INMCAMPSA S.A., Según lo establecido en la LEY DE PREVENCIÓN, DETECCIÓN Y ERRADICACIÓN DEL DELITO DE LAVADO DE ACTIVOS Y DEL FINANCIAMIENTO DE DELITO, debemos verificar el cumplimiento de lo previsto en esta norma respecto a las políticas, procedimientos y mecanismos implementados por el sujeto obligado para la prevención del lavado de activos, el financiamiento del terrorismo y otros delitos, valorar su eficacia operativa y proponer, de ser el caso, eventuales rectificaciones o mejoras.
A11: ¿¿¿¿¿¿ | C11: 1 | D11: Los sujetos obligados deben contar con políticas y procedimientos de control para prevenir el lavado de activos, el financiamiento del terrorismo y otros delitos de conformidad con lo establecido en la presente norma; y, adoptar medidas de control apropiadas y suficientes, orientadas a evitar que puedan ser utilizados como instrumentos para realizar actividades vinculadas al lavado de activos y/o al financiamiento del terrorismo y otros delitos.
A13: ¿¿ | C13: 2 | D13: Las políticas que adopta la compañía para prevenir el lavado de activos, el financiamiento del terrorismo y otros delitos, cumple con los siguientes parámetros:
A15: ¿¿ | D15: • | E15: Las políticas y procedimientos incorporados le permitan administrar, evaluar y mitigar con eficacia los riesgos que se hayan identificado.
A16: ¿ | D16: • | E16: Abarca toda clase de productos o servicios que ofrece la compañía.
A17: ¿¿¿¿ | D17: • | E17: Asegura que los miembros de la compañía tengan el debido conocimiento, acatamiento y aplicación de las normativas legales y reglamentarias relacionadas con la prevención de lavado de activos y el financiamiento del terrorismo y otros delitos.
A18: ¿¿ | D18: • | E18: Minimiza el grado de exposición inherente al lavado de activos y al financiamiento del terrorismo y otros delitos.
A19: ¿¿ | D19: • | E19: Establece políticas de debida diligencia según el riesgo que la misma compañía ha identificado.
A20: ¿¿¿ | D20: • | E20: Garantiza la reserva y confidencialidad de la información reportada, conforme lo previsto en la Ley de Prevención, Detección y Erradicación del Delito de Lavado de Activos y del Financiamiento de Delitos.
A22: ¿¿ | C22: 3 | D22: Los procedimientos de prevención para el lavado de activos, el financiamiento del terrorismo y otros delitos, adoptados por la compañía le permiten:
A24: ¿¿¿ | D24: • | E24: Identificar al cliente, conocer y verificar su información con el objeto de establecer el perfil, y determinar si el volumen de operaciones guardan relación con la información por éste proporcionada.
A25: ¿¿¿ | D25: • | E25: Comunicar a la Unidad de Análisis Financiero y Económico de la existencia de las transacciones y operaciones económicas que superen el umbral en los términos señalados en la ley.
A26: ¿¿¿ | D26: • | E26: Detectar operaciones o transacciones económicas inusuales e injustificadas, para reportarlas oportunamente y con los sustentos del caso a la Unidad de Análisis Financiero y Económico (UAFE).
A27: ¿¿ | D27: • | E27: Atender los requerimientos de información formulados por autoridades competentes.
A29: ¿¿¿¿¿ | C29: 4 | D29: Los representantes legales o administradores, oficiales de cumplimiento, socios y empleados, están obligados a guardar reserva y confidencialidad respecto de las operaciones que llegan a su conocimiento en el ejercicio de sus funciones. Expresamente se les prohíbe informar de cualquier notificación que hubieren hecho a las autoridades competentes.
A31: ¿¿¿ | C31: 5 | D31: El Manual de Prevención establece las políticas y los procedimientos de control que adopta la compañía y dispone cómo deben operar los mecanismos de prevención establecen los procedimientos :
A33: ¿¿ | D33: • | E33: Implementa la vinculación de nuevos clientes, así como confirma y actualiza la información aportada por los clientes antiguos.
A34: ¿¿ | D34: • | E34: Conserva y protege los registros operativos y documentos relacionados con los clientes y aquellos documentos que sean solicitados por las autoridades.
A35: ¿¿ | D35: • | E35: Define los canales de comunicación e instancias de reporte entre el oficial de cumplimiento y demás áreas de la compañía.
A36: ¿ | D36: • | E36: Atiende oportunamente los reportes periódicos de acuerdo a la ley.
A37: ¿¿ | D37: • | E37: Detecta señales de alerta de acuerdo a la naturaleza de los productos y servicios que ofrece la compañía.
A38: ¿ | D38: • | E38: Cumple las políticas de debidas diligencias que adopte al sujeto obligado.
A39: ¿¿¿ | D39: • | E39: Establece el sistema de prevención de riesgos que mide de forma cualitativa las probabilidades y los posibles impactos de riesgo que tiene cada cliente, operación o transacción dentro del giro de negocio de la organización.
A40: ¿¿ | C40: 6 | D40: El manual debe ser conocido por todo el personal y puede ser actualizado, en caso de requerirlo la compañía.
A42: ¿¿¿¿ | C42: 7 | D42: La compañía al inicio de la relación comercial o contractual, elabora un formulario que permita identificar al cliente, conocer la actividad económica que desarrollen en caso de que el cliente no cuente con alguno de los datos mínimos de información solicitada, no se inicia la relación comercial y se mantiene un registro de los mismos.
A44: ¿¿¿¿ | C44: 8 | D44: Para los clientes y operaciones calificadas por la empresa como de bajo riesgo, aplica procedimientos de Debida Diligencia Simplificada, lo que en ningún caso implicará omitir la presentación de lo señalado en el artículo 12 normas de prevención de lavado de activos, financiamiento del terrorismo y la verificara de lo consignado.
A46: ¿¿¿¿¿¿¿¿¿¿¿¿ | C46: 9 | D46: Los sujetos obligados del sector que se dedique a las actividades de la construcción e intermediación e inversión inmobiliaria, deben registrar todas las operaciones y transacciones que realizan sus clientes. Sin embargo, en lo que respecta a la información del cliente, para aquellas transacciones u operaciones individuales o múltiples que en un mes sean realizadas en beneficio de una misma persona, cuyos montos sean menores a los diez mil dólares de los Estados Unidos de América (USD $ 10.000,00) o su equivalente en otras monedas, se requerirá información básica como número de identificación, nombres y apellidos completos, dirección y teléfono. En el mismo caso, y cuando el monto iguale o supere los diez mil dólares de los Estados Unidos de América (USD $ 10.000,00) o su equivalente en otras monedas, se solicitará como mínimo la información establecida en el artículo 10 de la presente resolución, y/o dependiendo del tipo de cliente, se aplicarán procedimientos de debida diligencia.
A48: ¿¿¿¿¿¿ | C48: 10 | D48: La información y documentación que debe conservar el sujeto obligado debe ser adecuada y suficiente para poder reconstruir los vínculos transaccionales y, eventualmente, puedan llegar a servir como elementos en análisis, investigaciones o procesos judiciales en materia de lavado de activos y financiamiento del terrorismo y otros delitos. Para estos propósitos, como mínimo, la información a ser archivada por la compañía es la siguiente:
A50: ¿¿¿ | D50: • | E50: Expediente del cliente que debe contener todos los documentos e información recopilada por el sujeto obligado durante la relación comercial, con los soportes de su verificación.
D51: • | E51: Perfil financiero y transaccional del cliente.
D52: • | E52: Archivos de operaciones y correspondencia comercial.
A53: ¿¿¿ | D53: • | E53: Información relacionada con el manejo de fondos cuya cuantía o características no guarden relación con la actividad económica del cliente, o cuyo origen no pueda justificarse, así como las transacciones complejas y/o inusuales.
A54: ¿¿¿ | D54: • | E54: Informes que sustenten las razones por las cuales una operación calificada por el sujeto obligado como inusual e injustificado no fue reportada a la Unidad de Análisis Financiero y Económico (UAFE).
A56: ¿¿¿ | C56: 11 | D56: La junta general de socios de la compañía debe designar un oficial de cumplimiento para coordinar las actividades de control, vigilancia, detección, prevención y reporte de operaciones o transacciones económicas inusuales e injustificadas.
A58: ¿¿¿ | D58: • | E58: El oficial de cumplimiento deberá ser independiente de las otras áreas de la compañía y estará dotado de facultades y recursos suficientes para cumplir adecuadamente sus funciones.
A59: ¿¿¿ | D59: • | E59: El sujeto obligado notificará a la Superintendencia de Compañías y Valores la designación del oficial de cumplimiento de la compañía, dentro de los cinco (5) días siguientes a que se haya efectuado.
C61: CON RESPECTO A LOS PUNTOS MENCIONADOS ANTERIORMENTE DEBEMOS INDICAR:
A63: ¿¿¿¿ | D63: A | E63: En la revisión a los reportes de operaciones y transacciones individuales y múltiples reportadas a la UAFE dentro de los quince (15) días posteriores al cierre del ejercicio mensual de la compañía INMCAMPSA S.A., se pudo identificar que existen operaciones mensuales que se reportan fuera de los plazos establecidos.
E65: • | F65: Comentario de Gerencia:
A67: ¿¿¿ | E67: Tomaremos en cuenta dicha la observación de la presentación de los reportes mensuales a UAFE dentro de los plazos establecidos a fin de evitar ser llamados la atención por los entes de control.
E71: Pachar Celi Marcia Edith | M71: María José Zurita Campos | T71: Pachar Celi Marcia Edith
E72: Gerente General | M72: Oficial de cumplimiento
A74: ¿¿¿¿¿ | D74: B | E74: El Personal de apoyo en el cumplimiento de políticas de prevención de INMCAMPSA S.A. durante el período no ha recibido capacitaciones en materia de prevención y erradicación del delito de lavado de activos y financiamiento del terrorismo; No se ha cumplido con la divulgación y capacitación de su Manual que establece Fecha programada de ejecución.
E76: • | F76: Comentario de Gerencia:
A78: ¿¿ | E78: La compañía se encuentra realizando programas que le permitan capacitar a su personal en materia de prevención de lavado de activos.
E82: =+E71 -> Pachar Celi Marcia Edith | M82: María José Zurita Campos
E83: Gerente General | M83: Oficial de cumplimiento
A85: ¿¿ | D85: C | E85: De le revisión efectuada al manual de prevención de lavado de activos de la compañía se observan las siguientes deficiencias:
A87: ¿¿¡ | F87: Las Responsabilidades de la Junta de accionistas: en sus literales: t, u y v, no corresponden a responsabilidades la prevención de lavado de activos para este organismo.
A89: ¿¿¡ | F89: Del Sistema de Prevención de Riesgos (SPR): la compañía hace mención de auditores internos, sin embargo no cuenta a con el departamento de auditoría interna o auditor interno.
A91: ¿¿¿ | F91: Última actualización fue a Marzo del 2019: consta información del Oficial de Cumplimiento a esta fecha y no ha realizado la actualización de datos al oficial de cumplimiento actual.
E94: • | F94: Comentario de Gerencia:
A96: ¿¿ | E96: La compañía se encuentra en proceso de actualización de su Manual de prevención de lavado de activos.
E100: =+E82 -> Pachar Celi Marcia Edith | M100: María José Zurita Campos
E101: Gerente General | M101: Oficial de cumplimiento
A104: ¿¿¿¿ | C104: Este informe se emite exclusivamente para conocimiento de los Socios y Administración de Compañía INMCAMPSA S.A., y para su presentación a la Unidad de Análisis Financiero y Económico (UAFE) en cumplimiento de las disposiciones emitidas por esta entidad de control, y no debe ser utilizado para ningún otro propósito.
D109: 3 A.N.G. Administración de Negocios Gerenciales Cía. Ltda.
D110: Resolución No 08-G-DIC-0002553
D111: SC- RNAE. 662
O113: ____________________________________
O114: Econ. Roy Cisneros Mejía
O115: SOCIO

Sheet contrato lavado activo
C2: CONTRATO DE PROCEDIMIENTOS PREVIAMENTE CONVENIDOS ASUNTOS REQUERIDOS POR LEY ORGÁNICA DE PREVENCIÓN, DETECCIÓN Y ERRADICACIÓN DEL DELITO DE LAVADO DE ACTIVOS Y DEL FINANCIAMIENTO DE DELITOS
A4: ¿¿¿¿¿ | C4: La Compañía es sujeto obligado a reportar a la Unidad de Análisis Financiero y Económico (UAFE) Según el Art. 5. de la Ley Orgánica De Prevención, Detección y Erradicación del Delito de Lavado de Activos y del Financiamiento de Delitos, el cumplimiento de estas obligaciones deben ser verificados por un auditor externo por lo que se firma el presente contrato.
A6: ¿¿¿¿¿ | C6: Conste por el presente documento el Contrato de Procedimientos Previamente Convenidos sobre los Asuntos Requeridos por Ley Orgánica De Prevención, Detección y Erradicación del Delito de Lavado de Activos y del Financiamiento de Delitos que celebran “INMCAMPSA S.A.” y por otra parte 3 A.N.G. ADMINISTRACIÓN DE NEGOCIOS GERENCIALES CIA. LTDA., al tenor de las siguientes cláusulas:
C8: CLAUSULA PRIMERA: COMPARECIENTES.-
C10: Debido a lo antes mencionado concurren a celebrar el siguiente Contrato las siguientes Personas:
A12: ¿¿¿¿¿ | C12: a) Por una parte “INMCAMPSA S.A.” De Ruc # 0992395125001 de expediente # 118536 Representada Legalmente por la Sra. Pachar Celi Marcia Edith en calidad de GERENTE GENERAL – INMCAMPSA S.A., quien obra debidamente autorizado por la Junta general, parte a la que en adelante, para efectos del siguiente contrato, se podrá denominar LA COMPAÑÍA.
A14: ¿¿¿¿¿ | C14: b) Por otra parte, 3 A.N.G. ADMINISTRACIÓN DE NEGOCIOS GERENCIALES CIA. LTDA., con RUC# 0992541504001 debidamente calificado y registrado en la Superintendencia de Compañías con el SC-RNAE-No 662 y Representada Legalmente por Eco. Roy Cisneros Mejía en calidad de GERENTE GENERAL para efectos del presente contrato se le denominara “EL AUDITOR EXTERNO”.
A16: ¿¿¿¿ | C16: CLAUSULA SEGUNDA: OBJETO.- La compañía suscribe el contrato con el Auditor Externo y acepta, la revisión de los siguientes puntos, dispuestos por la Ley Orgánica De Prevención, Detección y Erradicación del Delito de Lavado de Activos y del Financiamiento de Delitos:
A18: ¿¿¿¿¿¿ | C18: 1. Revisaremos si la compañía cuenta con políticas y procedimientos de control para prevenir el lavado de activos, el financiamiento del terrorismo y otros delitos de conformidad con lo establecido en la presente norma; y, adoptar medidas de control apropiadas y suficientes, orientadas a evitar que puedan ser utilizados como instrumentos para realizar actividades vinculadas al lavado de activos y/o al financiamiento del terrorismo y otros delitos.
A20: ¿¿¿ | C20: 2. Se verificara las políticas que adopta la compañía para prevenir el lavado de activos, el financiamiento del terrorismo y otros delitos, cumple con los siguientes parámetros:
A22: ¿¿ | C22: · Las políticas y procedimientos incorporados le permitan administrar, evaluar y mitigar con eficacia los riesgos que se hayan identificado.
A25: ¿¿ | C25: · Abarca toda clase de productos o servicios que ofrece la compañía.
A27: ¿¿¿ | C27: · Asegura que los miembros de la compañía tengan el debido conocimiento, acatamiento y aplicación de las normativas legales y reglamentarias relacionadas con la prevención de lavado de activos y el financiamiento del terrorismo y otros delitos.
A29: ¿¿ | C29: · Minimiza el grado de exposición inherente al lavado de activos y al financiamiento del terrorismo y otros delitos.
A30: ¿¿ | C30: · Establece políticas de debida diligencia según el riesgo que la misma compañía ha identificado.
A31: ¿¿¿ | C31: · Garantiza la reserva y confidencialidad de la información reportada, conforme lo previsto en la Ley de Prevención, Detección y Erradicación del Delito de Lavado de Activos y del Financiamiento de Delitos.
A33: ¿¿¿ | C33: 3. Analizaremos los procedimientos de prevención para el lavado de activos, el financiamiento del terrorismo y otros delitos, que adoptado por la compañía le permiten:
... A36: ¿¿¿ | C36: · Detectar operaciones o transacciones económicas inusuales e injustificadas, para reportarlas oportunamente y con los sustentos del caso a la Unidad de Análisis Financiero y Económico (UAFE).
C37: · Atender los requerimientos de información formulados por autoridades competentes.
A39: ¿¿¿¿¿ | C39: 4. Verificaremos que los representantes legales o administradores, oficiales de cumplimiento, socios y empleados, estén obligados a guardar reserva y confidencialidad respecto de las operaciones que lleguen a su conocimiento en el ejercicio de sus funciones. Expresamente se les prohíbe informar de cualquier notificación que hubieren hecho a las autoridades competentes.
A40: ¿¿¿¿ | C40: 5. Verificaremos que el Manual de Prevención establezca las políticas y los procedimientos de control que adopte la compañía y disponga cómo deben operar los mecanismos de prevención estableciendo los procedimientos :
A41: ¿¿¿ | C41: · Implementa la vinculación de nuevos clientes, así como confirma y actualiza la información aportada por los clientes antiguos.
A42: ¿¿¿ | C42: · Conserva y protege los registros operativos y documentos relacionados con los clientes y aquellos documentos que sean solicitados por las autoridades.
A43: ¿¿¿ | C43: · Define los canales de comunicación e instancias de reporte entre el oficial de cumplimiento y demás áreas de la compañía.
C44: · Atiende oportunamente los reportes periódicos de acuerdo a la ley.
A45: ¿¿¿ | C45: · Detecta señales de alerta de acuerdo a la naturaleza de los productos y servicios que ofrece la compañía.
C46: · Cumple las políticas de debidas diligencias que adopte al sujeto obligado.
A49: ¿¿ | C49: 6. Verificaremos si el manual ha sido conocido por todo el personal y pueda ser actualizado, en caso de requerirlo la compañía.
A51: ¿¿¿¿¿ | C51: 7. Revisaremos que la compañía al inicio de la relación comercial o contractual, elabora un formulario que permita identificar al cliente, conocer la actividad económica que desarrollen en caso de que el cliente no cuente con alguno de los datos mínimos de información solicitada, no se inicia la relación comercial y se mantiene un registro de los mismos.
A52: ¿¿¿¿¿ | C52: 8. Se revisara si los clientes y operaciones calificadas por la empresa como de bajo riesgo, apliquen procedimientos de Debida Diligencia Simplificada, lo que en ningún caso implicará omitir la presentación de lo señalado en el artículo 12 normas de prevención de lavado de activos, financiamiento del terrorismo y la verificara de lo consignado.
A54: ¿¿¿¿¿¿¿¿¿¿¿ | C54: 9. Se verificara que el sujeto obligado del sector que se dedique a las actividades de la construcción e intermediación e inversión inmobiliaria, registren todas las operaciones y transacciones que realizan sus clientes. Sin embargo, en lo que respecta a la información del cliente, para aquellas transacciones u operaciones individuales o múltiples que en un mes sean realizadas en beneficio de una misma persona, cuyos montos sean menores a los diez mil dólares de los Estados Unidos de América (USD $ 10.000,00) o su equivalente en otras monedas, se requerirá información básica como número de identificación, nombres y apellidos completos, dirección y teléfono. En el mismo caso, y cuando el monto iguale o supere los diez mil dólares de los Estados Unidos de América (USD $ 10.000,00) o su equivalente en otras monedas, se solicitará como mínimo la información establecida en el artículo 10 de la presente resolución, y/o dependiendo del tipo de cliente, se aplicarán procedimientos de debida diligencia.
A56: ¿¿¿¿¿¿ | C56: 10. Se revisara la información y documentación que deba conservar el sujeto obligado sea adecuada y suficiente para poder reconstruir los vínculos transaccionales y, eventualmente, puedan llegar a servir como elementos en análisis, investigaciones o procesos judiciales en materia de lavado de activos y financiamiento del terrorismo y otros delitos. Para estos propósitos, como mínimo, la información a ser archivada por la compañía es la siguiente:
A57: ¿¿¿ | C57: · Expediente del cliente que debe contener todos los documentos e información recopilada por el sujeto obligado durante la relación comercial, con los soportes de su verificación.
C58: · Perfil financiero y transaccional del cliente.
C59: · Archivos de operaciones y correspondencia comercial.
A60: ¿¿¿¿ | C60: · Información relacionada con el manejo de fondos cuya cuantía o características no guarden relación con la actividad económica del cliente, o cuyo origen no pueda justificarse, así como las transacciones complejas y/o inusuales.
A61: ¿¿¿ | C61: · Informes que sustenten las razones por las cuales una operación calificada por el sujeto obligado como inusual e injustificado no fue reportada a la Unidad de Análisis Financiero y Económico (UAFE).
A62: ¿¿¿¿ | C62: 11. Se verificara si la junta general de socios de la compañía ha designado un oficial de cumplimiento para coordinar las actividades de control, vigilancia, detección, prevención y reporte de operaciones o transacciones económicas inusuales e injustificadas.
A63: ¿¿¿ | C63: · El oficial de cumplimiento deberá ser independiente de las otras áreas de la compañía y estará dotado de facultades y recursos suficientes para cumplir adecuadamente sus funciones.
A66: ¿¿¿ | C66: · El sujeto obligado notificará a la Superintendencia de Compañías y Valores la designación del oficial de cumplimiento de la compañía, dentro de los cinco (5) días siguientes a que se haya efectuado.
C68: CLAUSULA TERCERA: OBLIGACIONES DE EL AUDITOR EXTERNO.-
A70: ¿¿¿¿ | C70: · El Auditor Externo se obliga a guardar con total confidencialidad acerca de toda la información objeto del presente contrato, que sea de conocimiento de su personal; ya sea dentro o fuera de sus instalaciones de acuerdo a lo señalado en la Ley Orgánica De Prevención, Detección y Erradicación del Delito de Lavado de Activos y del Financiamiento de Delitos.
C72: Como resultado del trabajo contratado, “El Auditor Externo”, emitirá:
A74: ¿¿¿¿¿ | C74: · Informe en español de Procedimientos previamente convenidos sobre Asuntos Requeridos por Ley Orgánica De Prevención, Detección y Erradicación del Delito de Lavado de Activos y del Financiamiento de Delitos, con los comentarios de los involucrados relacionados a los puntos antes mencionados.
C76: CLAUSULA CUARTA: OBLIGACIONES DE LA COMPAÑÍA.-
A78: ¿¿¿¿¿ | C78: LA COMPAÑÍA, se obliga a facilitar el acceso de El Auditor Externo a la información y documentación que sea razonablemente indispensable para la ejecución del objeto del presente contrato, mediante la colaboración de los funcionarios y empleados de la compañía y que los documentos y datos de respaldo estén localizables por el personal de El Auditor Contable.
C80: CLAUSULA QUINTA: DECLARACIONES.-
A82: ¿¿¿¿ | C82: El Auditor Externo declara expresa de forma incondicional e irrevocablemente que asume toda y cada una de las obligaciones legales, laborales y de seguridad social en calidad de patrono en relación con el personal y funcionarios que a su nombre ejecuten los servicios materia de este contrato.
C84: CLAUSULA SEXTA: PLAZO.-
A86: ¿¿¿¿ | C86: El plazo en que se obliga a entregar a la Compañía, materia del presente contrato es de cuarenta y cinco (45) días, contados a partir de la recepción de los documentos, y anexos. Tiempo que se puede reducir significativamente en función al volumen de transacciones a ser auditadas.
C88: CLAUSULA SÉPTIMA: HONORARIOS.-
A90: ¿¿¿¿ | C90: Los costos relacionados a honorarios están incluidos en el contrato inicial de auditoria externa a los estados financieros debido a que la obligación de realizar el contrato por este requerimiento, salió posterior a la fecha de la firma del contrato de auditoria externa.
C92: CLAUSULA OCTAVA: JURISDICCIÓN Y COMPETENCIA.-
A94: ¿¿¿¿ | C94: Las partes declaran que se someten a los Jueces Competentes de lo Civil, con sede en Santo Domingo, Provincia de Santo Domingo de los Tsáchilas, así como también a la ejecutiva o verbal sumaria.
A96: ¿¿¿¿ | C96: Para constancia de lo expresado, las partes suscriben el presente contrato en dos Ejemplares de igual tenor y valor, en esta ciudad Santo Domingo, Provincia de Santo Domingo de los Tsáchilas, a los 03 días de septiembre del 2021, y sumilla todas las hojas que forman parte de este contrato.
C103: ………………………………………….
C104: =+'6 INFORME BALANCES'!L24 -> Sr. Eduardo Mendoza Hurtado
C105: =+'6 INFORME BALANCES'!L9 -> TABACALERA MENHURSA S.A.
C106: Representante Legal
C112: …………………………………….
C113: Econ. Roy Cisneros Mejía
C114: Gerente General
C117: 3 A.N.G. ADMINISTRACION DE NEGOCIOS GERENCIALES CIA. LTDA.
C118: Ruc: 0992541504001
C119: Resolución No 08-G-DIC-0002553 del 6 de mayo del 2008
C120: con el SC- RNAE--662
H130: =+K130 -> 0 | K130: =+'OPINION pymes con anexo '!J137 -> 0

Sheet Carta entrega inf. L-A
H3: Santo Domingo, 18 de abril del 2022 | I3: =+'OPINION pymes con anexo '!I72 -> Agosto, 18 del 2023
B6: =+'6 INFORME BALANCES'!L24 -> Sr. Eduardo Mendoza Hurtado
B7: Gerente General
B8: =+'OPINION pymes con anexo '!C75 -> TABACALERA MENHURSA S.A.
A11: ¿¿¿¿ | B11: Por medio de la presente estamos haciendo entrega del Informe de Auditoría Externa en prevención, detección y erradicación del delito de lavado de activos y del financiamiento del Terrorismo, y el Respectivo Contrato, para que sean firmados
A14: ¿ | B14: Procederemos a retirar nuestra copia cuando ustedes nos indiquen .
B16: Reiteramos nuestro agradecimiento por la confianza depositada
B23: ………………………………..
B24: Econ. Roy Cisneros Mejía
B25: Gerente General
B31: F…………………………….
B32: Recibido

Sheet 30CAPI VI 
C5: INFORME DE AUDITORÍA Y ANEXOS
C9: =+'25CAPI IV'!C8 -> TABACALERA MENHURSA S.A.
C16: V I
C21: INFORME SOBRE LA LEY DE PREVENCIÓN, DETECCIÓN Y ERRADICACIÓN DEL DELITO DE LAVADO DE ACTIVOS Y DEL FINANCIAMIENTO DE DELITO.

Sheet PAPELES
A1: sumaria | C1: VERIFICACIONES DE PAPELES DE CSED
C2: ROSA VALAREZO
A3: 101
B4: 1. Pasar al sobregiro contable pasivos el valor del banco Banco Pichincha Unidad de Negocios 3347028104
A5: 102
B6: 2. Falta confirmaciones de cuentas por cobrar
B7: 3. Falta confirmación de cuenta por cobrar relacionada
B8: 4. Falta poner referencia a los papeles de trabajo
B9: 5. Falta trabajo sobre los empleados
A10: 111
B11: 6. Verificar los incrementos y las dimensiones soportar y pedir listado de activos fijos con fechas de vencimiento
B12: 7. Soportar los 304mil
B13: 8. Falta poner referencia a los papeles de trabajo
A15: 202
B16: 9. Dejar la evidencia de los seleccionados para circula como ls cartas borradores de la circulación
B17: 10. Falta de trabajo de impuestos ligar
B18: 11. Falta poner referencia a los papeles de trabajo
A20: 204
B21: 12. Falta el movimiento en la provisión a trabajadores 2.12.01.01.01.001 de incremento y la obligación
B22: 13. Falta de trabajo 2.11.01.01.01.002
B23: 14. Falta papeles de trabajo
A24: 205
B25: 15. Falta de trabajo no está soportado el incremento y la obligación
B26: 16. Falta poner referencia a los papeles de trabajo
A27: 217
B28: 17. Falta de trabajo no está soportado la disminución o pago este es un acuerdo con el sri
B29: 18. Falta poner referencia a los papeles de trabajo
A30: 303
B31: 19. | C31: Falta de trabajo no está realizado el movimiento del patrimonio con las movimientos reales que tubo e patrimonio soportar la cuenta utilidades del ejercicio Falta poner
B32: 20. referencia a los papeles de trabajo
A34: 601
B35: 21 | C35: pedir el contrato y la factura del ingreso para liquidar estos valores
A38: 707
B39: 23 | C39: Falta de trabajo no está soportado falta las sumarias
B40: 24 | C40: Falta poner referencia a los papeles de trabajo
B41: 25 | C41: probrar la cuentas
B42: 26 | C42: ligar las depreciaciones
B43: 27 | C43: ligar los decimos y gastos con trabajadores
B44: 28 | C44: ligar los sueldo a la cuentas donde se probo los sueldos sacados de las planillas
B45: 29 | C45: ligar Capacidad Contratada Csed.net
C46: ligar y realizar trabajos en:
C47: Bonificacion Alimentacion
C48: Implentos de Seguridad
A50: 800 | C50: IMPUSTO A LA RENTA
B51: 30 | C51: falta asiento de cierre con provisiones de participacion a trabajadores y impuesto a la renta
B52: 31 | C52: pedir conciliacion tributaria y mapeo de las cuentas
A54: 801 | C54: PARTES RELACIONADAS
B55: 32 | C55: hacer tabajo de partes relacionadas soportes las obligaciones
B56: 33 | C56: soportar los detalles de la cuenta empleados y verificar si estan relacionadas
B57: 34 | C57: terminar la nota 15 que sale de soprtar la parte realcionada en el informe
A60: sumaria | C60: VERIFICACIONES DE PAPELES DE NEWBETA
C61: ELIZABET
B63: 1 | C63: falta terminar lo de lavado de activos
B64: 2 | C64: falta oficial de cumplimiento
B66: 3 | C66: Los mayores no estan cruzados con los balances pedir el mayor que cruce
B67: 4 | C67: gestionar las respuestas a las confirmaciones
A69: 204
B70: 5 | C70: Pedir la conciliacion tributaria
A71: 303
B72: 6 | C72: falta trabajo del movimiento del patrimonio reavaluo acta soporte
A74: 801 | C74: PARTES RELACIONADAS
B75: 7 | C75: hacer tabajo de partes relacionadas soportes las obligaciones
B76: 8 | C76: soportar los detalles de la cuenta empleados y verificar si estan relacionadas
B77: 9 | C77: terminar la nota que sale de soprtar la parte realcionada en el informe
A80: sumaria | C80: VERIFICACIONES DE PAPELES DE AGROBIJAMA
C81: PAUL
C82: AGOBIJAMA
A83: 111
B84: 1 | C84: Verificar los incrementos y las dimensiones soportar y pedir listado de activos fijos con fechas de vencimiento
B85: 2 | C85: Soportar los 44
B86: 3 | C86: Falta poner referencia a los papeles de trabajo
A88: 114 | C88: falta papeles
B89: 1 | C89: Verificar los incrementos y las dimensiones soportar y pedir listado de activos fijos con fechas de vencimiento
B90: 2 | C90: Soportar los 13
B91: 3 | C91: Falta poner referencia a los papeles de trabajo
A93: 214 | B93: 1 | C93: verificar los pagos por desahucio
C94: *SALDO | D94: 43101 | E94: 0 | F94: 4486.35 | G94: -4486.35 | I94: Saldo inicial | J94: 202070201001 | K94: Desahucio por Pagar
C95: DB-800084 | D95: 43465 | E95: 0 | F95: 1939.89 | G95: -6426.24 | I95: REGISTRO PROVISION CALCULO ACTUARIAL POR DESAHUCIO 2018 | J95: 202070201001 | K95: Desahucio por Pagar
C96: DB-800085 | D96: 43465 | E96: 485.42 | F96: 0 | G96: -5940.82 | I96: POR REVERSIONES DE PASIVOS POR BENEFICIOS A LOS EMPLEADOS 2018 | J96: 202070201001 | K96: Desahucio por Pagar
C98: 202070201 | D98: DESAHUCIO | F98: 0 | H98: 0 | J98: 0 | O98: 0
C99: 202070201001 | D99: Desahucio por Pagar | F99: 4486.35 | H99: 5940.82 | J99: 5940.82 | O99: 5940.82
C101: 7058 | D101: 501020102008 | E101: Desahucio (MOD) | F101: 968.06
C102: 7058 | D102: 501030102008 | E102: Desahucio (MOI) | F102: 1854.82
C103: 7059 | D103: 503010103006 | E103: Desahucio Administración | F103: 221.91
G104: =SUM(F101:F103) -> 3044.79
G106: =+G94+G104 -> -1441.56
G107: =+G96-G106 -> -4499.26
G108: =+G107+G104 -> -1454.47
C110: COMERMAYCON
C111: ROSA
A112: 849 | C112: Recomendar que pago el 25% de impuesto a la renta por no declara lo de los socios
C115: ILUCIONCORP
A116: 800 | C116: no fueron declaradas como relacionas opercaiones en el 101 recomendar
C119: saltiel
A120: 800 | C120: confirma la parte relaciona
C122: kayalu
B123: 1 | C123: arreglar los archivos GENERAL ANALISIS Y LOS OTRAS ACIRDE AL MODELO
A124: 211
B125: 2 | C125: reconocimiento del largo plazo a corto plazo
C126: 2018 | D126: DICIEMBRE | E126: 47663.74
...

Sheet INFORME GERENTE 
F2: INFORME DE GERENTE
H4: Buena Fe, 18 de agosto de 2023
B6: A los señores Socios y Directiva de
B7: =+'6 INFORME BALANCES'!C9 -> TABACALERA MENHURSA S.A.
A9: ¿¿¿¿¿ | B9: En mi calidad de Gerente General y en cumplimiento a la función que se me asigna el numeral 4 del Art. 321 de la Ley de Compañías, cúmpleme informarles que he examinado el balance de la Compañía al 31 de Diciembre del 2022 y el correspondiente estado de resultados, los flujos de efectivo, el estado de evolución del patrimonio, que le es relativo por el año terminado en esa fecha.
B11: 1. Respecto a la ventas
A12: ¿¿¿¿ | B12: Un análisis de las tendencias de ventas es una revisión de las mediciones relacionadas con las ventas o indicadores claves de rendimiento durante un período de tiempo específico. El período puede ser a corto, mediano o largo plazo. Las tendencias en las ventas pueden subir, bajar o permanecer sin cambios como es el caso del los periodos analizados.
G14: =+'6 INFORME BALANCES'!H38 -> 45291 | H14: =+'6 INFORME BALANCES'!I38 -> 44926
C15: Ventas Gravadas con 0% | D15: Venta Netas | G15: =+'5 PG101'!L11 -> 0 | H15: =+'5 PG101'!D11 -> 1040371.6
B17: 2. Respecto al comparativo de la ganancia bruta antes de gastos
B18: Los indicadores sobre los ingreso netos nos dieron el siguiente resultado:
G20: =+G14 -> 45291 | H20: =+H14 -> 44926
D21: Ganancia bruta antes de gastos | G21: =+'6 INFORME BALANCES'!H115 -> 0 | H21: =+'6 INFORME BALANCES'!I115 -> 73889.818
B23: 3. Respecto al efectivo y sus equivalentes
B24: La empresa al cierre del ejercicio mostro los siguientes resultados:
G26: =+G14 -> 45291 | H26: =+H14 -> 44926
D27: Equivalente de efectivo | G27: =+'101'!M12 -> 0 | H27: =+'101'!D12 -> 21075.33
B29: 4. Respecto a la cartera por pagar
A30: ¿¿ | B30: Toda la cartera del periodo anterior fue recuperada y la cartera de este periodo se estima que los clientes que adeudan cancelara a mas tardar los primeros tres meses
G32: =+G26 -> 45291 | H32: =+H26 -> 44926
C33: Cuentas por pagar (Corrientes) | G33: =+'6 INFORME BALANCES'!H66 -> 0 | H33: =+'6 INFORME BALANCES'!I66 -> 502.05
C34: Cuentas por pagar (No Corrientes) | G34: =+'6 INFORME BALANCES'!H76 -> 0 | H34: =+'6 INFORME BALANCES'!I76 -> 815103.45
G35: =SUM(G33:G34) -> 0 | H35: =SUM(H33:H34) -> 815605.5
B39: 5. Respecto a la utilidad para trabajadores y accionistas
A40: ¿¿ | B40: La utilidad de este periodo, utilidad a trabajadores y el impuesto a la renta es como sigue aplicando la normativa tributaria permitida.
G41: =+G32 -> 45291 | H41: =+H32 -> 44926
C42: PARTICIPACIÓN A TRABAJADORES | G42: =+'5 PG101'!L44 -> 0 | H42: =+'5 PG101'!D44 -> 0
C43: IMPUESTO A LA RENTA | G43: =+'5 PG101'!L45 -> 0 | H43: =+'5 PG101'!D45 -> 0
C44: RESULTADOS DEL EJERCICIO | G44: =+'5 PG101'!L48 -> 0 | H44: =+'5 PG101'!D48 -> -24472.242
B46: 6. Información importante a revelar
A48: ¿¿¿ | B48: 6.1. Sobre el Cumplimiento de objetivos previstos para el ejercicio económico materia del informe. Las operaciones realizadas en el período reflejan el cumplimiento de los objetivos planteados por mi administración.
A50: ¿¿¿ | B50: Debo informar a la junta que se han cumplido con las disposiciones de la Junta General y el Directorio de la compañía durante el periodo de gestión. Las operaciones realizadas en el año 2022 reflejan el cumplimiento de objetivos interpuestos a la administración.
A52: ¿¿¿¿ | B52: 6.2. Sobre los hechos extraordinarios producidos durante el ejercicio, en el ámbito administrativo, laboral y legal: Con fecha 2020-09-18, recibí el nombramiento por dos años como gerente general y se nombró con misma fecha como presidente a MENDOZA PALMA ERWIN EDUARDO por dos años.
A54: ¿¿¿¿¿ | B54: 6.3. Sobre la Situación financiera de la compañía al cierre del ejercicio y de los resultados anuales, comparados con los del ejercicio precedente: Se presentan en los cuadros que anteceden a este informe y los correspondientes balances. Se utilizó en la conciliación tributaria la amortización de las pérdidas acumuladas de períodos anteriores que permitió bajar impuestos en el período.
A56: ¿¿¿¿ | B56: Recomendaciones a la junta general respecto de políticas y estrategias para el siguiente ejercicio económico: Con base a los resultados obtenidos y la leve recuperación del período se solicita a la junta apoyar la estrategia financiera que permita el crecimiento de la compañía.
A58: ¿¿¿ | B58: 6.4. Sobre el estado de cumplimiento de las normas sobre propiedad intelectual y derechos de autor por parte de la compañía: La compañía cumple con las normas de propiedad intelectual y derechos de autor.
B60: El gerente a la directiva
A61: ¿¿¿ | B61: Por lo expuesto someto a consideración la aprobación final del balance general de a, al 31 de Diciembre del 2022 y el correspondiente estado de resultados por el año terminado en esa fecha.
C65: …..........................................................
C66: =+'6 INFORME BALANCES'!L24 -> Sr. Eduardo Mendoza Hurtado
C67: =+'6 INFORME BALANCES'!L25 -> Gerente General

Sheet INF COMISARIO
B9: INFORME DE COMISARIO 2022
B11: =+'INFORME GERENTE '!B7 -> TABACALERA MENHURSA S.A.
B17: DIRIGIDO A: | E17: ACCIONISTAS Y JUNTA DIRECTIVA
B18: FECHA: | E18: Agosto 18 de 2023
B22: Elaborado por:
B27: ___________________________
B28: Ing. Maricela Geoconda Pilligua
B29: Comisario Principal
D45: Señores accionistas y Junta Directiva de
A46: ¿ | D46: =+B11 -> TABACALERA MENHURSA S.A.
D47: Buena Fe, Ecuador
A49: ¿¿ | B49: Pongo a su consideración el informe de Comisario por el año 2022, de acuerdo a los lineamientos y disposiciones legales:
B51: 1. ANTECEDENTES LEGALES
A52: ¿¿¿¿ | B52: * | C52: El Art. 274 establece que las compañías, de creer conveniente, podrán nombrar comisarios. Cuando por disposición estatutaria se hubiere acordado la existencia de comisarios, éstos se sujetarán a las disposiciones establecidas en esta Ley con relación a sus atribuciones, derechos y obligaciones. Caso contrario, las disposiciones de esta Ley relacionadas con los comisarios no tendrán aplicación.
A54: ¿¿¿ | B54: * | C54: Los comisarios, socios o no, designados si el estatuto social hubiere acordado su existencia, tienen derecho ilimitado de inspección y vigilancia sobre todas las operaciones sociales, sin dependencia de la administración y en interés de la compañía.
A56: ¿¿ | B56: * | C56: La resolución No. 92.1.4.3.0014 de la Superintendencia de Compañías establece el cumplimiento de los requisitos mínimos que deben contener los informes de Comisarios.
A58: ¿ | B58: * | C58: La Junta General de Accionistas designó como comisario principal a Maricela Geoconda Pilligua.
B60: 2. RESPONSABILIDAD DEL COMISARIO
A61: ¿¿¿¿ | C61: Mi responsabilidad es expresar una opinión sobre los estados financieros de la Compañía, basada en la revisión efectuada y, sobre el cumplimiento por parte de la Administración de las normas legales, estatutarias Y reglamentarias, así como de las resoluciones de la Junta General, y de las recomendaciones y autorizaciones de la Administración.
A63: ¿¿¿¿ | C63: Esta revisión fue efectuada siguiendo los lineamientos de las normas internacionales de auditoría, pruebas selectivas de los registros contables y evidencia que soporta los importes y revelaciones incluidos en los estados financiero, evaluación de control interno y otros procedimientos de revisión.
A65: ¿¿¿¿¿¿ | C65: He obtenido de los administradores, información de las operaciones, registros contables y documentación sustentadora de las transacciones Adicionalmente, he revisado el estado de situación financiera al 31 de diciembre del 2022 y el correspondiente estado de resultados por el año terminado en esa fecha, así como los libros sociales, las actas de Junta de Accionistas. Considero que los resultados de la revisión proveen bases apropiadas para expresar mi opinión.
B67: 3. CUMPLIMIENTO DE RESOLUCIONES
A68: ¿¿¿¿ | C68: El resultado de la revisión efectuada, a las transacciones registradas, los actos de los administradores, normas legales, estatutarias y reglamentarias, así como las resoluciones adoptadas por las Juntas de Accionistas, los libros de actas de Juntas de accionistas, libro de acciones y accionistas, se conservan de conformidad con disposiciones legales.
B70: 4. EVALUACIÓN DEL CONTROL INTERNO
A72: ¿¿¿¿ | C72: La evaluación del entorno, normas, procedimientos y políticas nos han permitido dirimir la razonabilidad de la operatividad de TABACALERA MENHURSA S.A., en tal virtud permite certificar que los procedimientos y controles implementados por la gerencia, protegen y salvaguardan la integridad económica de los activos, obligaciones y resultados de la compañía.
B74: 5. DISPOSICIONES CONSTANTES DE LA LEY.
A76: ¿¿¿¿ | C76: En Cumpliendo con lo que establece el Art 321 de la ley de compañías, la compañía TABACALERA MENHURSA S.A. informó en los plazos establecidos a la Superintendencia de Compañías, Valores y Seguros de la contratación de 3ANG ADMINISTRACION DE NEGOCIOS GERENCIALES CIA. LTDA. como auditores externos por el período 2022.
B78: 6. SOBRE LA SITUACIÓN FINANCIERA.
A80: ¿¿¿¿ | C80: En mi opinión, los estados financieros presentan razonablemente en todos los aspectos importantes, la situación financiera de TABACALERA MENHURSA S.A., al 31 de diciembre de 2022, de conformidad con las disposiciones de la Ley de Compañías y principios contables vigentes en el Ecuador.
C82: La composición del balance general del 2022 y 2021 es el siguiente:
G84: 44926 | H84: 44561
C86: Activos
C87: Activos corrientes:
C88: Efectivo | G88: =+'6 INFORME BALANCES'!H42 -> 0 | H88: =+'6 INFORME BALANCES'!I42 -> 21075.33
C89: Otros activos corrientes | G89: =+'6 INFORME BALANCES'!H44 -> 0 | H89: =+'6 INFORME BALANCES'!I44 -> 0
C90: Inventarios | G90: =+'6 INFORME BALANCES'!H45 -> 0 | H90: =+'6 INFORME BALANCES'!I45 -> 0
C92: Total activos corrientes | G92: =SUM(G88:G91) -> 0 | H92: =SUM(H88:H91) -> 21075.33
C94: Activos no corrientes:
C95: Propiedad, planta y equipo | G95: =+'6 INFORME BALANCES'!H51 -> 0 | H95: =+'6 INFORME BALANCES'!I51 -> 770873.64
C97: Total activos no corrientes | G97: =SUM(G95:G96) -> 0 | H97: =SUM(H95:H96) -> 770873.64
C98: Total Activos | G98: =+G92+G97 -> 0 | H98: =+H92+H97 -> 791948.97
C100: Pasivos y patrimonio de los accionistas
C101: Pasivos corrientes:
C102: Cuentas por pagar | G102: =+'6 INFORME BALANCES'!H66 -> 0 | H102: =+'6 INFORME BALANCES'!I66 -> 502.05
C103: Obligaciones financieras | G103: 0 | H103: 0
C105: Total pasivos corrientes | G105: =SUM(G102:G104) -> 0 | H105: =SUM(H102:H104) -> 502.05
C107: Cuentas por pagar | G107: =+'6 INFORME BALANCES'!H76 -> 0 | H107: =+'6 INFORME BALANCES'!I76 -> 815103.45
C109: Total pasivos corrientes no Corriente | G109: =SUM(G107:G108) -> 0 | H109: =SUM(H107:H108) -> 815103.45
C110: Total pasivos | G110: =+G105+G109 -> 0 | H110: =+H105+H109 -> 815605.5
C112: Patrimonio de los accionistas:
C113: Capital Suscrito asignado | G113: =+'6 INFORME BALANCES'!H88 -> 0 | H113: =+'6 INFORME BALANCES'!I88 -> 800
C114: Resultados Acumulados | G114: =+'6 INFORME BALANCES'!H91 -> 0 | H114: =+'6 INFORME BALANCES'!I91 -> -24456.53
C116: Total patrimonio de los accionistas | G116: =SUM(G113:G115) -> 0 | H116: =SUM(H113:H115) -> -23656.53
C118: Total pasivo mas patrimonio | G118: =+G110+G116 -> 0 | H118: =+H110+H116 -> 791948.97
G119: =+G98-G118 -> 0 | H119: =+H98-H118 -> -0.0019999997
B121: 6.1. ANÁLISIS DE LOS RESULTADOS OBTENIDOS | C121: La composición del estado de resultados del 2022 y 2021 es el siguiente:
G123: 44926 | H123: 44561
C125: Ventas Netas | G125: =+'6 INFORME BALANCES'!H112 -> 0 | H125: =+'6 INFORME BALANCES'!I112 -> 1040371.6
C126: Costo de ventas y producción | G126: =+'6 INFORME BALANCES'!H113 -> 0 | H126: =+'6 INFORME BALANCES'!I113 -> 966481.79
C128: Utilidad bruta en ventas | G128: =+G125-G126 -> 0 | H128: =+H125-H126 -> 73889.818
C130: Costos y gastos de administración | G130: =+'6 INFORME BALANCES'!H117 -> 0 | H130: =+'6 INFORME BALANCES'!I117 -> 98055.14
C131: Gastos de ventas | G131: =+'6 INFORME BALANCES'!H118 -> 0 | H131: =+'6 INFORME BALANCES'!I118 -> 0
C133: Utilidad (pérdida)en operación | G133: =+G128-G130-G131 -> 0 | H133: =+H128-H130-H131 -> -24165.322
C134: mas
C135: Otros ingresos | G135: 0 | H135: 0
C136: menos
C137: Gastos financieros, netos | G137: =+'6 INFORME BALANCES'!H126 -> 0 | H137: =+'6 INFORME BALANCES'!I126 -> 306.92
C139: Utilidad (pérdida) antes de participación a trabajadores e imp. Renta | G139: =+G133-G137 -> 0 | H139: =+H133-H137 -> -24472.242
C141: Participación a trabajadores | G141: 0 | H141: 0
C142: Impuesto a la renta | G142: 0 | H142: 0
C143: Fondo de reserva legal | G143: 0 | H143: 0
C145: Utilidad (pérdida) Neta | G145: =+G139-G141-G142-G143 -> 0 | H145: =+H139-H141-H142-H143 -> -24472.242
B148: 7 | C148: EL COMISARIO A LA COMPAÑÍA:
A150: ¿¿ | C150: En mi calidad de Comisario de la Compañía puedo concluir que su situación de acuerdo a los Estados Financieros se presenta de una forma consistente.
A152: ¿¿¿ | C152: Señores Accionistas declaro haber cumplido con la Resolución Nº 92.1.4.3.0014 de la Superintendencia de Compañías y demás artículos que me conciernen de acuerdo a la ley de compañías.
D159: =+B28 -> Ing. Maricela Geoconda Pilligua
D160: Comisario Principal
D161: =+E18 -> Agosto 18 de 2023

Sheet ACTA DE JNTA 2022
A1: ¿¿ | B1: ACTA DE LA JUNTA GENERAL EXTRAORDINARIA DE ACCIONISTAS DE LA COMPAÑIA TABACALERA MENHURSA S.A.
A3: ¿¿¿¿ | B3: En la provincia de Los Rios, a los dieciocho días del mes de agosto del dos mil veintitres, a las diez horas, en las oficinas de la compañía ubicadas en las calles Avenida 7 de agosto en la ciudad San Jacinto de Buena Fe, ciudadela Recinto Federico Intriago, comparece los siguientes accionistas de la compañía:
A5: ¿¿¿¿¿¿ | B5: Por un lado, MENDOZA HURTADO ANDREA KATHERINE, propietario de doscientas (200) acciones, por otro lado, MENDOZA HURTADO EDUARDO ISRAEL, propietario de doscientas (200) acciones, y MENDOZA PALMA ERWIN EDUARDO propietario de cuatrocientas (400) acciones. Todas las acciones son ordinarias y nominativas. pagadas en su totalidad. de un dólar de los Estados Unidos de América cada una, que en proporción a su valor pagado. dan derecho a igual número de votos.
A7: ¿¿¿¿ | B7: Preside la Junta, El señor MENDOZA PALMA ERWIN EDUARDO en calidad de Presidente, y en calidad de Secretario el Señor MENDOZA HURTADO EDUARDO ISRAEL y amparado en el Art. 238 de la Codificación a la Ley de Compañías acuerdan construirse en Junta General Extraordinaria de Accionistas, para conocer y resolver los siguientes puntos del orden del día:
B9: 1. Conocer y aprobar los estados financieros de la compañía, periodo 2022
B10: 2. Conocer y aprobar el Informe de Gerente, periodo 2022
B11: 3. Conocer y aprobar el Informe de Comisario, periodo 2022
B12: 4. Conocer y aprobar el Informe de Auditoria, periodo 2022
B13: 5. Conocer y resolver sobre el destino de los resultados del período 2022.
A15: ¿¿ | B15: Por secretaría se confirma la presencia del 100% del Capital Suscrito y Pagado y procede a dar lectura del primer punto: 1. Conocer y aprobar los estados financieros de la compañía, periodo 2022.
A17: ¿¿¿¿ | B17: Toma la palabra el presidente de la junta, quien manifiesta que el Estado de Situación Financiera, Estado de Resultados integrales, el Estado de Cambio en el Patrimonio, y el Estado de Flujo de Efectivo correspondientes al ejercicio económico del año 2022 se encuentra acorde a las Normas Internacional de Información Financieras NIIF, los accionistas han revisado los balances y aprueban por unanimidad.
A19: ¿¿¿¿ | B19: Se procede con el segundo punto del orden del día: 2. Conocer y aprobar el Informe de Gerente, periodo 2022, El Gerente Señor MENDOZA HURTADO EDUARDO ISRAEL, salva su voto debido a que es su gestion la que se pone en consideracion, toma la palabra el Señor MENDOZA PALMA ERWIN EDUARDO en calidad de Presidente y se procede aprobar la gestion del gerente.
A21: ¿¿¿ | B21: Se procede con el tercer punto del orden del día: 3. Conocer y aprobar el Informe de Comisario, periodo 2022. Para esto se da lectura al informe, la junta previamente recibió los informes y no tienen observaciones al mismo, y lo dan por aprobado.
A23: ¿¿¿¿ | B23: Se procede con el cuarto punto del orden del día: 4. Conocer y aprobar el Informe de Auditoria, periodo 2022 por parte de la compañía auditora 3ANG Administracion de Negocios Gerenciales Cia. Ltda.. Se procede a dar lectura del Informe de Auditoria, la junta previamente recibió los informes y no tienen observaciones al mismo lo dan por aprobado.
A25: ¿¿¿ | B25: Se procede con el quinto punto del orden del día: 5. Conocer y resolver sobre el destino de las perdidas del período 2022. La junta resuelve por unanimidad de todos los votos válidos, acumular las perdidas del presente año.
A27: ¿¿¿ | B27: Concluida la Junta General Extraordinaria de Accionistas y no habiendo puntos más que tratar, de conformidad con el Art. 238 de la Ley de Compañías, se concede un receso de 15 minutos para la redacción del acta. Para constancia firman:
B34: …............................................ | F34: ................................................
B35: Mendoza Palma Erwin E. | F35: Mendoza Hurtado Eduardo I.
B36: Presidente / Accionista | F36: Secretario / Accionista
D43: …............................................
D44: Mendoza Hurtado Andrea K.
D45: Accionista

Sheet 29 INDEPENDENCIA EQ
C5: CERTIFICACIÓN JURAMENTADA
C9: INDEPENDENCIA DEL EQUIPO DE AUDITORÍA
C11: AUDITORIA A LOS ESTADOS FINANCIEROS POR EL PERIODO 2023 DE LA COMPAÑÍA.
C13: TABACALERA MENHURSA S.A.
C17: 3 A.N.G ADMINISTRACION DE NEGOCIOS GERENCIALES CIA. LTDA., CERTIFICA BAJO JURAMENTO que el equipo de auditoría participante y el suscriptor del informe, no se encuentran incursos en ninguna de las prohibiciones establecidas en el artículo 197 de la Ley de Mercado de Valores y los artículos 328, 329 de la ley de compañías .
C22: 3ANG Administración de Negocios Gerenciales. Cía. Ltda.
C23: Registro Nacional de Auditores Externos
C24: SC – RNAE-662
C25: Econ. Roy Cisneros Mejía
C26: SOCIO

Sheet 28 Certif del equipo (2)
C10: CERTIFICADO
A18: ¿¿¿¿ | C18: Por medio de la presente hago constar que la compañía 3 A.N.G ADMINISTRACION DE NEGOCIOS GERENCIALES CIA. LTDA. Con Ruc 0992541504001, fue nuestro auditor externo en el año 2023. En la que participaron las siguientes Personas:
C21: Econ Roy Cisneros Mejía.
C22: Ing. Maria Elizabeth Palacios
C25: Cumpliendo satisfactoriamente con sus compromisos.
C28: Constancia que expido a solicitud de la parte interesada. Por requerimientos de la Superintendencia de Compañias, Valores y Seguros.
C29: =+'OPINION pymes con anexo '!I72 -> Agosto, 18 del 2023
C35: _________________________________________
C36: =+'6 INFORME BALANCES'!L24 -> Sr. Eduardo Mendoza Hurtado
C37: =+'6 INFORME BALANCES'!L25 -> Gerente General

Sheet 27CAPI V
C5: INFORME DE AUDITORÍA Y ANEXOS
C9: TABACALERA MENHURSA S.A.
C15: V
C21: CERTIFICACIONES JURAMENTADAS

Sheet 26CARTA DE REPRESENN
C2: TABACALERA MENHURSA S.A.
C4: R.U.C.No. 1291784468001
C6: Señores :
C7: 3 A.N.G. ADMINISTRACION DE NEGOCIOS GERENCIALES CIA. LTDA.
A9: ¿¿¿¿¿¿¿¿¿¿¿ | C9: Esta carta de representación se provee en relación con sus auditorías de los estados financieros de la compañía TABACALERA MENHURSA S.A., los cuales comprenden los balances generales al 31 de diciembre de 2023 y los correspondientes estados de resultados, cambios en el patrimonio, flujos de efectivo y las notas a los estados financieros por los años terminados en esas fechas, cuyo examen se efectuó con el propósito de expresar una opinión sobre si dichos estados financieros presentan razonablemente, en todos los aspectos de importancia material, la situación financiera de la compañía TABACALERA MENHURSA S.A., los resultados de sus operaciones y sus flujos de efectivo de acuerdo con normas internacionales de contabilidad y las normas de información financiera generalmente aceptados en Ecuador y si dichos principios fueron aplicados de manera uniforme.
A11: ¿¿¿¿¿¿¿¿¿¿¿ | C11: Reconocemos que estos estados financieros, preparados y presentados de acuerdo con principios de contabilidad generalmente aceptados en Ecuador, son de nuestra responsabilidad y previamente a su emisión nos hemos cerciorado del cumplimiento satisfactorio de las afirmaciones explícitas e implícitas contenidas en los mismos(integridad, existencia, exactitud, derechos y obligaciones, valuación y presentación y revelación de los hechos económicos), por lo que aprobamos estos estados financieros. Igualmente, reconocemos que esta responsabilidad incluye: diseñar, implementar y mantener el control interno relevante para preparación y presentación de estados financieros libres de errores de importancia material, bien sea por fraude o error; seleccionar y aplicar políticas contables apropiadas, así como establecer estimados contables que sean razonables en las circunstancias.
A13: ¿¿¿¿¿¿¿ | C13: Declaro que la información financiera bajo las Normas Internacionales de Información Financiera NIIF presentada a ustedes como auditores externos., revela todas las transacciones económicas realizadas por la compañía que yo represento en el periodo 2023 y me declaro responsable como representante legal de la compañía respecto a la veracidad de la información incorporada en los estados financieros referidos al ejercicio terminado al 31 de diciembre de 2023, de acuerdo al siguiente detalle.
D15: - | E15: Estado de Situación Financiera
D16: - | E16: Estado de Resultado Integral
D17: - | E17: Estado de Cambios en el Patrimonio
D18: - | E18: Estado de Flujo de Efectivo
D19: - | E19: Políticas Contables
D20: - | E20: Notas Explicativas a los Estados Financieros
A22: ¿¿ | C22: Así también informar a ustedes que los mayores contables que respaldan los estados financieros antes mencionados son confiables, verificables y reposan en nuestros archivos.
A24: ¿¿¿¿ | C24: Hemos efectuado las debidas indagaciones con los directores y funcionarios de la compañía que tienen los conocimientos y la experiencia relevantes. Por lo tanto, confirmamos, a nuestro leal saber y entender, las siguientes representaciones efectuadas a ustedes durante el desarrollo de su trabajo:
A26: ¿¿¿¿ | C26: 1. Hemos cumplido nuestras responsabilidades, de conformidad con los términos del contrato de prestación de servicios , en relación con la preparación y presentación de los estados financieros, de acuerdo con principios de contabilidad generalmente aceptados en Ecuador y la Superintendencia de Compañías
A28: ¿¿ | C28: 2. Los métodos de medición y los supuestos significativos que se utilizaron para establecer estimaciones contables, son apropiados.
A30: ¿¿¿ | C30: 3. No hay eventos posteriores a los estados financieros que requieran ajustes o revelación en notas, de conformidad con los principios de contabilidad generalmente aceptados en Ecuador.
A32: pp | C32: 4. Los efectos de los errores no corregidos son inmateriales, individualmente y agregados, a los estados financieros en su conjunto.
A34: pp | C34: 5. Le hemos dado acceso a toda la información relevante para la preparación de los estados financieros, tales como los registros contables y documentación de respaldo.
A36: pp | C36: 6. Hemos proporcionados todas las actas de las reuniones de Accionistas y de la Junta Directiva, se ha entregado a ustedes para su verificación.
A38: ¿¿¿ | C38: 7. Hemos proporcionado toda la información adicional que ustedes nos han solicitado para el propósito de su auditoría, y acceso sin restricciones a las personas de la Compañía de las cuales ustedes determinaron necesario obtener evidencia de auditoría.
A40: ¿¿¿ | C40: 8. Hemos proporcionado toda la información relacionada a controversias judiciales que afecten a la empresa para el propósito de su auditoría con el acceso sin restricciones a las cuales ustedes determinaron necesario obtener evidencia de auditoría.
C47: ________________________________________ | H47: ________________________________________
C48: =+'6 INFORME BALANCES'!L24 -> Sr. Eduardo Mendoza Hurtado | H48: =+'6 INFORME BALANCES'!L28 -> Sr. Alfonso Solorzano Moncada
C49: =+'6 INFORME BALANCES'!L25 -> Gerente General | H49: =+'6 INFORME BALANCES'!L29 -> Contador

Sheet 25CAPI IV
C4: INFORME DE AUDITORÍA Y ANEXOS
C8: TABACALERA MENHURSA S.A.
C14: IV
C20: CARTA DE REPRESENTACIÓN

Sheet 24CAPI III
C3: INFORME DE AUDITORÍA Y ANEXOS
C7: =+'23CAPI II'!C9 -> TABACALERA MENHURSA S.A.
C13: III
C19: COMUNICACIÓN DE DEFICIENCIAS DE CONTROL INTERNO

Sheet 23CAPI II
C4: INFORME DE AUDITORÍA Y ANEXOS
C9: =+'22CAPI I'!C10 -> TABACALERA MENHURSA S.A.
C14: I I
C19: INFORME DE LOS AUDITORES INDEPENDIENTES

Sheet 22CAPI  I
C5: INFORME DE AUDITORÍA Y ANEXOS
C10: =+'8 CONCILIA DEL PATRIMONIO'!B2 -> TABACALERA MENHURSA S.A.
C17: I
C23: ACTA DE ENTREGA
C29: =+'6 INFORME BALANCES'!L24 -> Sr. Eduardo Mendoza Hurtado
C30: GERENTE GENERAL
A34: ¿¿¿ | C34: Por medio del presente y una vez aprobado el borrador, estamos haciendo entrega de dos ejemplares del Informe de Auditoría Externa, y la Comunicación de Deficiencias de Control Interno, correspondiente al período auditado 2023, para que sean firmados por ustedes.
A37: ¿¿ | C37: Por favor, nuestro ejemplar procederemos a retirar cuando ustedes nos indiquen.
A40: ¿¿ | C40: Reiteramos nuestro agradecimiento por la confianza depositada.
C44: ---------------------------------------------
C45: Econ. Roy Cisneros Mejia
C46: Gerente
C50: ---------------------------------------------
C51: Recibido por
C52: =+'6 INFORME BALANCES'!L28 -> Sr. Alfonso Solorzano Moncada
A54: ¿¿¿ | C54: Con fecha ______/______/_______estamos entregando a ustedes sus originales firmados para que sigan con los procedimientos ante la Superintendencia de Compañias, Valores y Seguros.

Sheet 2 BL preli

Sheet 101 anterior
S1: Valor no deducible
A2: FORMULARIO RENTA SOCIEDADES
A4: OPERACIONES CON PARTES RELACIONADAS LOCALES Y/O DEL EXTERIOR
B5: CON PARTES RELACIONADAS LOCALES
C6: Operaciones de activo | N6: 3 | O6: 1 BL anterior=SUMAR.SI('1 BL anterior'!A:A;N6;'1 BL anterior'!E:E)
C7: Operaciones de pasivo | N7: 4 | O7: =SUMIF('1 BL anterior'!A:A,N7,'1 BL anterior'!E:E) -> 0 | AC7: =+O7-AA7-AB7 -> 0
C8: Operaciones de ingreso | N8: 5 | O8: =SUMIF('1 BL anterior'!A:A,N8,'1 BL anterior'!E:E) -> 0 | AC8: =+O8-AA8-AB8 -> 0
C9: Operaciones de egreso | N9: 6 | O9: =SUMIF('1 BL anterior'!A:A,N9,'1 BL anterior'!E:E) -> 0 | AC9: =+O9-AA9-AB9 -> 0
C10: Operaciones de regalías, servicios técnicos, administrativos, de consultoría y similares | N10: 7 | O10: =SUMIF('1 BL anterior'!A:A,N10,'1 BL anterior'!E:E) -> 0 | AC10: =+O10-AA10-AB10 -> 0
B11: CON PARTES RELACIONADAS EN PARAÍSOS FISCALES, JURISDICCIONES DE MENOR IMPOSICIÓN Y RÉGIMENES FISCALES PREFERENTES | AC11: =+O11-AA11-AB11 -> 0
C12: Operaciones de activo | N12: 8 | O12: =SUMIF('1 BL anterior'!A:A,N12,'1 BL anterior'!E:E) -> 0 | AC12: =+O12-AA12-AB12 -> 0
C13: Operaciones de pasivo | N13: 9 | O13: =SUMIF('1 BL anterior'!A:A,N13,'1 BL anterior'!E:E) -> 0 | AC13: =+O13-AA13-AB13 -> 0
C14: Operaciones de ingreso | N14: 10 | O14: =SUMIF('1 BL anterior'!A:A,N14,'1 BL anterior'!E:E) -> 0 | AC14: =+O14-AA14-AB14 -> 0
C15: Operaciones de egreso | N15: 11 | O15: =SUMIF('1 BL anterior'!A:A,N15,'1 BL anterior'!E:E) -> 0 | AC15: =+O15-AA15-AB15 -> 0
C16: Operaciones de regalías, servicios técnicos, administrativos, de consultoría y similares | N16: 12 | O16: =SUMIF('1 BL anterior'!A:A,N16,'1 BL anterior'!E:E) -> 0 | AC16: =+O16-AA16-AB16 -> 0
B17: CON PARTES RELACIONADAS EN OTRAS JURISDICCIONES O RÉGIMENES DEL EXTERIOR | AC17: =+O17-AA17-AB17 -> 0
C18: Operaciones de activo | N18: 13 | O18: =SUMIF('1 BL anterior'!A:A,N18,'1 BL anterior'!E:E) -> 0 | AC18: =+O18-AA18-AB18 -> 0
C19: Operaciones de pasivo | N19: 14 | O19: =SUMIF('1 BL anterior'!A:A,N19,'1 BL anterior'!E:E) -> 0 | AC19: =+O19-AA19-AB19 -> 0
C20: Operaciones de ingreso | N20: 15 | O20: =SUMIF('1 BL anterior'!A:A,N20,'1 BL anterior'!E:E) -> 0 | AC20: =+O20-AA20-AB20 -> 0
C21: Operaciones de egreso | N21: 16 | O21: =SUMIF('1 BL anterior'!A:A,N21,'1 BL anterior'!E:E) -> 0 | AC21: =+O21-AA21-AB21 -> 0
C22: Operaciones de regalías, servicios técnicos, administrativos, de consultoría y similares | N22: 17 | O22: =SUMIF('1 BL anterior'!A:A,N22,'1 BL anterior'!E:E) -> 0 | AC22: =+O22-AA22-AB22 -> 0
B23: TOTAL OPERACIONES CON PARTES RELACIONADAS | N23: 029 | AC23: =+O23-AA23-AB23 -> 0
B24: ¿Sujeto pasivo exento de aplicación del régimen de precios de transferencia? | N24: 30 | O24: =SUMIF('1 BL anterior'!A:A,N24,'1 BL anterior'!E:E) -> 0 | AC24: =+O24-AA24-AB24 -> 0
A25: ESTADO DE SITUACIÓN FINANCIERA | AC25: =+O25-AA25-AB25 -> 0
B26: ACTIVO | AC26: =+O26-AA26-AB26 -> 0
C27: ACTIVOS CORRIENTES | AC27: =+O27-AA27-AB27 -> 0
D28: Efectivo y equivalentes al efectivo | N28: 311 | O28: =SUMIF('1 BL anterior'!B:B,N28,'1 BL anterior'!E:E) -> 21075.33 | AB28: 4632.67 | AC28: =+O28-AA28-AB28 -> 16442.66
D29: CUENTAS Y DOCUMENTOS POR COBRAR CORRIENTES | AC29: =+O29-AA29-AB29 -> 0
E30: CUENTAS Y DOCUMENTOS POR COBRAR COMERCIALES CORRIENTES | AC30: =+O30-AA30-AB30 -> 0
F31: RELACIONADAS | AC31: =+O31-AA31-AB31 -> 0
A32: ______ | B32: ______ | C32: ______ | D32: ______ | E32: ______ | F32: ______ | G32: Locales | N32: 312 | O32: =SUMIF('1 BL anterior'!B:B,N32,'1 BL anterior'!E:E) -> 0 | AC32: =+O32-AA32-AB32 -> 0
G33: Del exterior | N33: 313 | O33: =SUMIF('1 BL anterior'!B:B,N33,'1 BL anterior'!E:E) -> 0 | AC33: =+O33-AA33-AB33 -> 0
G34: (-) Deterioro acumulado del valor de cuentas y documentos por cobrar comerciales por incobrabilidad (provisiones para créditos incobrables) | N34: 314 | O34: =SUMIF('1 BL anterior'!B:B,N34,'1 BL anterior'!E:E) -> 0 | AC34: =+O34-AA34-AB34 -> 0
F35: NO RELACIONADAS | AC35: =+O35-AA35-AB35 -> 0
G36: Locales | N36: 315 | O36: =SUMIF('1 BL anterior'!B:B,N36,'1 BL anterior'!E:E) -> 0 | AC36: =+O36-AA36-AB36 -> 0
G37: Del exterior | N37: 316 | O37: =SUMIF('1 BL anterior'!B:B,N37,'1 BL anterior'!E:E) -> 0 | AC37: =+O37-AA37-AB37 -> 0
G38: (-) Deterioro acumulado del valor de cuentas y documentos por cobrar comerciales por incobrabilidad (provisiones para créditos incobrables) | N38: 317 | O38: =SUMIF('1 BL anterior'!B:B,N38,'1 BL anterior'!E:E) -> 0 | Q38: exceder del 10% de la cartera total. | R38: .- Las provisiones para créditos incobrables originados en operaciones del giro ordinario del negocio, efectuadas en cada ejercicio impositivo a razón del 1% anual sobre los créditos comerciales concedidos en dicho ejercicio y que se encuentren pendientes de recaudación al cierre del mismo, sin que la provisión acumulada pueda exceder del 10% de la cartera total. | AC38: =+O38-AA38-AB38 -> 0
E39: OTRAS CUENTAS Y DOCUMENTOS POR COBRAR CORRIENTES | AC39: =+O39-AA39-AB39 -> 0
F40: A ACCIONISTAS, SOCIOS, PARTICIPES, BENEFICIARIOS U OTROS TITULARES DE DERECHOS REPRESENTATIVOS DE CAPITAL | AC40: =+O40-AA40-AB40 -> 0
G41: Locales | N41: 318 | O41: =SUMIF('1 BL anterior'!B:B,N41,'1 BL anterior'!E:E) -> 0 | AC41: =+O41-AA41-AB41 -> 0
G42: Del exterior | N42: 319 | O42: =SUMIF('1 BL anterior'!B:B,N42,'1 BL anterior'!E:E) -> 0 | AC42: =+O42-AA42-AB42 -> 0
F43: DIVIDENDOS POR COBRAR | AC43: =+O43-AA43-AB43 -> 0
G44: En efectivo | N44: 320 | O44: =SUMIF('1 BL anterior'!B:B,N44,'1 BL anterior'!E:E) -> 0 | AC44: =+O44-AA44-AB44 -> 0
G45: En activos diferentes del efectivo | N45: 321 | O45: =SUMIF('1 BL anterior'!B:B,N45,'1 BL anterior'!E:E) -> 0 | AC45: =+O45-AA45-AB45 -> 0
F46: OTRAS RELACIONADAS | AC46: =+O46-AA46-AB46 -> 0
G47: Locales | N47: 322 | O47: =SUMIF('1 BL anterior'!B:B,N47,'1 BL anterior'!E:E) -> 0 | AC47: =+O47-AA47-AB47 -> 0
G48: Del exterior | N48: 323 | O48: =SUMIF('1 BL anterior'!B:B,N48,'1 BL anterior'!E:E) -> 0 | AC48: =+O48-AA48-AB48 -> 0
G49: (-) Deterioro acumulado del valor de otras cuentas y documentos por cobrar por incobrabilidad (provisiones para créditos incobrables) | N49: 324 | O49: =SUMIF('1 BL anterior'!B:B,N49,'1 BL anterior'!E:E) -> 0 | AC49: =+O49-AA49-AB49 -> 0
F50: OTRAS NO RELACIONADAS | AC50: =+O50-AA50-AB50 -> 0
G51: Locales | N51: 325 | O51: =SUMIF('1 BL anterior'!B:B,N51,'1 BL anterior'!E:E) -> 0 | AC51: =+O51-AA51-AB51 -> 0
G52: Del exterior | N52: 326 | O52: =SUMIF('1 BL anterior'!B:B,N52,'1 BL anterior'!E:E) -> 0 | AC52: =+O52-AA52-AB52 -> 0
G53: (-) Deterioro acumulado del valor de otras cuentas y documentos por cobrar por incobrabilidad (provisiones para créditos incobrables) | N53: 327 | O53: =SUMIF('1 BL anterior'!B:B,N53,'1 BL anterior'!E:E) -> 0 | AC53: =+O53-AA53-AB53 -> 0
D54: OTROS ACTIVOS FINANCIEROS CORRIENTES | AC54: =+O54-AA54-AB54 -> 0
E55: A costo amortizado | N55: 328 | O55: =SUMIF('1 BL anterior'!B:B,N55,'1 BL anterior'!E:E) -> 0 | AC55: =+O55-AA55-AB55 -> 0
E56: (-) Deterioro acumulado del valor de otros activos financieros corrientes medidos a costo amortizado (provisiones para créditos incobrables) | N56: 329 | O56: =SUMIF('1 BL anterior'!B:B,N56,'1 BL anterior'!E:E) -> 0 | AC56: =+O56-AA56-AB56 -> 0
E57: A valor razonable | N57: 330 | O57: =SUMIF('1 BL anterior'!B:B,N57,'1 BL anterior'!E:E) -> 0 | AC57: =+O57-AA57-AB57 -> 0
D58: PORCIÓN CORRIENTE DE ARRENDAMIENTOS FINANCIEROS POR COBRAR | AC58: =+O58-AA58-AB58 -> 0
E59: Relacionadas | N59: 331 | O59: =SUMIF('1 BL anterior'!B:B,N59,'1 BL anterior'!E:E) -> 0 | AC59: =+O59-AA59-AB59 -> 0
E60: No relacionadas | N60: 332 | O60: =SUMIF('1 BL anterior'!B:B,N60,'1 BL anterior'!E:E) -> 0 | AC60: =+O60-AA60-AB60 -> 0
D61: IMPORTE BRUTO ADEUDADO POR LOS CLIENTES POR EL TRABAJO EJECUTADO EN CONTRATOS DE CONSTRUCCIÓN | AC61: =+O61-AA61-AB61 -> 0
E62: Relacionadas | N62: 333 | O62: =SUMIF('1 BL anterior'!B:B,N62,'1 BL anterior'!E:E) -> 0 | AC62: =+O62-AA62-AB62 -> 0
E63: No relacionadas | N63: 334 | O63: =SUMIF('1 BL anterior'!B:B,N63,'1 BL anterior'!E:E) -> 0 | AC63: =+O63-AA63-AB63 -> 0
D64: ACTIVOS POR IMPUESTOS CORRIENTES | AC64: =+O64-AA64-AB64 -> 0
E65: Crédito tributario a favor del sujeto pasivo (ISD) | N65: 335 | O65: =SUMIF('1 BL anterior'!B:B,N65,'1 BL anterior'!E:E) -> 0 | AC65: =+O65-AA65-AB65 -> 0
E66: Crédito tributario a favor del sujeto pasivo (IVA) | N66: 336 | O66: =SUMIF('1 BL anterior'!B:B,N66,'1 BL anterior'!E:E) -> 0 | AC66: =+O66-AA66-AB66 -> 0
E67: Crédito tributario a favor del sujeto pasivo (Impuesto a la Renta) | N67: 337 | O67: =SUMIF('1 BL anterior'!B:B,N67,'1 BL anterior'!E:E) -> 0 | AC67: =+O67-AA67-AB67 -> 0
E68: Otros | N68: 338 | O68: =SUMIF('1 BL anterior'!B:B,N68,'1 BL anterior'!E:E) -> 0 | AC68: =+O68-AA68-AB68 -> 0
D69: INVENTARIOS | AC69: =+O69-AA69-AB69 -> 0
E70: Mercaderías en tránsito | N70: 339 | O70: =SUMIF('1 BL anterior'!B:B,N70,'1 BL anterior'!E:E) -> 0 | AC70: =+O70-AA70-AB70 -> 0
E71: Inventario de materia prima (no para la construcción) | N71: 340 | O71: =SUMIF('1 BL anterior'!B:B,N71,'1 BL anterior'!E:E) -> 0 | AC71: =+O71-AA71-AB71 -> 0
E72: Inventario de productos en proceso (excluyendo obras/inmuebles en construcción para la venta) | N72: 341 | O72: =SUMIF('1 BL anterior'!B:B,N72,'1 BL anterior'!E:E) -> 0 | AB72: 281088.75 | AC72: =+O72-AA72-AB72 -> -281088.75
E73: Inventario de prod. term. y mercad. en almacén (excluyendo obras/inmuebles terminados para la venta) | N73: 342 | O73: =SUMIF('1 BL anterior'!B:B,N73,'1 BL anterior'!E:E) -> 0 | AC73: =+O73-AA73-AB73 -> 0
E74: Inventario de suministros, herramientas, repuestos y materiales (no para la construcción) | N74: 343 | O74: =SUMIF('1 BL anterior'!B:B,N74,'1 BL anterior'!E:E) -> 0 | AC74: =+O74-AA74-AB74 -> 0
E75: Inventario de materia prima, suministros y materiales para la construcción | N75: 344 | O75: =SUMIF('1 BL anterior'!B:B,N75,'1 BL anterior'!E:E) -> 0 | AC75: =+O75-AA75-AB75 -> 0
E76: Inventario de obras/inmuebles en construcción para la venta | N76: 345 | O76: =SUMIF('1 BL anterior'!B:B,N76,'1 BL anterior'!E:E) -> 0 | AC76: =+O76-AA76-AB76 -> 0
E77: Inventario de obras/inmuebles terminados para la venta | N77: 346 | O77: =SUMIF('1 BL anterior'!B:B,N77,'1 BL anterior'!E:E) -> 0 | AC77: =+O77-AA77-AB77 -> 0
E78: (-) Deterioro acumulado del valor de inventarios por ajuste al valor neto realizable | N78: 347 | O78: =SUMIF('1 BL anterior'!B:B,N78,'1 BL anterior'!E:E) -> 0 | AC78: =+O78-AA78-AB78 -> 0
D79: ACTIVOS NO CORRIENTES MANTENIDOS PARA LA VENTA | AC79: =+O79-AA79-AB79 -> 0
E80: Costo | N80: 348 | O80: =SUMIF('1 BL anterior'!B:B,N80,'1 BL anterior'!E:E) -> 0 | AC80: =+O80-AA80-AB80 -> 0
E81: (-) Deterioro acumulado del valor de activos no corrientes mantenidos para la venta | N81: 349 | O81: =SUMIF('1 BL anterior'!B:B,N81,'1 BL anterior'!E:E) -> 0 | AC81: =+O81-AA81-AB81 -> 0
D82: ACTIVOS BIOLÓGICOS | AC82: =+O82-AA82-AB82 -> 0
E83: PLANTAS VIVAS Y FRUTOS EN CRECIMIENTO | AC83: =+O83-AA83-AB83 -> 0
F84: A costo | N84: 350 | O84: =SUMIF('1 BL anterior'!B:B,N84,'1 BL anterior'!E:E) -> 0 | AC84: =+O84-AA84-AB84 -> 0
F85: (-) Deterioro acumulado del valor de activos biológicos medidos a costo | N85: 351 | O85: =SUMIF('1 BL anterior'!B:B,N85,'1 BL anterior'!E:E) -> 0 | AC85: =+O85-AA85-AB85 -> 0
F86: A valor razonable menos los costos de venta | N86: 352 | O86: =SUMIF('1 BL anterior'!B:B,N86,'1 BL anterior'!E:E) -> 0 | AC86: =+O86-AA86-AB86 -> 0
E87: ANIMALES VIVOS | AC87: =+O87-AA87-AB87 -> 0
F88: A costo | N88: 353 | O88: =SUMIF('1 BL anterior'!B:B,N88,'1 BL anterior'!E:E) -> 0 | AC88: =+O88-AA88-AB88 -> 0
F89: (-) Deterioro acumulado del valor de activos biológicos medidos a costo | N89: 354 | O89: =SUMIF('1 BL anterior'!B:B,N89,'1 BL anterior'!E:E) -> 0 | AC89: =+O89-AA89-AB89 -> 0
F90: A valor razonable menos los costos de venta | N90: 355 | O90: =SUMIF('1 BL anterior'!B:B,N90,'1 BL anterior'!E:E) -> 0 | AC90: =+O90-AA90-AB90 -> 0
D91: GASTOS PAGADOS POR ANTICIPADO (PREPAGADOS) | AC91: =+O91-AA91-AB91 -> 0
E92: Propaganda y publicidad prepagada | N92: 356 | O92: =SUMIF('1 BL anterior'!B:B,N92,'1 BL anterior'!E:E) -> 0 | AC92: =+O92-AA92-AB92 -> 0
E93: Arrendamientos operativos pagados por anticipado | N93: 357 | O93: =SUMIF('1 BL anterior'!B:B,N93,'1 BL anterior'!E:E) -> 0 | AC93: =+O93-AA93-AB93 -> 0
E94: Primas de seguro pagadas por anticipado | N94: 358 | O94: =SUMIF('1 BL anterior'!B:B,N94,'1 BL anterior'!E:E) -> 0 | AC94: =+O94-AA94-AB94 -> 0
E95: Otros | N95: 359 | O95: =SUMIF('1 BL anterior'!B:B,N95,'1 BL anterior'!E:E) -> 0 | AC95: =+O95-AA95-AB95 -> 0
D96: Otros Activos Corrientes | N96: 360 | O96: =SUMIF('1 BL anterior'!B:B,N96,'1 BL anterior'!E:E) -> 0 | Q96: según blance | R96: dife | AC96: =+O96-AA96-AB96 -> 0
C97: TOTAL ACTIVOS CORRIENTES | N97: 361 | O97: =SUM(O28:O96) -> 21075.33 | P97: =+'6 INFORME BALANCES'!I48 -> 21075.33 | AB97: 285721.42 | AC97: =+O97-AA97-AB97 -> -264646.09
C98: ACTIVOS NO CORRIENTES | AC98: =+O98-AA98-AB98 -> 0
D99: PROPIEDADES, PLANTA Y EQUIPO | AC99: =+O99-AA99-AB99 -> 0
E100: TERRENOS | AC100: =+O100-AA100-AB100 -> 0
F101: Costo histórico antes de reexpresiones o revaluaciones | N101: 362 | O101: =SUMIF('1 BL anterior'!B:B,N101,'1 BL anterior'!E:E) -> 0 | AC101: =+O101-AA101-AB101 -> 0
...

Sheet costo de ventas
A4: TABACALERA MENHURSA S.A.
A5: 44197 | D5: 12239.48 | H5: 1.1.3.1.4.1.01 | I5: Bodega principal 12 | L5: 251732.44 | M5: 256365.11
A6: 44197 | H6: 1.1.3.3.1.1.01 | I6: Productos quimicos | L6: 168.56 | M6: 256533.67
A7: 44197 | H7: 1.1.3.3.1.1.02 | I7: GLP industrial | L7: 21883.36 | M7: 278417.03
A8: 44197 | H8: 1.1.3.3.1.1.04 | I8: Suministros de Oficina Inventario Cultivo | L8: 26.95 | M8: 278443.98
A9: 44197 | H9: 1.1.3.3.1.1.17 | I9: Construcciones | L9: 450 | M9: 278893.98
A10: 44197 | H10: 1.1.3.3.1.1.18 | I10: Hilos para proceso de tabaco | L10: 625.11 | M10: 279519.09
A11: 44197 | H11: 1.1.3.3.1.1.19 | I11: Insumos agrcolas | L11: 49.14 | M11: 279568.23
A12: 44197 | H12: 1.1.3.3.1.1.21 | I12: Mant de equipos de riego | L12: 223.21 | M12: 279791.44
A13: 44197 | H13: 1.1.3.3.1.1.26 | I13: Materiales de construccin | L13: 664.29 | M13: 280455.73
A14: 44197 | H14: 1.1.3.3.1.1.27 | I14: Materiales de ferretera | L14: 264.76 | M14: 280720.49
A15: 44197 | H15: 1.1.3.3.1.1.28 | I15: Materiales de riego | L15: 120.62 | M15: 280841.11
A16: 44197 | H16: 1.1.3.3.1.1.29 | I16: Materiales para proceso de tabaco | L16: 3136.96 | M16: 283978.07
A17: 44197 | H17: 1.1.3.3.1.1.37 | I17: Intereses y comisiones bancarias | L17: 8.82 | M17: 283986.89
A18: 44197 | H18: 1.1.3.3.1.1.39 | I18: Suministro materiales y otros | L18: 1068.37 | M18: 285055.26
A19: 44197 | H19: 1.1.5.1.01 | I19: Iva sobre compras | J19: 666.16 | L19: 666.16 | M19: 285721.42
A20: 44197 | C20: COMPRA | D20: COMPRA GYS. | E20: 001002000003348 | F20: COM-92 | G20: 0000000103 | H20: 1.1.3.3.1.1.04 | I20: Suministros de Oficina Inventario Cultivo | J20: 4579.3 | K20: 0 | L20: 4579.3 | M20: 4579.3
A21: 44197 | C21: COMPRA | D21: COMPRA GYS. | E21: 001002000003348 | F21: COM-92 | G21: 0000000103 | H21: 1.1.5.1.01 | I21: Iva sobre compras | J21: 549.52 | K21: 0 | L21: 549.52 | M21: 5128.82
A22: 44202 | C22: COMPRA | D22: COMPRA GYS. | E22: 011003012087633 | F22: COM-91 | G22: 0000000102 | H22: 1.1.3.3.1.1.02 | I22: GLP industrial | J22: 3079.57 | K22: 0 | L22: 3079.57 | M22: 3079.57
A23: 44202 | C23: COMPRA | D23: COMPRA GYS. | E23: 011003012087633 | F23: COM-91 | G23: 0000000102 | H23: 1.1.5.1.01 | I23: Iva sobre compras | J23: 369.55 | K23: 0 | L23: 369.55 | M23: 3449.12
A24: 44203 | C24: COMPRA | D24: COMPRA GYS. | E24: 001100000006230 | F24: COM-363 | G24: 0000000380 | H24: 1.1.3.3.1.1.27 | I24: Materiales de ferretera | J24: 66.07 | K24: 0 | L24: 66.07 | M24: 66.07
A25: 44203 | C25: COMPRA | D25: COMPRA GYS. | E25: 001100000006230 | F25: COM-363 | G25: 0000000380 | H25: 1.1.5.1.01 | I25: Iva sobre compras | J25: 7.93 | K25: 0 | L25: 7.93 | M25: 74
A26: 44208 | C26: COMPRA | D26: COMPRA GYS. | E26: 001900000000736 | F26: COM-90 | G26: 0000000101 | H26: 1.1.3.3.1.1.04 | I26: Suministros de Oficina Inventario Cultivo | J26: 829.76 | K26: 0 | L26: 829.76 | M26: 829.76
A27: 44208 | C27: COMPRA | D27: COMPRA GYS. | E27: 001900000000736 | F27: COM-90 | G27: 0000000101 | H27: 1.1.5.1.01 | I27: Iva sobre compras | J27: 99.57 | K27: 0 | L27: 99.57 | M27: 929.33
A28: 44209 | C28: COMPRA | D28: COMPRA GYS. | E28: 011003001208798 | F28: COM-100 | G28: 0000000111 | H28: 1.1.3.3.1.1.02 | I28: GLP industrial | J28: 2775.7 | K28: 0 | L28: 2775.7 | M28: 2775.7
A29: 44209 | C29: COMPRA | D29: COMPRA GYS. | E29: 011003001208798 | F29: COM-100 | G29: 0000000111 | H29: 1.1.5.1.01 | I29: Iva sobre compras | J29: 333.08 | K29: 0 | L29: 333.08 | M29: 3108.78
A30: 44209 | C30: COMPRA | D30: COMPRA GYS. | E30: 011003012087980 | F30: COM-93 | G30: 0000000104 | H30: 1.1.3.3.1.1.02 | I30: GLP industrial | J30: 2775.7 | K30: 0 | L30: 2775.7 | M30: 2775.7
A31: 44209 | C31: COMPRA | D31: COMPRA GYS. | E31: 011003012087980 | F31: COM-93 | G31: 0000000104 | H31: 1.1.5.1.01 | I31: Iva sobre compras | J31: 333.08 | K31: 0 | L31: 333.08 | M31: 3108.78
... A149: 44326 | C149: COMPRA | D149: COMPRA GYS. | E149: 001002000105067 | F149: COM-85 | G149: 0000000096 | H149: 1.1.5.1.01 | I149: Iva sobre compras | J149: 346.42 | K149: 0 | L149: 346.42 | M149: 3233.26
A150: 44326 | C150: COMPRA | D150: COMPRA GYS. | E150: 001002000105066 | F150: COM-86 | G150: 0000000097 | H150: 1.1.5.1.01 | I150: Iva sobre compras | K150: 0 | M150: 13472.6
A151: 44216 | H151: 1.1.3
J153: =SUBTOTAL(9,J19:J152) -> 99073.79 | L153: =SUM(L2:L152) -> 379496.38
L154: 396198
J155: =+J153-L153 -> -280422.59 | L155: =+L153-L154 -> -16701.62
J157: =+'5 PG101'!L48 -> 0
J158: =+J157+J149 -> 346.42

Sheet plan de cuentas
B1: EMPRESA: | C1: TABACALERA MENHURSA S.A.
B2: USUARIO: | C2: SIN NOMBRE
B3: DIRECCIÓN: | C3: VIA SANTO DOMINGO RECINTO FEDERICO INTRIAGO
B4: FECHA DE IMPRESIÓN | C4: 2022-08-26 11:39:48
C6: PLAN DE CUENTAS
B7: CUENTA | C7: DESCRIPCIÓN | D7: SALDO
A8: 311 | B8: 1 | C8: Activos | D8: 0
A9: 0 | B9: 1.01 | C9: activo corriente | D9: 0
A10: 0 | B10: 1.01.01 | C10: efectivo y equivalentes a efectivo | D10: 0
A11: 0 | B11: 1.01.01.01 | C11: Caja efectivo | D11: 0
A12: 0 | B12: 1.01.01.01.01 | C12: Caja recaudaciones | D12: 0
A13: 311 | B13: 1.01.01.01.01.01 | C13: Caja General | D13: 0
A14: 0 | B14: 1.01.01.01.01.02 | C14: Caja 2 | D14: 0
A15: 0 | B15: 1.01.01.01.01.03 | C15: Caja 3 | D15: 0
A16: 0 | B16: 1.01.01.01.01.04 | C16: Caja 3 | D16: 0
A17: 0 | B17: 1.01.01.01.01.05 | C17: Caja 4 | D17: 0
A18: 0 | B18: 1.01.01.01.02 | C18: Caja tarjeta de credito | D18: 0
A19: 0 | B19: 1.01.01.01.02.01 | C19: Mastercard | D19: 0
A20: 0 | B20: 1.01.01.01.02.02 | C20: Visa | D20: 0
A21: 0 | B21: 1.01.01.01.02.03 | C21: America Express | D21: 0
... A169: 0 | B169: 1.01.03.03.01.03.01 | C169: Sector 3 | D169: 0
B170: 1.01.03.03.01.04 | C170: Sector 4 | D170: 0
A171: 0 | B171: 1.01.03.03.01.04.01 | C171: Sector 4 | D171: 0
A172: 0 | B172: 1.01.03.03.01.05 | C172: Sector 5 | D172: 0
A173: 0 | B173: 1.01.03.03.02 | C173: Animales vivos | D173: 0
A174: 359 | B174: 1.01.03.03.02.01 | C174: Costo | D174: 0
A175: 0 | B175: 1.01.03.03.02.01.01 | C175: Hato ganadero 1 | D175: 0
A176: 0 | B176: 1.01.03.03.02.02 | C176: (-) Deterioro acumulado del valor de activos biológicos medidos a costo | D176: 0
A177: 0 | B177: 1.01.03.03.02.02.01 | C177: Hato ganadero 1 | D177: 0
A178: 336 | B178: 1.01.03.03.02.03 | C178: A valor razonable menos los costos de venta | D178: 0
A179: 0 | B179: 1.01.03.03.02.03.01 | C179: Hato ganadero 1 | D179: 0
A180: 0 | B180: 1.01.04 | C180: Servicios y otros pagos anticipados | D180: 0
A181: 0 | B181: 1.01.04.03 | C181: Anticipos | D181: 0
A182: 0 | B182: 1.01.04.03.01 | C182: Pagos anticipos | D182: 0
... A242: 0 | B242: 1.01.06.04.01 | C242: Cuenta 1 | D242: 0
A243: 0 | B243: 1.02 | C243: Activos no corrientes | D243: 0
A244: 0 | B244: 1.02.01 | C244: Propiedad planta y equipos | D244: 0
A245: 0 | B245: 1.02.01.01 | C245: Terrenos | D245: 0
A246: 0 | B246: 1.02.01.01.01 | C246: terrreno 1 | D246: 0
A247: 0 | B247: 1.02.01.02 | C247: Edificios | D247: 0
A248: 0 | B248: 1.02.01.02.01 | C248: Costo histórico antes de reexpresiones o revaluaciones | D248: 0
A249: 0 | B249: 1.02.01.02.01.01 | C249: Edificio 1 | D249: 0
A250: 0 | B250: 1.02.01.02.02 | C250: Ajuste acumulado por reexpresiones o revaluaciones | D250: 0
A251: 0 | B251: 1.02.01.02.02.01 | C251: Edificio 1 | D251: 0
A252: 0 | B252: 1.02.01.03 | C252: Naves, aeronaves, barcazasy similares | D252: 0
A253: 0 | B253: 1.02.01.03.01 | C253: Costo histórico antes de reexpresiones o revaluaciones | D253: 0
A254: 0 | B254: 1.02.01.03.01.01 | C254: Nave1 | D254: 0
A255: 0 | B255: 1.02.01.03.02 | C255: Ajuste acumulado por reexpresiones o revaluaciones | D255: 0
... A425: 519 | B425: 1.02.11.01.01 | C425: costos pagado anticipados | D425: 0
A426: 0 | B426: 2 | C426: Pasivos | D426: 0
A427: 0 | B427: 2.01 | C427: Pasivo corriente | D427: 0
A428: 0 | B428: 2.01.01 | C428: Pasivos financieros con cambios en resultados | D428: 0
A429: 0 | B429: 2.01.01.01 | C429: dfgdfg | D429: 0
A430: 0 | B430: 2.01.02 | C430: Pasivos por contratos de arrendamientos financieros | D430: 0
A431: 0 | B431: 2.01.03 | C431: Cuentas y documentos por pagar | D431: 0
A432: 0 | B432: 2.01.03.01 | C432: Cuentas por pagar | D432: 0
A433: 0 | B433: 2.01.03.01.01 | C433: Proveedores por pagar | D433: 0
A434: 0 | B434: 2.01.03.01.01.01 | C434: Proveedores por pagar local | D434: 0
A435: 0 | B435: 2.01.03.01.01.02 | C435: Proveedores por pagar Exterior | D435: 0
A436: 0 | B436: 2.01.03.02 | C436: Documentos por pagar | D436: 0
A437: 0 | B437: 2.01.03.02.01 | C437: Documentos por pagar local | D437: 0
A438: 0 | B438: 2.01.03.02.01.01 | C438: Documentos por pagar local | D438: 0
A439: 0 | B439: 2.01.03.03 | C439: Por pagar Socios o participes | D439: 0
... A541: 0 | B541: 2.01.11.02 | C541: Otros Pasivos corrientes pagos | D541: 0
A542: 0 | B542: 2.02 | C542: pasivo no corriente | D542: 0
A543: 0 | B543: 2.02.02 | C543: cuentas y documentos por pagar | D543: 0
A544: 0 | B544: 2.02.02.01 | C544: Cuentas por pagar | D544: 0
A545: 0 | B545: 2.02.02.02 | C545: Documentos por pagar | D545: 0
A546: 0 | B546: 2.02.02.02.01 | C546: no Relacionadas | D546: 0
A547: 0 | B547: 2.02.02.02.02 | C547: Relacionadas | D547: 0
A548: 0 | B548: 2.02.02.03 | C548: Cuentas por pagar socios y accionistas | D548: 0
A549: 0 | B549: 2.02.02.03.01 | C549: Cuentas por pagar Socios y Accionistas | D549: 0
A550: 0 | B550: 2.02.03 | C550: Obligaciones con instituciones financieras | D550: 0
A551: 0 | B551: 2.02.03.01 | C551: Locales | D551: 0
A552: 0 | B552: 2.02.03.02 | C552: Del exterior | D552: 0
A553: 0 | B553: 2.02.03.03 | C553: Crédito a mutuo | D553: 0
A554: 0 | B554: 2.02.03.04 | C554: Porción no corriente de obligaciones emitidas | D554: 0
... A580: 0 | B580: 2.02.08.02 | C580: Otros | D580: 0
A581: 0 | B581: 3 | C581: Patrimonio | D581: 0
A582: 0 | B582: 3.01 | C582: patrimonio atribuible a propietarios | D582: 0
A583: 0 | B583: 3.01.01 | C583: Capital suscrito y o asignado | D583: 0
A584: 0 | B584: 3.01.01.01 | C584: socio1 | D584: 0
A585: 0 | B585: 3.01.01.02 | C585: socio2 | D585: 0
A586: 0 | B586: 3.01.02 | C586: Aportes de socios o accionistas para futura capitalizacin | D586: 0
A587: 0 | B587: 3.01.04 | C587: Reservas | D587: 0
A588: 0 | B588: 3.01.04.01 | C588: Reserva legal | D588: 0
A589: 0 | B589: 3.01.04.02 | C589: Reserva facultativa | D589: 0
A590: 0 | B590: 3.01.04.03 | C590: Otras | D590: 0
A591: 0 | B591: 3.01.05 | C591: resultados acumulados | D591: 0
A592: 0 | B592: 3.01.05.01 | C592: Reserva de capital | D592: 0
A593: 0 | B593: 3.01.05.02 | C593: Reserva por donaciones | D593: 0
A594: 0 | B594: 3.01.05.03 | C594: Reserva por valuación (procedente de la aplicación de normas ecuatorianas de contabilidad - NEC) | D594: 0
... A616: 0 | B616: 3.01.08.01 | C616: socios | D616: 0
A617: 0 | B617: 4 | C617: Ingresos | D617: 0
A618: 0 | B618: 4.01 | C618: Ingresos de actividades ordinarias | D618: 0
A619: 0 | B619: 4.01.01 | C619: Ventas locales de bienes | D619: 0
A620: 0 | B620: 4.01.01.01 | C620: Gravadas con tarifa 12% de iva | D620: 0
A621: 0 | B621: 4.01.01.02 | C621: Gravadas con tarifa 0% de iva o exentas de iva | D621: 0
A622: 0 | B622: 4.01.01.03 | C622: Descuentos sobre Ventas 12% | D622: 0
A623: 0 | B623: 4.01.01.04 | C623: Descuentos sobre Ventas 0% | D623: 0
...

Sheet 900 (2)
C1: RAZÓN SOCIAL: | E1: TABACALERA MENHURSA S.A.
C2: RUC: | E2: 1291784468001 | AD2: SI | AF2: SI | AG2: CÉDULA
C3: EXPEDIENTE: | E3: 144928 | X3: INDIVIDUAL | Z3: ACTIVO | AA3: MODELO DEL COSTO | AD3: NO | AF3: NO | AG3: PASAPORTE
C4: INDICACIONES: | X4: CONSOLIDADO | Z4: PASIVO | AA4: MODELO DEL REAVALÚO | AD4: PARCIALMENTE | AF4: NO APLICA
C5: Este cuestionario debe incluirlo y ligarlo a la sumaria, pegar con formato de origen
B6: ¿¿ | C6: a. | D6: TODAS las Operciones con partes relacionadas verifique si se efectuaron en términos y condiciones equiparables a otras de igual especie, realizadas con terceros. | Z6: PATRIMONIO
B7: ¿¿ | C7: b. | D7: TODOS los movimientoas del patrimonio deben estar soportados con actas de junta con copias en los papeles de trabajo | X7: ✔ | Z7: INGRESO | AD7: SI
B8: ¿¿ | C8: c. | D8: TODOS los Movimientos de activos fijos deben quedar soportados con los diarios y si hay ventas con las facturas | X8: X | Z8: GASTO | AD8: NO
B9: ¿¿ | C9: d. | D9: TODAS las obligaciones bancarias y PARTES RELACIONADAS deben tener la confirmacion de saldos | AD9: DESCONOCE
C11: ASPECTOS QUE DEBEN REVELAR LAS NOTAS A LOS ESTADOS FINANCIEROS | X11: NIIF PYMES | Z11: MARCO CONCEPTUAL
C12: a. | D12: Transacciones importantes con Partes Relacionadas | X12: NIIF COMPLETAS | Z12: SECCION 2
C13: b. | D13: Transacciones recursos recibidos por parte de clientes en forma anticipada.
C14: c. | D14: Si el dictamen contienen párrafos de énfasis motivos que origina.
C16: PARTICULAR ATENCIÓN A LO SIGUIENTE:
C17: a. | D17: Determinación de Materialidad
C18: b. | D18: Aspectos analizados sobre entendimiento de negocio
C19: c. | D19: Cuentas Patrimoniales
C20: d, | D20: Antigüedad de aportes de socios o aumento de capital
C21: e. | D21: Identificar si la compañía realizó transacciones con Partes Relacionadas
C22: f. | D22: Obligaciones con Instituciones
C23: g. | D23: Fuentes de financiamiento.
C25: INFORME A EMITIR | G25: INDIVIDUAL
C26: OBJETIVOS:
B27: ¿ | D27: Expresar una opinión sobre la razonabilidad de los estados financieros en su conjunto.
C28: ESTADOS FINANCIEROS SUJETOS A REVISIÓN
D29: Estado De Situación Financiera | G29: ✔
D30: Estado De Resultado Integral | G30: ✔
D31: Estado De Cambio En El Patrimonio | G31: ✔
D32: Estado De Flujo De Efectivo | G32: ✔
D33: Notas A Los Estados Financieros | G33: ✔
C34: ALCANCE
B35: ¿¿¿¿¿¿¿¿ | D35: Nuestros objetivos son obtener una seguridad razonable de que los estados financieros en su conjunto están libres de incorrección material, debida a fraude o error, y emitir un informe de auditoría que contiene nuestra opinión. Seguridad razonable es un alto grado de seguridad pero no garantiza que una auditoría realizada de conformidad con las NIA siempre detecte una incorrección material cuando existe. Las incorrecciones pueden deberse a fraude o error y se consideran materiales si, individualmente o de forma agregada, puede preverse razonablemente que influyan en las decisiones económicas que los usuarios toman basándose en los estados financieros.
D37: HONORARIOS | G37: 2500
D38: AUDITORÍA INICIAL | G38: ✔
D39: AUDITORÍA RECURRENTE
C42: RESPONSABILIDAD DEL AUDITOR
B43: ¿¿¿¿¿¿¿ | D43: Como parte de una auditoría de conformidad con las NIA (Normas Internacionales de Auditoría), aplicamos nuestro juicio profesional y mantenemos una actitud de escepticismo profesional durante toda la auditoría. También: Identificamos y valoramos los riesgos de incorrección material en los estados financieros, debida a fraude o error, diseñamos y aplicamos procedimientos de auditoría para responder a dichos riesgos y obtenemos evidencia de auditoría suficiente y adecuada para proporcionar una base para nuestra opinión.
C46: RESPONSABILIDAD DE LA ADMINISTRACIÓN
B47: ¿¿¿¿¿ | D47: La Administración es responsable de la preparación y presentación fiel de los estados financieros adjuntos de conformidad con las NIIF PYMES, y del control interno que la administración considere necesario para permitir la preparación de estados financieros libres de incorrección material, debida a fraude o error. Los responsables del gobierno de la entidad son responsables de la supervisión del proceso de información financiera de la Sociedad.
B49: ¿¿ | C49: IDENTIFICACIÓN DEL MARCO REFERENCIA APLICABLE EN LA ELABORACIÓN DE LOS ESTADOS FINANCIERO
B50: ¿¿ | D50: La preparación y presentación fiel de los estados financieros de conformidad con las NIIF PYMES | J50: NIIF PYMES
C52: ACTIVIDAD DE LA COMPAÑÍA
B53: ¿¿¿¿ | D53: Producir, importar, exportar, vender, comprar, distribuir y comercializar productos y servicios relacionados con la perforación petrolera; b) Servicios de inspección, mantenimiento, reparación y ajuste de tuberías; c) Servicios de perforación direccional, incluido el servicio de toma de medidas durante la perforación y servicio de registro durante la perforación...
B55: ¿¿ | D55: ¿Esta actividad económica corresponde a la actividad PRINCIPAL que efectivamente realiza la compañía? | J55: SI
D57: Fecha de informe de Auditoría | H57: =+'OPINION pymes con anexo '!I72 -> Agosto, 18 del 2023 | K57: (Ver opinión) | M57: =200/1.12 -> 178.57143
D58: Fecha de entrega del informe de Auditoría | H58: 44833 | K58: (Ver opinión)
C60: CONCLUSIONES Y HALLAZGOS
C61: MARQUE EL TIPO DE OPINIÓN EMITIDA CORRESPONDIENTE AL PERÍODO AUDITADO:
D62: TIPO DE OPINIÓN
D63: No modificada o favorable | G63: ✔
D64: Modificada - con salvedades
D65: Modificada - desfavorable o adversa
D66: Modificada - denegación o abstención
C68: JUSTIFICACIÓN DE LA OPINIÓN:
B69: ¿¿¿¿¿¿¿¿¿¿¿ | D69: En nuestra opinión, los estados financieros adjuntos presentan razonablemente, en todos sus aspectos importantes, la situación financiera de la Compañía TABACALERA MENHURSA S.A., al 31 de diciembre del 2021, así como sus resultados y flujos de efectivo correspondientes al ejercicio terminado en esa fecha, de conformidad con las Normas Internacionales de Información Financiera (NIIF PYMES). Fundamento de la opinión. Hemos llevado a cabo nuestra auditoría de conformidad con las Normas Internacionales de Auditoría (NIA). Nuestras responsabilidades de acuerdo con dichas normas se describen más adelante en la sección Responsabilidades del auditor en relación con la auditoría de los estados financieros de nuestro informe. Somos independientes de la Compañía de conformidad con el Código de Ética para Profesionales de la Contabilidad del Consejo de Normas Internacionales de Ética para Contadores (Código de Ética del IESBA), y hemos cumplido las demás responsabilidades de ética de conformidad con el Código de Ética del IESBA. Consideramos que la evidencia de auditoría que hemos obtenido proporciona una base suficiente y adecuada para nuestra opinión.
B71: ¿¿ | C71: MARQUE EL TIPO DE OPINIÓN EMITIDA EN EL INFORME CORRESPONDIENTE AL EJERCICIO FISCAL ANTERIOR
D72: TIPO DE OPINIÓN
D73: No modificada o favorable
D74: Modificada - con salvedades
D75: Modificada - desfavorable o adversa
D76: Modificada - denegación o abstención
D77: No obligada | G77: ✔
D78: Omiso en la entrega del informe
C80: NOMBRE DEL AUDITOR DEL AÑO ANTERIOR | G80: 662 3ANG ACIA LTDA
G81: NO PRESENTO AUDITORIA AÑO ANTERIOR
J82: Responda
B83: ¿¿ | C83: ¿Todos los hechos o situaciones relevantes que superaron el nivel de materialidad determinado fueron debidamente analizados y documentados? | J83: SI
C84: ¿Existió suficiente evidencia para respaldar la opinión emitida por el Auditor? | J84: SI
C85: ¿La compañía auditada está en causal de disolución por pérdidas de capital? | J85: SI
C87: ESTADOS FINANCIEROS AUDITADOS
C88: Por favor ingrese la información de los estados financieros:
D89: Ingresar Individual:AQUI | F89: MAPEO FORM.101 EN EXCEL CONFORME AL 101 CARGADO POR EL CLIENTE
C92: Nombre Representante Legal: | F92: MENDOZA PALMA ERWIN EDUARDO | K92: Llenar
C93: CI Representante Legal: | F93: 1708804552 | K93: Llenar
C94: Nombre Contador: | F94: ALFONSO SOLORZANO MONCADA | K94: Llenar
C95: Identificación Contador: | H95: INDICAR SI ES | K95: Llenar
C97: ESTADO DE CAMBIOS EN EL PATRIMONIO | G97: Información se llena en línea
C98: ESTADO DE FLUJOS DE EFECTIVO | G98: Información se llena en línea
C100: DETERMINACIÓN DE LA MATERIALIDAD
D102: Valor USD | E102: =+H103*H102 -> 0 | G102: % | H102: =+'11Materialidad SUM'!L35 -> 0.03
B103: ¿¿ | D103: RUBRO EN FUNCIÓN DEL CUAL SE CALCULÓ LA MATERIALIDAD | G103: ACTIVO | H103: =+'11Materialidad SUM'!K38 -> 0
C105: Marque los aspectos analizados sobre el entendimiento del negocio del cliente:
D106: Entendimiento del negocio | G106: Responda
D107: Organización | G107: SI
D108: Estructura | G108: SI
D109: Principales operaciones | G109: SI
D110: Políticas y procedimientos de control | G110: SI
D111: Principales clientes | G111: SI
D112: Principales proveedores | G112: SI
D113: Factores que afecta su operatividad | G113: SI
D114: Normativa del sector | G114: SI
D115: Manual de funciones | G115: SI
D116: Otros
J117: Responda
B118: ¿ | C118: ¿La empresa auditada contó con un plan o manual de cuentas? | J118: SI
B119: ¿ | C119: ¿La empresa auditada contó con políticas y procedimientos contables? | J119: SI
B120: ¿¿ | C120: ¿El auditor externo examinó los contratos importantes celebrados por la compañía y vigentes en el período de la auditoría? | J120: SI
B122: ¿¿ | C122: Se aplicaron procedimientos de auditoría adecuados para evaluar la calidad y efectividad del:
D123: Descripción | G123: Responda
D124: Sistema de Contabilidad | G124: SI
...

Sheet 101 2018 (2021)
S1: Valor no deducible
A2: FORMULARIO RENTA SOCIEDADES
A4: OPERACIONES CON PARTES RELACIONADAS LOCALES Y/O DEL EXTERIOR
B5: CON PARTES RELACIONADAS LOCALES
C6: Operaciones de activo | N6: 3 | O6: =SUMIF('3BL ACTUAL'!A:A,N6,'3BL ACTUAL'!E:E) -> 0 | AC6: =+O6-AA6-AB6 -> 0 | AD6: =+O6+AA6+AB6 -> 0
C7: Operaciones de pasivo | N7: 4 | O7: =SUMIF('3BL ACTUAL'!A:A,N7,'3BL ACTUAL'!E:E) -> 0 | AC7: =+O7-AA7-AB7 -> 0 | AD7: =+O7+AA7+AB7 -> 0
C8: Operaciones de ingreso | N8: 5 | O8: =SUMIF('3BL ACTUAL'!A:A,N8,'3BL ACTUAL'!E:E) -> 0 | AC8: =+O8-AA8-AB8 -> 0 | AD8: =+O8+AA8+AB8 -> 0
C9: Operaciones de egreso | N9: 6 | O9: =SUMIF('3BL ACTUAL'!A:A,N9,'3BL ACTUAL'!E:E) -> 0 | AC9: =+O9-AA9-AB9 -> 0 | AD9: =+O9+AA9+AB9 -> 0
C10: Operaciones de regalías, servicios técnicos, administrativos, de consultoría y similares | N10: 7 | O10: =SUMIF('3BL ACTUAL'!A:A,N10,'3BL ACTUAL'!E:E) -> 0 | AC10: =+O10-AA10-AB10 -> 0 | AD10: =+O10+AA10+AB10 -> 0
B11: CON PARTES RELACIONADAS EN PARAÍSOS FISCALES, JURISDICCIONES DE MENOR IMPOSICIÓN Y RÉGIMENES FISCALES PREFERENTES | AC11: =+O11-AA11-AB11 -> 0 | AD11: =+O11+AA11+AB11 -> 0
C12: Operaciones de activo | N12: 8 | O12: =SUMIF('3BL ACTUAL'!A:A,N12,'3BL ACTUAL'!E:E) -> 0 | AC12: =+O12-AA12-AB12 -> 0 | AD12: =+O12+AA12+AB12 -> 0
C13: Operaciones de pasivo | N13: 9 | O13: =SUMIF('3BL ACTUAL'!A:A,N13,'3BL ACTUAL'!E:E) -> 0 | AC13: =+O13-AA13-AB13 -> 0 | AD13: =+O13+AA13+AB13 -> 0
C14: Operaciones de ingreso | N14: 10 | O14: =SUMIF('3BL ACTUAL'!A:A,N14,'3BL ACTUAL'!E:E) -> 0 | AC14: =+O14-AA14-AB14 -> 0 | AD14: =+O14+AA14+AB14 -> 0
C15: Operaciones de egreso | N15: 11 | O15: =SUMIF('3BL ACTUAL'!A:A,N15,'3BL ACTUAL'!E:E) -> 0 | AC15: =+O15-AA15-AB15 -> 0 | AD15: =+O15+AA15+AB15 -> 0
C16: Operaciones de regalías, servicios técnicos, administrativos, de consultoría y similares | N16: 12 | O16: =SUMIF('3BL ACTUAL'!A:A,N16,'3BL ACTUAL'!E:E) -> 0 | AC16: =+O16-AA16-AB16 -> 0 | AD16: =+O16+AA16+AB16 -> 0
B17: CON PARTES RELACIONADAS EN OTRAS JURISDICCIONES O RÉGIMENES DEL EXTERIOR | AC17: =+O17-AA17-AB17 -> 0 | AD17: =+O17+AA17+AB17 -> 0
C18: Operaciones de activo | N18: 13 | O18: =SUMIF('3BL ACTUAL'!A:A,N18,'3BL ACTUAL'!E:E) -> 0 | AC18: =+O18-AA18-AB18 -> 0 | AD18: =+O18+AA18+AB18 -> 0
C19: Operaciones de pasivo | N19: 14 | O19: =SUMIF('3BL ACTUAL'!A:A,N19,'3BL ACTUAL'!E:E) -> 0 | AC19: =+O19-AA19-AB19 -> 0 | AD19: =+O19+AA19+AB19 -> 0
C20: Operaciones de ingreso | N20: 15 | O20: =SUMIF('3BL ACTUAL'!A:A,N20,'3BL ACTUAL'!E:E) -> 0 | AC20: =+O20-AA20-AB20 -> 0 | AD20: =+O20+AA20+AB20 -> 0
C21: Operaciones de egreso | N21: 16 | O21: =SUMIF('3BL ACTUAL'!A:A,N21,'3BL ACTUAL'!E:E) -> 0 | AC21: =+O21-AA21-AB21 -> 0 | AD21: =+O21+AA21+AB21 -> 0
C22: Operaciones de regalías, servicios técnicos, administrativos, de consultoría y similares | N22: 17 | O22: =SUMIF('3BL ACTUAL'!A:A,N22,'3BL ACTUAL'!E:E) -> 0 | AC22: =+O22-AA22-AB22 -> 0 | AD22: =+O22+AA22+AB22 -> 0
B23: TOTAL OPERACIONES CON PARTES RELACIONADAS | N23: 029 | AC23: =+O23-AA23-AB23 -> 0 | AD23: =+O23+AA23+AB23 -> 0
B24: ¿Sujeto pasivo exento de aplicación del régimen de precios de transferencia? | N24: 30 | O24: =SUMIF('3BL ACTUAL'!A:A,N24,'3BL ACTUAL'!E:E) -> 0 | AC24: =+O24-AA24-AB24 -> 0 | AD24: =+O24+AA24+AB24 -> 0
A25: ESTADO DE SITUACIÓN FINANCIERA | AC25: =+O25-AA25-AB25 -> 0 | AD25: =+O25+AA25+AB25 -> 0
B26: ACTIVO | AC26: =+O26-AA26-AB26 -> 0 | AD26: =+O26+AA26+AB26 -> 0
C27: ACTIVOS CORRIENTES | AC27: =+O27-AA27-AB27 -> 0 | AD27: =+O27+AA27+AB27 -> 0
D28: Efectivo y equivalentes al efectivo | N28: 311 | O28: =SUMIF('3BL ACTUAL'!B:B,N28,'3BL ACTUAL'!E:E) -> 0 | AB28: 19813.35 | AC28: =+O28-AA28-AB28 -> -19813.35 | AD28: =+O28+AA28+AB28 -> 19813.35
D29: CUENTAS Y DOCUMENTOS POR COBRAR CORRIENTES | AC29: =+O29-AA29-AB29 -> 0 | AD29: =+O29+AA29+AB29 -> 0
E30: CUENTAS Y DOCUMENTOS POR COBRAR COMERCIALES CORRIENTES | AC30: =+O30-AA30-AB30 -> 0 | AD30: =+O30+AA30+AB30 -> 0
F31: RELACIONADAS | AC31: =+O31-AA31-AB31 -> 0 | AD31: =+O31+AA31+AB31 -> 0
A32: ______ | B32: ______ | C32: ______ | D32: ______ | E32: ______ | F32: ______ | G32: Locales | N32: 312 | O32: =SUMIF('3BL ACTUAL'!B:B,N32,'3BL ACTUAL'!E:E) -> 0 | AC32: =+O32-AA32-AB32 -> 0 | AD32: =+O32+AA32+AB32 -> 0
G33: Del exterior | N33: 313 | O33: =SUMIF('3BL ACTUAL'!B:B,N33,'3BL ACTUAL'!E:E) -> 0 | AC33: =+O33-AA33-AB33 -> 0 | AD33: =+O33+AA33+AB33 -> 0
G34: (-) Deterioro acumulado del valor de cuentas y documentos por cobrar comerciales por incobrabilidad (provisiones para créditos incobrables) | N34: 314 | O34: =SUMIF('3BL ACTUAL'!B:B,N34,'3BL ACTUAL'!E:E) -> 0 | AC34: =+O34-AA34-AB34 -> 0 | AD34: =+O34+AA34+AB34 -> 0
F35: NO RELACIONADAS | AC35: =+O35-AA35-AB35 -> 0 | AD35: =+O35+AA35+AB35 -> 0
G36: Locales | N36: 315 | O36: =SUMIF('3BL ACTUAL'!B:B,N36,'3BL ACTUAL'!E:E) -> 0 | AC36: =+O36-AA36-AB36 -> 0 | AD36: =+O36+AA36+AB36 -> 0
G37: Del exterior | N37: 316 | O37: =SUMIF('3BL ACTUAL'!B:B,N37,'3BL ACTUAL'!E:E) -> 0 | AC37: =+O37-AA37-AB37 -> 0 | AD37: =+O37+AA37+AB37 -> 0
G38: (-) Deterioro acumulado del valor de cuentas y documentos por cobrar comerciales por incobrabilidad (provisiones para créditos incobrables) | N38: 317 | O38: =SUMIF('3BL ACTUAL'!B:B,N38,'3BL ACTUAL'!E:E) -> 0 | Q38: exceder del 10% de la cartera total. | R38: .- Las provisiones para créditos incobrables originados en operaciones del giro ordinario del negocio, efectuadas en cada ejercicio impositivo a razón del 1% anual sobre los créditos comerciales concedidos en dicho ejercicio y que se encuentren pendientes de recaudación al cierre del mismo, sin que la provisión acumulada pueda exceder del 10% de la cartera total. | AC38: =+O38-AA38-AB38 -> 0 | AD38: =+O38+AA38+AB38 -> 0
E39: OTRAS CUENTAS Y DOCUMENTOS POR COBRAR CORRIENTES | AC39: =+O39-AA39-AB39 -> 0 | AD39: =+O39+AA39+AB39 -> 0
F40: A ACCIONISTAS, SOCIOS, PARTICIPES, BENEFICIARIOS U OTROS TITULARES DE DERECHOS REPRESENTATIVOS DE CAPITAL | AC40: =+O40-AA40-AB40 -> 0 | AD40: =+O40+AA40+AB40 -> 0
G41: Locales | N41: 318 | O41: =SUMIF('3BL ACTUAL'!B:B,N41,'3BL ACTUAL'!E:E) -> 0 | AC41: =+O41-AA41-AB41 -> 0 | AD41: =+O41+AA41+AB41 -> 0
G42: Del exterior | N42: 319 | O42: =SUMIF('3BL ACTUAL'!B:B,N42,'3BL ACTUAL'!E:E) -> 0 | AC42: =+O42-AA42-AB42 -> 0 | AD42: =+O42+AA42+AB42 -> 0
F43: DIVIDENDOS POR COBRAR | AC43: =+O43-AA43-AB43 -> 0 | AD43: =+O43+AA43+AB43 -> 0
G44: En efectivo | N44: 320 | O44: =SUMIF('3BL ACTUAL'!B:B,N44,'3BL ACTUAL'!E:E) -> 0 | AC44: =+O44-AA44-AB44 -> 0 | AD44: =+O44+AA44+AB44 -> 0
G45: En activos diferentes del efectivo | N45: 321 | O45: =SUMIF('3BL ACTUAL'!B:B,N45,'3BL ACTUAL'!E:E) -> 0 | AC45: =+O45-AA45-AB45 -> 0 | AD45: =+O45+AA45+AB45 -> 0
F46: OTRAS RELACIONADAS | AC46: =+O46-AA46-AB46 -> 0 | AD46: =+O46+AA46+AB46 -> 0
G47: Locales | N47: 322 | O47: =SUMIF('3BL ACTUAL'!B:B,N47,'3BL ACTUAL'!E:E) -> 0 | AC47: =+O47-AA47-AB47 -> 0 | AD47: =+O47+AA47+AB47 -> 0
G48: Del exterior | N48: 323 | O48: =SUMIF('3BL ACTUAL'!B:B,N48,'3BL ACTUAL'!E:E) -> 0 | AC48: =+O48-AA48-AB48 -> 0 | AD48: =+O48+AA48+AB48 -> 0
G49: (-) Deterioro acumulado del valor de otras cuentas y documentos por cobrar por incobrabilidad (provisiones para créditos incobrables) | N49: 324 | O49: =SUMIF('3BL ACTUAL'!B:B,N49,'3BL ACTUAL'!E:E) -> 0 | AC49: =+O49-AA49-AB49 -> 0 | AD49: =+O49+AA49+AB49 -> 0
F50: OTRAS NO RELACIONADAS | AC50: =+O50-AA50-AB50 -> 0 | AD50: =+O50+AA50+AB50 -> 0
G51: Locales | N51: 325 | O51: =SUMIF('3BL ACTUAL'!B:B,N51,'3BL ACTUAL'!E:E) -> 0 | AC51: =+O51-AA51-AB51 -> 0 | AD51: =+O51+AA51+AB51 -> 0
G52: Del exterior | N52: 326 | O52: =SUMIF('3BL ACTUAL'!B:B,N52,'3BL ACTUAL'!E:E) -> 0 | AC52: =+O52-AA52-AB52 -> 0 | AD52: =+O52+AA52+AB52 -> 0
G53: (-) Deterioro acumulado del valor de otras cuentas y documentos por cobrar por incobrabilidad (provisiones para créditos incobrables) | N53: 327 | O53: =SUMIF('3BL ACTUAL'!B:B,N53,'3BL ACTUAL'!E:E) -> 0 | AC53: =+O53-AA53-AB53 -> 0 | AD53: =+O53+AA53+AB53 -> 0
D54: OTROS ACTIVOS FINANCIEROS CORRIENTES | AC54: =+O54-AA54-AB54 -> 0 | AD54: =+O54+AA54+AB54 -> 0
E55: A costo amortizado | N55: 328 | O55: =SUMIF('3BL ACTUAL'!B:B,N55,'3BL ACTUAL'!E:E) -> 0 | AC55: =+O55-AA55-AB55 -> 0 | AD55: =+O55+AA55+AB55 -> 0
E56: (-) Deterioro acumulado del valor de otros activos financieros corrientes medidos a costo amortizado (provisiones para créditos incobrables) | N56: 329 | O56: =SUMIF('3BL ACTUAL'!B:B,N56,'3BL ACTUAL'!E:E) -> 0 | AC56: =+O56-AA56-AB56 -> 0 | AD56: =+O56+AA56+AB56 -> 0
E57: A valor razonable | N57: 330 | O57: =SUMIF('3BL ACTUAL'!B:B,N57,'3BL ACTUAL'!E:E) -> 0 | AC57: =+O57-AA57-AB57 -> 0 | AD57: =+O57+AA57+AB57 -> 0
D58: PORCIÓN CORRIENTE DE ARRENDAMIENTOS FINANCIEROS POR COBRAR | AC58: =+O58-AA58-AB58 -> 0 | AD58: =+O58+AA58+AB58 -> 0
E59: Relacionadas | N59: 331 | O59: =SUMIF('3BL ACTUAL'!B:B,N59,'3BL ACTUAL'!E:E) -> 0 | AC59: =+O59-AA59-AB59 -> 0 | AD59: =+O59+AA59+AB59 -> 0
E60: No relacionadas | N60: 332 | O60: =SUMIF('3BL ACTUAL'!B:B,N60,'3BL ACTUAL'!E:E) -> 0 | AC60: =+O60-AA60-AB60 -> 0 | AD60: =+O60+AA60+AB60 -> 0
D61: IMPORTE BRUTO ADEUDADO POR LOS CLIENTES POR EL TRABAJO EJECUTADO EN CONTRATOS DE CONSTRUCCIÓN | AC61: =+O61-AA61-AB61 -> 0 | AD61: =+O61+AA61+AB61 -> 0
E62: Relacionadas | N62: 333 | O62: =SUMIF('3BL ACTUAL'!B:B,N62,'3BL ACTUAL'!E:E) -> 0 | AC62: =+O62-AA62-AB62 -> 0 | AD62: =+O62+AA62+AB62 -> 0
E63: No relacionadas | N63: 334 | O63: =SUMIF('3BL ACTUAL'!B:B,N63,'3BL ACTUAL'!E:E) -> 0 | AC63: =+O63-AA63-AB63 -> 0 | AD63: =+O63+AA63+AB63 -> 0
D64: ACTIVOS POR IMPUESTOS CORRIENTES | AC64: =+O64-AA64-AB64 -> 0 | AD64: =+O64+AA64+AB64 -> 0
E65: Crédito tributario a favor del sujeto pasivo (ISD) | N65: 335 | O65: =SUMIF('3BL ACTUAL'!B:B,N65,'3BL ACTUAL'!E:E) -> 0 | AC65: =+O65-AA65-AB65 -> 0 | AD65: =+O65+AA65+AB65 -> 0
E66: Crédito tributario a favor del sujeto pasivo (IVA) | N66: 336 | O66: =SUMIF('3BL ACTUAL'!B:B,N66,'3BL ACTUAL'!E:E) -> 0 | AC66: =+O66-AA66-AB66 -> 0 | AD66: =+O66+AA66+AB66 -> 0
E67: Crédito tributario a favor del sujeto pasivo (Impuesto a la Renta) | N67: 337 | O67: =SUMIF('3BL ACTUAL'!B:B,N67,'3BL ACTUAL'!E:E) -> 0 | AC67: =+O67-AA67-AB67 -> 0 | AD67: =+O67+AA67+AB67 -> 0
E68: Otros | N68: 338 | O68: =SUMIF('3BL ACTUAL'!B:B,N68,'3BL ACTUAL'!E:E) -> 0 | AC68: =+O68-AA68-AB68 -> 0 | AD68: =+O68+AA68+AB68 -> 0
D69: INVENTARIOS | AC69: =+O69-AA69-AB69 -> 0 | AD69: =+O69+AA69+AB69 -> 0
E70: Mercaderías en tránsito | N70: 339 | O70: =SUMIF('3BL ACTUAL'!B:B,N70,'3BL ACTUAL'!E:E) -> 0 | AC70: =+O70-AA70-AB70 -> 0 | AD70: =+O70+AA70+AB70 -> 0
E71: Inventario de materia prima (no para la construcción) | N71: 340 | O71: =SUMIF('3BL ACTUAL'!B:B,N71,'3BL ACTUAL'!E:E) -> 0 | AC71: =+O71-AA71-AB71 -> 0 | AD71: =+O71+AA71+AB71 -> 0
E72: Inventario de productos en proceso (excluyendo obras/inmuebles en construcción para la venta) | N72: 341 | O72: =SUMIF('3BL ACTUAL'!B:B,N72,'3BL ACTUAL'!E:E) -> 0 | AB72: 251470.34 | AC72: =+O72-AA72-AB72 -> -251470.34 | AD72: =+O72+AA72+AB72 -> 251470.34
E73: Inventario de prod. term. y mercad. en almacén (excluyendo obras/inmuebles terminados para la venta) | N73: 342 | O73: =SUMIF('3BL ACTUAL'!B:B,N73,'3BL ACTUAL'!E:E) -> 0 | AC73: =+O73-AA73-AB73 -> 0 | AD73: =+O73+AA73+AB73 -> 0
E74: Inventario de suministros, herramientas, repuestos y materiales (no para la construcción) | N74: 343 | O74: =SUMIF('3BL ACTUAL'!B:B,N74,'3BL ACTUAL'!E:E) -> 0 | AC74: =+O74-AA74-AB74 -> 0 | AD74: =+O74+AA74+AB74 -> 0
E75: Inventario de materia prima, suministros y materiales para la construcción | N75: 344 | O75: =SUMIF('3BL ACTUAL'!B:B,N75,'3BL ACTUAL'!E:E) -> 0 | AC75: =+O75-AA75-AB75 -> 0 | AD75: =+O75+AA75+AB75 -> 0
E76: Inventario de obras/inmuebles en construcción para la venta | N76: 345 | O76: =SUMIF('3BL ACTUAL'!B:B,N76,'3BL ACTUAL'!E:E) -> 0 | AC76: =+O76-AA76-AB76 -> 0 | AD76: =+O76+AA76+AB76 -> 0
E77: Inventario de obras/inmuebles terminados para la venta | N77: 346 | O77: =SUMIF('3BL ACTUAL'!B:B,N77,'3BL ACTUAL'!E:E) -> 0 | AC77: =+O77-AA77-AB77 -> 0 | AD77: =+O77+AA77+AB77 -> 0
E78: (-) Deterioro acumulado del valor de inventarios por ajuste al valor neto realizable | N78: 347 | O78: =SUMIF('3BL ACTUAL'!B:B,N78,'3BL ACTUAL'!E:E) -> 0 | AC78: =+O78-AA78-AB78 -> 0 | AD78: =+O78+AA78+AB78 -> 0
D79: ACTIVOS NO CORRIENTES MANTENIDOS PARA LA VENTA | AC79: =+O79-AA79-AB79 -> 0 | AD79: =+O79+AA79+AB79 -> 0
E80: Costo | N80: 348 | O80: =SUMIF('3BL ACTUAL'!B:B,N80,'3BL ACTUAL'!E:E) -> 0 | AC80: =+O80-AA80-AB80 -> 0 | AD80: =+O80+AA80+AB80 -> 0
E81: (-) Deterioro acumulado del valor de activos no corrientes mantenidos para la venta | N81: 349 | O81: =SUMIF('3BL ACTUAL'!B:B,N81,'3BL ACTUAL'!E:E) -> 0 | AC81: =+O81-AA81-AB81 -> 0 | AD81: =+O81+AA81+AB81 -> 0
D82: ACTIVOS BIOLÓGICOS | AC82: =+O82-AA82-AB82 -> 0 | AD82: =+O82+AA82+AB82 -> 0
E83: PLANTAS VIVAS Y FRUTOS EN CRECIMIENTO | AC83: =+O83-AA83-AB83 -> 0 | AD83: =+O83+AA83+AB83 -> 0
F84: A costo | N84: 350 | O84: =SUMIF('3BL ACTUAL'!B:B,N84,'3BL ACTUAL'!E:E) -> 0 | AC84: =+O84-AA84-AB84 -> 0 | AD84: =+O84+AA84+AB84 -> 0
F85: (-) Deterioro acumulado del valor de activos biológicos medidos a costo | N85: 351 | O85: =SUMIF('3BL ACTUAL'!B:B,N85,'3BL ACTUAL'!E:E) -> 0 | AC85: =+O85-AA85-AB85 -> 0 | AD85: =+O85+AA85+AB85 -> 0
F86: A valor razonable menos los costos de venta | N86: 352 | O86: =SUMIF('3BL ACTUAL'!B:B,N86,'3BL ACTUAL'!E:E) -> 0 | AC86: =+O86-AA86-AB86 -> 0 | AD86: =+O86+AA86+AB86 -> 0
E87: ANIMALES VIVOS | AC87: =+O87-AA87-AB87 -> 0 | AD87: =+O87+AA87+AB87 -> 0
F88: A costo | N88: 353 | O88: =SUMIF('3BL ACTUAL'!B:B,N88,'3BL ACTUAL'!E:E) -> 0 | AC88: =+O88-AA88-AB88 -> 0 | AD88: =+O88+AA88+AB88 -> 0
F89: (-) Deterioro acumulado del valor de activos biológicos medidos a costo | N89: 354 | O89: =SUMIF('3BL ACTUAL'!B:B,N89,'3BL ACTUAL'!E:E) -> 0 | AC89: =+O89-AA89-AB89 -> 0 | AD89: =+O89+AA89+AB89 -> 0
F90: A valor razonable menos los costos de venta | N90: 355 | O90: =SUMIF('3BL ACTUAL'!B:B,N90,'3BL ACTUAL'!E:E) -> 0 | AC90: =+O90-AA90-AB90 -> 0 | AD90: =+O90+AA90+AB90 -> 0
D91: GASTOS PAGADOS POR ANTICIPADO (PREPAGADOS) | AC91: =+O91-AA91-AB91 -> 0 | AD91: =+O91+AA91+AB91 -> 0
E92: Propaganda y publicidad prepagada | N92: 356 | O92: =SUMIF('3BL ACTUAL'!B:B,N92,'3BL ACTUAL'!E:E) -> 0 | AC92: =+O92-AA92-AB92 -> 0 | AD92: =+O92+AA92+AB92 -> 0
E93: Arrendamientos operativos pagados por anticipado | N93: 357 | O93: =SUMIF('3BL ACTUAL'!B:B,N93,'3BL ACTUAL'!E:E) -> 0 | AC93: =+O93-AA93-AB93 -> 0 | AD93: =+O93+AA93+AB93 -> 0
E94: Primas de seguro pagadas por anticipado | N94: 358 | O94: =SUMIF('3BL ACTUAL'!B:B,N94,'3BL ACTUAL'!E:E) -> 0 | AC94: =+O94-AA94-AB94 -> 0 | AD94: =+O94+AA94+AB94 -> 0
E95: Otros | N95: 359 | O95: =SUMIF('3BL ACTUAL'!B:B,N95,'3BL ACTUAL'!E:E) -> 0 | AC95: =+O95-AA95-AB95 -> 0 | AD95: =+O95+AA95+AB95 -> 0
D96: Otros Activos Corrientes | N96: 360 | O96: =SUMIF('3BL ACTUAL'!B:B,N96,'3BL ACTUAL'!E:E) -> 0 | Q96: según blance | R96: dife | AC96: =+O96-AA96-AB96 -> 0 | AD96: =+O96+AA96+AB96 -> 0
C97: TOTAL ACTIVOS CORRIENTES | N97: 361 | O97: =SUM(O28:O96) -> 0 | AB97: 271283.69 | AC97: =+O97-AA97-AB97 -> -271283.69 | AD97: =+O97+AA97+AB97 -> 271283.69
C98: ACTIVOS NO CORRIENTES | AC98: =+O98-AA98-AB98 -> 0 | AD98: =+O98+AA98+AB98 -> 0
D99: PROPIEDADES, PLANTA Y EQUIPO | AC99: =+O99-AA99-AB99 -> 0 | AD99: =+O99+AA99+AB99 -> 0
E100: TERRENOS | AC100: =+O100-AA100-AB100 -> 0 | AD100: =+O100+AA100+AB100 -> 0
F101: Costo histórico antes de reexpresiones o revaluaciones | N101: 362 | O101: =SUMIF('3BL ACTUAL'!B:B,N101,'3BL ACTUAL'!E:E) -> 0 | AC101: =+O101-AA101-AB101 -> 0 | AD101: =+O101+AA101+AB101 -> 0
...

Sheet FLUJO ANTERIOR
P1: ANTERIO | Q1: ACTUAL | R1: VARIACIÓN | S1: OPERACIÓN | T1: OPERACIÓN FUENTE | U1: OPERACIÓN USO | V1: INVERSION | W1: INVERSION FUENTE | X1: INVERSION USO | Y1: FINANCIAMIENTO | Z1: FINANCIAMIENTO FUENTE | AA1: FINANCIAMIENTO USO | AB1: ELIMINACIONES | AC1: CONTROL | AD1: CERO | AF1: 2017 | AG1: AÑO ATUAL | AH1: AÑO ANTERIOR
A2: ESTADO DE SITUACIÓN FINANCIERA
B3: ACTIVO | AF3: 2017
C4: ACTIVOS CORRIENTES | AF4: 2017
D5: Efectivo y equivalentes al efectivo | N5: 311 | O5: + | P5: 4632.67 | Q5: 52887.77 | R5: -48255.1 | T5: 0 | U5: 0 | W5: 0 | X5: 0 | Z5: 0 | AA5: 0 | AC5: -48255.1 | AD5: 0 | AE5: 101 | AF5: 311 | AG5: 52887.77 | AH5: 4632.67
D6: CUENTAS Y DOCUMENTOS POR COBRAR CORRIENTES | AG6: 0 | AH6: 0
E7: CUENTAS Y DOCUMENTOS POR COBRAR COMERCIALES CORRIENTES | AG7: 0 | AH7: 0
F8: RELACIONADAS | AG8: 0 | AH8: 0
A9: ______ | B9: ______ | C9: ______ | D9: ______ | E9: ______ | F9: ______ | G9: Locales | N9: 312 | O9: + | P9: 0 | Q9: 0 | R9: 0 | S9: 0 | T9: 0 | U9: 0 | W9: 0 | X9: 0 | Z9: 0 | AA9: 0 | AC9: 0 | AD9: 0 | AE9: 102 | AF9: 312 | AG9: 0 | AH9: 0
G10: Del exterior | N10: 313 | O10: + | P10: 0 | Q10: 0 | R10: 0 | S10: 0 | T10: 0 | U10: 0 | W10: 0 | X10: 0 | Z10: 0 | AA10: 0 | AC10: 0 | AD10: 0 | AE10: 102 | AF10: 313 | AG10: 0 | AH10: 0
G11: (-) Deterioro acumulado del valor de cuentas y documentos por cobrar comerciales por incobrabilidad (provisiones para créditos incobrables) | N11: 314 | O11: - | P11: 0 | Q11: 0 | R11: 0 | S11: 0 | T11: 0 | U11: 0 | W11: 0 | X11: 0 | Z11: 0 | AA11: 0 | AC11: 0 | AD11: 0 | AE11: 102 | AF11: 314 | AG11: 0 | AH11: 0
F12: NO RELACIONADAS | AG12: 0 | AH12: 0
G13: Locales | N13: 315 | O13: + | P13: 0 | Q13: 0 | R13: 0 | S13: 0 | T13: 0 | U13: 0 | W13: 0 | X13: 0 | Z13: 0 | AA13: 0 | AC13: 0 | AD13: 0 | AE13: 102 | AF13: 315 | AG13: 0 | AH13: 0
G14: Del exterior | N14: 316 | O14: + | P14: 0 | Q14: 0 | R14: 0 | S14: 0 | T14: 0 | U14: 0 | W14: 0 | X14: 0 | Z14: 0 | AA14: 0 | AC14: 0 | AD14: 0 | AE14: 102 | AF14: 316 | AG14: 0 | AH14: 0
G15: (-) Deterioro acumulado del valor de cuentas y documentos por cobrar comerciales por incobrabilidad (provisiones para créditos incobrables) | N15: 317 | O15: - | P15: 0 | Q15: 0 | R15: 0 | S15: 0 | T15: 0 | U15: 0 | W15: 0 | X15: 0 | Z15: 0 | AA15: 0 | AC15: 0 | AD15: 0 | AE15: 102 | AF15: 317 | AG15: 0 | AH15: 0
E16: OTRAS CUENTAS Y DOCUMENTOS POR COBRAR CORRIENTES | AG16: 0 | AH16: 0
F17: A ACCIONISTAS, SOCIOS, PARTICIPES, BENEFICIARIOS U OTROS TITULARES DE DERECHOS REPRESENTATIVOS DE CAPITAL | AG17: 0 | AH17: 0
G18: Locales | N18: 318 | O18: + | P18: 0 | Q18: 0 | R18: 0 | S18: 0 | T18: 0 | U18: 0 | W18: 0 | X18: 0 | Z18: 0 | AA18: 0 | AC18: 0 | AD18: 0 | AE18: 102 | AF18: 318 | AG18: 0 | AH18: 0
G19: Del exterior | N19: 319 | O19: + | P19: 0 | Q19: 0 | R19: 0 | S19: 0 | T19: 0 | U19: 0 | W19: 0 | X19: 0 | Z19: 0 | AA19: 0 | AC19: 0 | AD19: 0 | AE19: 102 | AF19: 319 | AG19: 0 | AH19: 0
F20: DIVIDENDOS POR COBRAR | AG20: 0 | AH20: 0
G21: En efectivo | N21: 320 | O21: + | P21: 0 | Q21: 0 | R21: 0 | S21: 0 | T21: 0 | U21: 0 | W21: 0 | X21: 0 | Z21: 0 | AA21: 0 | AC21: 0 | AD21: 0 | AE21: 102 | AF21: 320 | AG21: 0 | AH21: 0
G22: En activos diferentes del efectivo | N22: 321 | O22: + | P22: 0 | Q22: 0 | R22: 0 | S22: 0 | T22: 0 | U22: 0 | W22: 0 | X22: 0 | Z22: 0 | AA22: 0 | AC22: 0 | AD22: 0 | AE22: 102 | AF22: 321 | AG22: 0 | AH22: 0
F23: OTRAS RELACIONADAS | AG23: 0 | AH23: 0
G24: Locales | N24: 322 | O24: + | P24: 0 | Q24: 0 | R24: 0 | S24: 0 | T24: 0 | U24: 0 | W24: 0 | X24: 0 | Z24: 0 | AA24: 0 | AC24: 0 | AD24: 0 | AE24: 102 | AF24: 322 | AG24: 0 | AH24: 0
G25: Del exterior | N25: 323 | O25: + | P25: 0 | Q25: 0 | R25: 0 | S25: 0 | T25: 0 | U25: 0 | W25: 0 | X25: 0 | Z25: 0 | AA25: 0 | AC25: 0 | AD25: 0 | AE25: 102 | AF25: 323 | AG25: 0 | AH25: 0
G26: (-) Deterioro acumulado del valor de otras cuentas y documentos por cobrar por incobrabilidad (provisiones para créditos incobrables) | N26: 324 | O26: - | P26: 0 | Q26: 0 | R26: 0 | S26: 0 | T26: 0 | U26: 0 | W26: 0 | X26: 0 | Z26: 0 | AA26: 0 | AC26: 0 | AD26: 0 | AE26: 102 | AF26: 324 | AG26: 0 | AH26: 0
F27: OTRAS NO RELACIONADAS | AG27: 0 | AH27: 0
G28: Locales | N28: 325 | O28: + | P28: 0 | Q28: 0 | R28: 0 | S28: 0 | T28: 0 | U28: 0 | W28: 0 | X28: 0 | Z28: 0 | AA28: 0 | AC28: 0 | AD28: 0 | AE28: 102 | AF28: 325 | AG28: 0 | AH28: 0 | AI28: 184
G29: Del exterior | N29: 326 | O29: + | P29: 0 | Q29: 0 | R29: 0 | S29: 0 | T29: 0 | U29: 0 | W29: 0 | X29: 0 | Z29: 0 | AA29: 0 | AC29: 0 | AD29: 0 | AE29: 102 | AF29: 326 | AG29: 0 | AH29: 0
G30: (-) Deterioro acumulado del valor de otras cuentas y documentos por cobrar por incobrabilidad (provisiones para créditos incobrables) | N30: 327 | O30: - | P30: 0 | Q30: 0 | R30: 0 | S30: 0 | T30: 0 | U30: 0 | W30: 0 | X30: 0 | Z30: 0 | AA30: 0 | AC30: 0 | AD30: 0 | AE30: 103 | AF30: 327 | AG30: 0 | AH30: 0
D31: OTROS ACTIVOS FINANCIEROS CORRIENTES | AG31: 0 | AH31: 0
E32: A costo amortizado | N32: 328 | O32: + | P32: 0 | Q32: 0 | R32: 0 | S32: 0 | T32: 0 | U32: 0 | W32: 0 | X32: 0 | Z32: 0 | AA32: 0 | AC32: 0 | AD32: 0 | AE32: 103 | AF32: 328 | AG32: 0 | AH32: 0
E33: (-) Deterioro acumulado del valor de otros activos financieros corrientes medidos a costo amortizado (provisiones para créditos incobrables) | N33: 329 | O33: - | P33: 0 | Q33: 0 | R33: 0 | S33: 0 | T33: 0 | U33: 0 | W33: 0 | X33: 0 | Z33: 0 | AA33: 0 | AC33: 0 | AD33: 0 | AE33: 103 | AF33: 329 | AG33: 0 | AH33: 0
E34: A valor razonable | N34: 330 | O34: + | P34: 0 | Q34: 0 | R34: 0 | S34: 0 | T34: 0 | U34: 0 | W34: 0 | X34: 0 | Z34: 0 | AA34: 0 | AC34: 0 | AD34: 0 | AE34: 103 | AF34: 330 | AG34: 0 | AH34: 0
D35: PORCIÓN CORRIENTE DE ARRENDAMIENTOS FINANCIEROS POR COBRAR | AG35: 0 | AH35: 0
E36: Relacionadas | N36: 331 | O36: + | P36: 0 | Q36: 0 | R36: 0 | S36: 0 | T36: 0 | U36: 0 | W36: 0 | X36: 0 | Z36: 0 | AA36: 0 | AC36: 0 | AD36: 0 | AE36: 103 | AF36: 331 | AG36: 0 | AH36: 0
E37: No relacionadas | N37: 332 | O37: + | P37: 0 | Q37: 0 | R37: 0 | S37: 0 | T37: 0 | U37: 0 | W37: 0 | X37: 0 | Z37: 0 | AA37: 0 | AC37: 0 | AD37: 0 | AE37: 103 | AF37: 332 | AG37: 0 | AH37: 0
D38: IMPORTE BRUTO ADEUDADO POR LOS CLIENTES POR EL TRABAJO EJECUTADO EN CONTRATOS DE CONSTRUCCIÓN | AG38: 0 | AH38: 0
E39: Relacionadas | N39: 333 | O39: + | P39: 0 | Q39: 0 | R39: 0 | S39: 0 | T39: 0 | U39: 0 | W39: 0 | X39: 0 | Z39: 0 | AA39: 0 | AC39: 0 | AD39: 0 | AE39: 103 | AF39: 333 | AG39: 0 | AH39: 0
E40: No relacionadas | N40: 334 | O40: + | P40: 0 | Q40: 0 | R40: 0 | S40: 0 | T40: 0 | U40: 0 | W40: 0 | X40: 0 | Z40: 0 | AA40: 0 | AC40: 0 | AD40: 0 | AE40: 103 | AF40: 334 | AG40: 0 | AH40: 0
D41: ACTIVOS POR IMPUESTOS CORRIENTES | AG41: 0 | AH41: 0
E42: Crédito tributario a favor del sujeto pasivo (ISD) | N42: 335 | O42: + | P42: 0 | Q42: 0 | R42: 0 | S42: 0 | T42: 0 | U42: 0 | W42: 0 | X42: 0 | Z42: 0 | AA42: 0 | AC42: 0 | AD42: 0 | AE42: 103 | AF42: 335 | AG42: 0 | AH42: 0
E43: Crédito tributario a favor del sujeto pasivo (IVA) | N43: 336 | O43: + | P43: 0 | Q43: 0 | R43: 0 | S43: 0 | T43: 0 | U43: 0 | W43: 0 | X43: 0 | Z43: 0 | AA43: 0 | AC43: 0 | AD43: 0 | AE43: 103 | AF43: 336 | AG43: 0 | AH43: 0
E44: Crédito tributario a favor del sujeto pasivo (Impuesto a la Renta) | N44: 337 | O44: + | P44: 0 | Q44: 0 | R44: 0 | S44: 0 | T44: 0 | U44: 0 | W44: 0 | X44: 0 | Z44: 0 | AA44: 0 | AC44: 0 | AD44: 0 | AE44: 103 | AF44: 337 | AG44: 0 | AH44: 0
E45: Otros | N45: 338 | O45: + | P45: 666.16 | Q45: 23679.04 | R45: -23012.88 | S45: -23012.88 | T45: 0 | U45: -23012.88 | W45: 0 | X45: 0 | Z45: 0 | AA45: 0 | AC45: -23012.88 | AD45: 0 | AE45: 103 | AF45: 338 | AG45: 23679.04 | AH45: 666.16
D46: INVENTARIOS | AG46: 0 | AH46: 0
E47: Mercaderías en tránsito | N47: 339 | O47: + | P47: 0 | Q47: 0 | R47: 0 | S47: 0 | T47: 0 | U47: 0 | W47: 0 | X47: 0 | Z47: 0 | AA47: 0 | AC47: 0 | AD47: 0 | AE47: 104 | AF47: 339 | AG47: 0 | AH47: 0
E48: Inventario de materia prima (no para la construcción) | N48: 340 | O48: + | P48: 0 | Q48: 0 | R48: 0 | S48: 0 | T48: 0 | U48: 0 | W48: 0 | X48: 0 | Z48: 0 | AA48: 0 | AC48: 0 | AD48: 0 | AE48: 104 | AF48: 340 | AG48: 0 | AH48: 0
E49: Inventario de productos en proceso (excluyendo obras/inmuebles en construcción para la venta) | N49: 341 | O49: + | P49: 279972.59 | Q49: 348653.81 | R49: -68681.22 | S49: -68681.22 | T49: 0 | U49: -68681.22 | W49: 0 | X49: 0 | Z49: 0 | AA49: 0 | AC49: -68681.22 | AD49: 0 | AE49: 104 | AF49: 341 | AG49: 348653.81 | AH49: 279972.59
E50: Inventario de prod. term. y mercad. en almacén (excluyendo obras/inmuebles terminados para la venta) | N50: 342 | O50: + | P50: 0 | Q50: 0 | R50: 0 | S50: 0 | T50: 0 | U50: 0 | W50: 0 | X50: 0 | Z50: 0 | AA50: 0 | AC50: 0 | AD50: 0 | AE50: 104 | AF50: 342 | AG50: 0 | AH50: 0
E51: Inventario de suministros, herramientas, repuestos y materiales (no para la construcción) | N51: 343 | O51: + | P51: 0 | Q51: 0 | R51: 0 | S51: 0 | T51: 0 | U51: 0 | W51: 0 | X51: 0 | Z51: 0 | AA51: 0 | AC51: 0 | AD51: 0 | AE51: 104 | AF51: 343 | AG51: 0 | AH51: 0
E52: Inventario de materia prima, suministros y materiales para la construcción | N52: 344 | O52: + | P52: 0 | Q52: 0 | R52: 0 | S52: 0 | T52: 0 | U52: 0 | W52: 0 | X52: 0 | Z52: 0 | AA52: 0 | AC52: 0 | AD52: 0 | AE52: 104 | AF52: 344 | AG52: 0 | AH52: 0
E53: Inventario de obras/inmuebles en construcción para la venta | N53: 345 | O53: + | P53: 0 | Q53: 0 | R53: 0 | S53: 0 | T53: 0 | U53: 0 | W53: 0 | X53: 0 | Z53: 0 | AA53: 0 | AC53: 0 | AD53: 0 | AE53: 104 | AF53: 345 | AG53: 0 | AH53: 0
E54: Inventario de obras/inmuebles terminados para la venta | N54: 346 | O54: + | P54: 0 | Q54: 0 | R54: 0 | S54: 0 | T54: 0 | U54: 0 | W54: 0 | X54: 0 | Z54: 0 | AA54: 0 | AC54: 0 | AD54: 0 | AE54: 104 | AF54: 346 | AG54: 0 | AH54: 0
E55: (-) Deterioro acumulado del valor de inventarios por ajuste al valor neto realizable | N55: 347 | O55: - | P55: 0 | Q55: 0 | R55: 0 | S55: 0 | T55: 0 | U55: 0 | W55: 0 | X55: 0 | Z55: 0 | AA55: 0 | AC55: 0 | AD55: 0 | AE55: 104 | AF55: 347 | AG55: 0 | AH55: 0
D56: ACTIVOS NO CORRIENTES MANTENIDOS PARA LA VENTA | AG56: 0 | AH56: 0
E57: Costo | N57: 348 | O57: + | P57: 0 | Q57: 0 | R57: 0 | T57: 0 | U57: 0 | V57: 0 | W57: 0 | X57: 0 | Z57: 0 | AA57: 0 | AC57: 0 | AD57: 0 | AE57: 104 | AF57: 348 | AG57: 0 | AH57: 0
E58: (-) Deterioro acumulado del valor de activos no corrientes mantenidos para la venta | N58: 349 | O58: - | P58: 0 | Q58: 0 | R58: 0 | S58: 0 | T58: 0 | U58: 0 | W58: 0 | X58: 0 | Z58: 0 | AA58: 0 | AC58: 0 | AD58: 0 | AE58: 104 | AF58: 349 | AG58: 0 | AH58: 0
D59: ACTIVOS BIOLÓGICOS | AG59: 0 | AH59: 0
E60: PLANTAS VIVAS Y FRUTOS EN CRECIMIENTO | AG60: 0 | AH60: 0
F61: A costo | N61: 350 | O61: + | P61: 0 | Q61: 0 | R61: 0 | T61: 0 | U61: 0 | V61: 0 | W61: 0 | X61: 0 | Z61: 0 | AA61: 0 | AC61: 0 | AD61: 0 | AE61: 104 | AF61: 350 | AG61: 0 | AH61: 0
F62: (-) Deterioro acumulado del valor de activos biológicos medidos a costo | N62: 351 | O62: - | P62: 0 | Q62: 0 | R62: 0 | S62: 0 | T62: 0 | U62: 0 | W62: 0 | X62: 0 | Z62: 0 | AA62: 0 | AC62: 0 | AD62: 0 | AE62: 104 | AF62: 351 | AG62: 0 | AH62: 0
F63: A valor razonable menos los costos de venta | N63: 352 | O63: + | P63: 0 | Q63: 0 | R63: 0 | T63: 0 | U63: 0 | V63: 0 | W63: 0 | X63: 0 | Z63: 0 | AA63: 0 | AC63: 0 | AD63: 0 | AE63: 104 | AF63: 352 | AG63: 0 | AH63: 0
E64: ANIMALES VIVOS | AG64: 0 | AH64: 0
F65: A costo | N65: 353 | O65: + | P65: 0 | Q65: 0 | R65: 0 | T65: 0 | U65: 0 | V65: 0 | W65: 0 | X65: 0 | Z65: 0 | AA65: 0 | AC65: 0 | AD65: 0 | AE65: 104 | AF65: 353 | AG65: 0 | AH65: 0
F66: (-) Deterioro acumulado del valor de activos biológicos medidos a costo | N66: 354 | O66: - | P66: 0 | Q66: 0 | R66: 0 | S66: 0 | T66: 0 | U66: 0 | W66: 0 | X66: 0 | Z66: 0 | AA66: 0 | AC66: 0 | AD66: 0 | AE66: 104 | AF66: 354 | AG66: 0 | AH66: 0
F67: A valor razonable menos los costos de venta | N67: 355 | O67: + | P67: 0 | Q67: 0 | R67: 0 | T67: 0 | U67: 0 | V67: 0 | W67: 0 | X67: 0 | Z67: 0 | AA67: 0 | AC67: 0 | AD67: 0 | AE67: 104 | AF67: 355 | AG67: 0 | AH67: 0
D68: GASTOS PAGADOS POR ANTICIPADO (PREPAGADOS) | AG68: 0 | AH68: 0
E69: Propaganda y publicidad prepagada | N69: 356 | O69: + | P69: 0 | Q69: 0 | R69: 0 | S69: 0 | T69: 0 | U69: 0 | W69: 0 | X69: 0 | Z69: 0 | AA69: 0 | AC69: 0 | AD69: 0 | AE69: 105 | AF69: 356 | AG69: 0 | AH69: 0
E70: Arrendamientos operativos pagados por anticipado | N70: 357 | O70: + | P70: 0 | Q70: 0 | R70: 0 | S70: 0 | T70: 0 | U70: 0 | W70: 0 | X70: 0 | Z70: 0 | AA70: 0 | AC70: 0 | AD70: 0 | AE70: 105 | AF70: 357 | AG70: 0 | AH70: 0
E71: Primas de seguro pagadas por anticipado | N71: 358 | O71: + | P71: 0 | Q71: 0 | R71: 0 | S71: 0 | T71: 0 | U71: 0 | W71: 0 | X71: 0 | Z71: 0 | AA71: 0 | AC71: 0 | AD71: 0 | AE71: 105 | AF71: 358 | AG71: 0 | AH71: 0
E72: Otros | N72: 359 | O72: + | P72: 0 | Q72: 0 | R72: 0 | S72: 0 | T72: 0 | U72: 0 | W72: 0 | X72: 0 | Z72: 0 | AA72: 0 | AC72: 0 | AD72: 0 | AE72: 105 | AF72: 359 | AG72: 0 | AH72: 0
D73: Otros Activos Corrientes | N73: 360 | O73: + | P73: 0 | Q73: 0 | R73: 0 | S73: 0 | T73: 0 | U73: 0 | W73: 0 | X73: 0 | Z73: 0 | AA73: 0 | AC73: 0 | AD73: 0 | AE73: 105 | AF73: 360 | AG73: 0 | AH73: 0
C74: TOTAL ACTIVOS CORRIENTES | N74: 361 | R74: 0 | S74: 0 | T74: 0 | U74: 0 | W74: 0 | X74: 0 | Z74: 0 | AA74: 0 | AC74: 0 | AD74: 0 | AE74: 105 | AF74: 361 | AG74: 0 | AH74: 0
C75: ACTIVOS NO CORRIENTES | R75: 0 | T75: 0 | U75: 0 | W75: 0 | X75: 0 | Z75: 0 | AA75: 0 | AC75: 0 | AD75: 0 | AG75: 0 | AH75: 0
D76: PROPIEDADES, PLANTA Y EQUIPO | AG76: 0 | AH76: 0
E77: TERRENOS | AG77: 0 | AH77: 0
F78: Costo histórico antes de reexpresiones o revaluaciones | N78: 362 | O78: + | P78: 0 | Q78: 0 | R78: 0 | T78: 0 | U78: 0 | V78: 0 | W78: 0 | X78: 0 | Z78: 0 | AA78: 0 | AC78: 0 | AD78: 0 | AE78: 111 | AF78: 362 | AG78: 0 | AH78: 0
F79: Ajuste acumulado por reexpresiones o revaluaciones | G79: ajuste acumulado por reexpresiones o revaluaciones | K79: ajuste acumulado por reexpresiones o revaluaciones | L79: ajuste acumulado por reexpresiones o revaluaciones | M79: ajuste acumulado por reexpresiones o revaluaciones | N79: 363 | O79: + | P79: 0 | Q79: 0 | R79: 0 | T79: 0 | U79: 0 | V79: 0 | W79: 0 | X79: 0 | Z79: 0 | AA79: 0 | AB79: 0 | AC79: 0 | AD79: 0 | AE79: 111 | AF79: 363 | AG79: 0 | AH79: 0
E80: EDIFICIOS Y OTROS INMUEBLES (EXCEPTO TERRENOS) | AG80: 0 | AH80: 0
F81: Costo histórico antes de reexpresiones o revaluaciones | N81: 364 | O81: + | P81: 0 | Q81: 0 | R81: 0 | T81: 0 | U81: 0 | V81: 0 | W81: 0 | X81: 0 | Z81: 0 | AA81: 0 | AC81: 0 | AD81: 0 | AE81: 111 | AF81: 364 | AG81: 0 | AH81: 0
F82: Ajuste acumulado por reexpresiones o revaluaciones | G82: ajuste acumulado por reexpresiones o revaluaciones | K82: ajuste acumulado por reexpresiones o revaluaciones | L82: ajuste acumulado por reexpresiones o revaluaciones | M82: ajuste acumulado por reexpresiones o revaluaciones | N82: 365 | O82: + | P82: 0 | Q82: 0 | R82: 0 | T82: 0 | U82: 0 | V82: 0 | W82: 0 | X82: 0 | Z82: 0 | AA82: 0 | AB82: 0 | AC82: 0 | AD82: 0 | AE82: 111 | AF82: 365 | AG82: 0 | AH82: 0
E83: NAVES, AERONAVES, BARCAZAS Y SIMILARES | AG83: 0 | AH83: 0
F84: Costo histórico antes de reexpresiones o revaluaciones | N84: 366 | O84: + | P84: 0 | Q84: 0 | R84: 0 | T84: 0 | U84: 0 | V84: 0 | W84: 0 | X84: 0 | Z84: 0 | AA84: 0 | AC84: 0 | AD84: 0 | AE84: 111 | AF84: 366 | AG84: 0 | AH84: 0
F85: Ajuste acumulado por reexpresiones o revaluaciones | G85: ajuste acumulado por reexpresiones o revaluaciones | K85: ajuste acumulado por reexpresiones o revaluaciones | L85: ajuste acumulado por reexpresiones o revaluaciones | M85: ajuste acumulado por reexpresiones o revaluaciones | N85: 367 | O85: + | P85: 0 | Q85: 0 | R85: 0 | T85: 0 | U85: 0 | V85: 0 | W85: 0 | X85: 0 | Z85: 0 | AA85: 0 | AC85: 0 | AD85: 0 | AE85: 111 | AF85: 367 | AG85: 0 | AH85: 0
E86: MAQUINARIA, EQUIPO, INSTALACIONES Y ADECUACIONES | AG86: 0 | AH86: 0
F87: Costo histórico antes de reexpresiones o revaluaciones | N87: 368 | O87: + | P87: 266077.46 | Q87: 408105.13 | R87: -142027.67 | T87: 0 | U87: 0 | V87: -142027.67 | W87: 0 | X87: -142027.67 | Z87: 0 | AA87: 0 | AC87: -142027.67 | AD87: 0 | AE87: 111 | AF87: 368 | AG87: 408105.13 | AH87: 266077.46
F88: Ajuste acumulado por reexpresiones o revaluaciones | G88: ajuste acumulado por reexpresiones o revaluaciones | N88: 369 | O88: + | P88: 0 | Q88: 0 | R88: 0 | T88: 0 | U88: 0 | V88: 0 | W88: 0 | X88: 0 | Z88: 0 | AA88: 0 | AC88: 0 | AD88: 0 | AE88: 111 | AF88: 369 | AG88: 0 | AH88: 0
E89: PLANTAS PRODUCTORAS (AGRICULTURA) | AG89: 0 | AH89: 0
F90: Costo histórico antes de reexpresiones o revaluaciones | N90: 370 | O90: + | P90: 0 | Q90: 0 | R90: 0 | T90: 0 | U90: 0 | V90: 0 | W90: 0 | X90: 0 | Z90: 0 | AA90: 0 | AC90: 0 | AD90: 0 | AE90: 111 | AF90: 370 | AG90: 0 | AH90: 0
F91: Ajuste acumulado por reexpresiones o revaluaciones | N91: 371 | O91: + | P91: 0 | Q91: 0 | R91: 0 | T91: 0 | U91: 0 | V91: 0 | W91: 0 | X91: 0 | Z91: 0 | AA91: 0 | AC91: 0 | AD91: 0 | AE91: 111 | AF91: 371 | AG91: 0 | AH91: 0
E92: Construcciones en Curso y Otros Activos en Tránsito | N92: 372 | O92: + | P92: 317737.03 | Q92: 454254.09 | R92: -136517.06 | T92: 0 | U92: 0 | V92: -136517.06 | W92: 0 | X92: -136517.06 | Z92: 0 | AA92: 0 | AC92: -136517.06 | AD92: 0 | AE92: 111 | AF92: 372 | AG92: 454254.09 | AH92: 317737.03
E93: Muebles y enseres | N93: 373 | O93: + | P93: 0 | Q93: 0 | R93: 0 | T93: 0 | U93: 0 | V93: 0 | W93: 0 | X93: 0 | Z93: 0 | AA93: 0 | AC93: 0 | AD93: 0 | AE93: 111 | AF93: 373 | AG93: 0 | AH93: 0
E94: Equipo de Computación | N94: 374 | O94: + | P94: 0 | Q94: 500 | R94: -500 | T94: 0 | U94: 0 | V94: -500 | W94: 0 | X94: -500 | Z94: 0 | AA94: 0 | AC94: -500 | AD94: 0 | AE94: 111 | AF94: 374 | AG94: 500 | AH94: 0
E95: Vehículos, Equipo de Transporte y Caminero Móvil | N95: 375 | O95: + | P95: 0 | Q95: 26500 | R95: -26500 | T95: 0 | U95: 0 | V95: -26500 | W95: 0 | X95: -26500 | Z95: 0 | AA95: 0 | AC95: -26500 | AD95: 0 | AE95: 111 | AF95: 375 | AG95: 26500 | AH95: 0
E96: PROPIEDADES, PLANTA Y EQUIPO POR CONTRATOS DE ARRENDAMIENTO FINANCIERO | AG96: 0 | AH96: 0
F97: Terrenos | N97: 376 | O97: + | P97: 0 | Q97: 0 | R97: 0 | T97: 0 | U97: 0 | V97: 0 | W97: 0 | X97: 0 | Z97: 0 | AA97: 0 | AC97: 0 | AD97: 0 | AE97: 111 | AF97: 376 | AG97: 0 | AH97: 0
F98: Edificios y otros inmuebles (excepto terrenos) | G98: edificios y otros inmuebles (excepto terrenos) | K98: edificios y otros inmuebles (excepto terrenos) | L98: edificios y otros inmuebles (excepto terrenos) | M98: edificios y otros inmuebles (excepto terrenos) | N98: 377 | O98: + | P98: 0 | Q98: 0 | R98: 0 | T98: 0 | U98: 0 | V98: 0 | W98: 0 | X98: 0 | Z98: 0 | AA98: 0 | AC98: 0 | AD98: 0 | AE98: 111 | AF98: 377 | AG98: 0 | AH98: 0
F99: Naves, aeronaves, barcazas y similares | G99: naves, aeronaves, barcazas y similares | K99: naves, aeronaves, barcazas y similares | L99: naves, aeronaves, barcazas y similares | M99: naves, aeronaves, barcazas y similares | N99: 378 | O99: + | P99: 0 | Q99: 0 | R99: 0 | T99: 0 | U99: 0 | V99: 0 | W99: 0 | X99: 0 | Z99: 0 | AA99: 0 | AC99: 0 | AD99: 0 | AE99: 111 | AF99: 378 | AG99: 0 | AH99: 0
F100: Maquinaria, equipo, instalaciones y adecuaciones | G100: maquinaria, equipo, instalaciones y adecuaciones | K100: maquinaria, equipo, instalaciones y adecuaciones | L100: maquinaria, equipo, instalaciones y adecuaciones | M100: maquinaria, equipo, instalaciones y adecuaciones | N100: 379 | O100: + | P100: 0 | Q100: 0 | R100: 0 | T100: 0 | U100: 0 | V100: 0 | W100: 0 | X100: 0 | Z100: 0 | AA100: 0 | AC100: 0 | AD100: 0 | AE100: 111 | AF100: 379 | AG100: 0 | AH100: 0
...

Sheet FLUJO ACTUAL
P1: ANTERIO | Q1: ACTUAL | R1: VARIACIÓN | S1: OPERACIÓN | T1: OPERACIÓN FUENTE | U1: OPERACIÓN USO | V1: INVERSION | W1: INVERSION FUENTE | X1: INVERSION USO | Y1: FINANCIAMIENTO | Z1: FINANCIAMIENTO FUENTE | AA1: FINANCIAMIENTO USO | AB1: ELIMINACIONES | AC1: CONTROL | AD1: CERO | AF1: 2017 | AG1: AÑO ATUAL | AH1: AÑO ANTERIOR
A2: ESTADO DE SITUACIÓN FINANCIERA
B3: ACTIVO | AF3: 2017
C4: ACTIVOS CORRIENTES | AF4: 2017
D5: Efectivo y equivalentes al efectivo | N5: 311 | O5: + | P5: =SUMIF(AF:AF,N5,AH:AH) -> 21075.33 | Q5: =SUMIF(AF:AF,N5,AG:AG) -> 0 | R5: =+P5-Q5 -> 21075.33 | T5: =IF(S5>0,S5,0) -> 0 | U5: =IF(S5>0,0,S5) -> 0 | W5: =IF(V5>0,V5,0) -> 0 | X5: =IF(V5>0,0,V5) -> 0 | Z5: =IF(Y5>0,Y5,0) -> 0 | AA5: =IF(Y5>0,0,Y5) -> 0 | AC5: =+Y5+V5+S5+R5 -> 21075.33 | AD5: =+AC5-R5 -> 0 | AE5: 101 | AF5: 311 | AG5: =SUMIF('3BL ACTUAL'!B:B,AF5,'3BL ACTUAL'!E:E) -> 0 | AH5: =SUMIF('1 BL anterior'!B:B,AF5,'1 BL anterior'!E:E) -> 21075.33
D6: CUENTAS Y DOCUMENTOS POR COBRAR CORRIENTES | AG6: =SUMIF('3BL ACTUAL'!B:B,AF6,'3BL ACTUAL'!E:E) -> 0 | AH6: =SUMIF('1 BL anterior'!B:B,AF6,'1 BL anterior'!E:E) -> 0
E7: CUENTAS Y DOCUMENTOS POR COBRAR COMERCIALES CORRIENTES | AG7: =SUMIF('3BL ACTUAL'!B:B,AF7,'3BL ACTUAL'!E:E) -> 0 | AH7: =SUMIF('1 BL anterior'!B:B,AF7,'1 BL anterior'!E:E) -> 0
F8: RELACIONADAS | AG8: =SUMIF('3BL ACTUAL'!B:B,AF8,'3BL ACTUAL'!E:E) -> 0 | AH8: =SUMIF('1 BL anterior'!B:B,AF8,'1 BL anterior'!E:E) -> 0
A9: ______ | B9: ______ | C9: ______ | D9: ______ | E9: ______ | F9: ______ | G9: Locales | N9: 312 | O9: + | P9: =SUMIF(AF:AF,N9,AH:AH) -> 0 | Q9: =SUMIF(AF:AF,N9,AG:AG) -> 0 | R9: =+P9-Q9 -> 0 | S9: =+R9 -> 0 | T9: =IF(S9>0,S9,0) -> 0 | U9: =IF(S9>0,0,S9) -> 0 | W9: =IF(V9>0,V9,0) -> 0 | X9: =IF(V9>0,0,V9) -> 0 | Z9: =IF(Y9>0,Y9,0) -> 0 | AA9: =IF(Y9>0,0,Y9) -> 0 | AC9: =+Y9+V9+S9+-AB9 -> 0 | AD9: =+AC9-R9 -> 0 | AE9: 102 | AF9: 312 | AG9: =SUMIF('3BL ACTUAL'!B:B,AF9,'3BL ACTUAL'!E:E) -> 0 | AH9: =SUMIF('1 BL anterior'!B:B,AF9,'1 BL anterior'!E:E) -> 0
G10: Del exterior | N10: 313 | O10: + | P10: =SUMIF(AF:AF,N10,AH:AH) -> 0 | Q10: =SUMIF(AF:AF,N10,AG:AG) -> 0 | R10: =+P10-Q10 -> 0 | S10: =+R10 -> 0 | T10: =IF(S10>0,S10,0) -> 0 | U10: =IF(S10>0,0,S10) -> 0 | W10: =IF(V10>0,V10,0) -> 0 | X10: =IF(V10>0,0,V10) -> 0 | Z10: =IF(Y10>0,Y10,0) -> 0 | AA10: =IF(Y10>0,0,Y10) -> 0 | AC10: =+Y10+V10+S10+-AB10 -> 0 | AD10: =+AC10-R10 -> 0 | AE10: 102 | AF10: 313 | AG10: =SUMIF('3BL ACTUAL'!B:B,AF10,'3BL ACTUAL'!E:E) -> 0 | AH10: =SUMIF('1 BL anterior'!B:B,AF10,'1 BL anterior'!E:E) -> 0
G11: (-) Deterioro acumulado del valor de cuentas y documentos por cobrar comerciales por incobrabilidad (provisiones para créditos incobrables) | N11: 314 | O11: - | P11: =SUMIF(AF:AF,N11,AH:AH) -> 0 | Q11: =SUMIF(AF:AF,N11,AG:AG) -> 0 | R11: =+P11-Q11 -> 0 | S11: =+R11 -> 0 | T11: =IF(S11>0,S11,0) -> 0 | U11: =IF(S11>0,0,S11) -> 0 | W11: =IF(V11>0,V11,0) -> 0 | X11: =IF(V11>0,0,V11) -> 0 | Z11: =IF(Y11>0,Y11,0) -> 0 | AA11: =IF(Y11>0,0,Y11) -> 0 | AC11: =+Y11+V11+S11+-AB11 -> 0 | AD11: =+AC11-R11 -> 0 | AE11: 102 | AF11: 314 | AG11: =SUMIF('3BL ACTUAL'!B:B,AF11,'3BL ACTUAL'!E:E) -> 0 | AH11: =SUMIF('1 BL anterior'!B:B,AF11,'1 BL anterior'!E:E) -> 0
F12: NO RELACIONADAS | AG12: =SUMIF('3BL ACTUAL'!B:B,AF12,'3BL ACTUAL'!E:E) -> 0 | AH12: =SUMIF('1 BL anterior'!B:B,AF12,'1 BL anterior'!E:E) -> 0
G13: Locales | N13: 315 | O13: + | P13: =SUMIF(AF:AF,N13,AH:AH) -> 0 | Q13: =SUMIF(AF:AF,N13,AG:AG) -> 0 | R13: =+P13-Q13 -> 0 | S13: =+R13 -> 0 | T13: =IF(S13>0,S13,0) -> 0 | U13: =IF(S13>0,0,S13) -> 0 | W13: =IF(V13>0,V13,0) -> 0 | X13: =IF(V13>0,0,V13) -> 0 | Z13: =IF(Y13>0,Y13,0) -> 0 | AA13: =IF(Y13>0,0,Y13) -> 0 | AC13: =+Y13+V13+S13+-AB13 -> 0 | AD13: =+AC13-R13 -> 0 | AE13: 102 | AF13: 315 | AG13: =SUMIF('3BL ACTUAL'!B:B,AF13,'3BL ACTUAL'!E:E) -> 0 | AH13: =SUMIF('1 BL anterior'!B:B,AF13,'1 BL anterior'!E:E) -> 0
G14: Del exterior | N14: 316 | O14: + | P14: =SUMIF(AF:AF,N14,AH:AH) -> 0 | Q14: =SUMIF(AF:AF,N14,AG:AG) -> 0 | R14: =+P14-Q14 -> 0 | S14: =+R14 -> 0 | T14: =IF(S14>0,S14,0) -> 0 | U14: =IF(S14>0,0,S14) -> 0 | W14: =IF(V14>0,V14,0) -> 0 | X14: =IF(V14>0,0,V14) -> 0 | Z14: =IF(Y14>0,Y14,0) -> 0 | AA14: =IF(Y14>0,0,Y14) -> 0 | AC14: =+Y14+V14+S14+-AB14 -> 0 | AD14: =+AC14-R14 -> 0 | AE14: 102 | AF14: 316 | AG14: =SUMIF('3BL ACTUAL'!B:B,AF14,'3BL ACTUAL'!E:E) -> 0 | AH14: =SUMIF('1 BL anterior'!B:B,AF14,'1 BL anterior'!E:E) -> 0
G15: (-) Deterioro acumulado del valor de cuentas y documentos por cobrar comerciales por incobrabilidad (provisiones para créditos incobrables) | N15: 317 | O15: - | P15: =SUMIF(AF:AF,N15,AH:AH) -> 0 | Q15: =SUMIF(AF:AF,N15,AG:AG) -> 0 | R15: =+P15-Q15 -> 0 | S15: =+R15 -> 0 | T15: =IF(S15>0,S15,0) -> 0 | U15: =IF(S15>0,0,S15) -> 0 | W15: =IF(V15>0,V15,0) -> 0 | X15: =IF(V15>0,0,V15) -> 0 | Z15: =IF(Y15>0,Y15,0) -> 0 | AA15: =IF(Y15>0,0,Y15) -> 0 | AC15: =+Y15+V15+S15+-AB15 -> 0 | AD15: =+AC15-R15 -> 0 | AE15: 102 | AF15: 317 | AG15: =SUMIF('3BL ACTUAL'!B:B,AF15,'3BL ACTUAL'!E:E) -> 0 | AH15: =SUMIF('1 BL anterior'!B:B,AF15,'1 BL anterior'!E:E) -> 0
E16: OTRAS CUENTAS Y DOCUMENTOS POR COBRAR CORRIENTES | AG16: =SUMIF('3BL ACTUAL'!B:B,AF16,'3BL ACTUAL'!E:E) -> 0 | AH16: =SUMIF('1 BL anterior'!B:B,AF16,'1 BL anterior'!E:E) -> 0
F17: A ACCIONISTAS, SOCIOS, PARTICIPES, BENEFICIARIOS U OTROS TITULARES DE DERECHOS REPRESENTATIVOS DE CAPITAL | AG17: =SUMIF('3BL ACTUAL'!B:B,AF17,'3BL ACTUAL'!E:E) -> 0 | AH17: =SUMIF('1 BL anterior'!B:B,AF17,'1 BL anterior'!E:E) -> 0
G18: Locales | N18: 318 | O18: + | P18: =SUMIF(AF:AF,N18,AH:AH) -> 0 | Q18: =SUMIF(AF:AF,N18,AG:AG) -> 0 | R18: =+P18-Q18 -> 0 | S18: =+R18 -> 0 | T18: =IF(S18>0,S18,0) -> 0 | U18: =IF(S18>0,0,S18) -> 0 | W18: =IF(V18>0,V18,0) -> 0 | X18: =IF(V18>0,0,V18) -> 0 | Z18: =IF(Y18>0,Y18,0) -> 0 | AA18: =IF(Y18>0,0,Y18) -> 0 | AC18: =+Y18+V18+S18+-AB18 -> 0 | AD18: =+AC18-R18 -> 0 | AE18: 102 | AF18: 318 | AG18: =SUMIF('3BL ACTUAL'!B:B,AF18,'3BL ACTUAL'!E:E) -> 0 | AH18: =SUMIF('1 BL anterior'!B:B,AF18,'1 BL anterior'!E:E) -> 0
G19: Del exterior | N19: 319 | O19: + | P19: =SUMIF(AF:AF,N19,AH:AH) -> 0 | Q19: =SUMIF(AF:AF,N19,AG:AG) -> 0 | R19: =+P19-Q19 -> 0 | S19: =+R19 -> 0 | T19: =IF(S19>0,S19,0) -> 0 | U19: =IF(S19>0,0,S19) -> 0 | W19: =IF(V19>0,V19,0) -> 0 | X19: =IF(V19>0,0,V19) -> 0 | Z19: =IF(Y19>0,Y19,0) -> 0 | AA19: =IF(Y19>0,0,Y19) -> 0 | AC19: =+Y19+V19+S19+-AB19 -> 0 | AD19: =+AC19-R19 -> 0 | AE19: 102 | AF19: 319 | AG19: =SUMIF('3BL ACTUAL'!B:B,AF19,'3BL ACTUAL'!E:E) -> 0 | AH19: =SUMIF('1 BL anterior'!B:B,AF19,'1 BL anterior'!E:E) -> 0
F20: DIVIDENDOS POR COBRAR | AG20: =SUMIF('3BL ACTUAL'!B:B,AF20,'3BL ACTUAL'!E:E) -> 0 | AH20: =SUMIF('1 BL anterior'!B:B,AF20,'1 BL anterior'!E:E) -> 0
G21: En efectivo | N21: 320 | O21: + | P21: =SUMIF(AF:AF,N21,AH:AH) -> 0 | Q21: =SUMIF(AF:AF,N21,AG:AG) -> 0 | R21: =+P21-Q21 -> 0 | S21: =+R21 -> 0 | T21: =IF(S21>0,S21,0) -> 0 | U21: =IF(S21>0,0,S21) -> 0 | W21: =IF(V21>0,V21,0) -> 0 | X21: =IF(V21>0,0,V21) -> 0 | Z21: =IF(Y21>0,Y21,0) -> 0 | AA21: =IF(Y21>0,0,Y21) -> 0 | AC21: =+Y21+V21+S21+-AB21 -> 0 | AD21: =+AC21-R21 -> 0 | AE21: 102 | AF21: 320 | AG21: =SUMIF('3BL ACTUAL'!B:B,AF21,'3BL ACTUAL'!E:E) -> 0 | AH21: =SUMIF('1 BL anterior'!B:B,AF21,'1 BL anterior'!E:E) -> 0
G22: En activos diferentes del efectivo | N22: 321 | O22: + | P22: =SUMIF(AF:AF,N22,AH:AH) -> 0 | Q22: =SUMIF(AF:AF,N22,AG:AG) -> 0 | R22: =+P22-Q22 -> 0 | S22: =+R22 -> 0 | T22: =IF(S22>0,S22,0) -> 0 | U22: =IF(S22>0,0,S22) -> 0 | W22: =IF(V22>0,V22,0) -> 0 | X22: =IF(V22>0,0,V22) -> 0 | Z22: =IF(Y22>0,Y22,0) -> 0 | AA22: =IF(Y22>0,0,Y22) -> 0 | AC22: =+Y22+V22+S22+-AB22 -> 0 | AD22: =+AC22-R22 -> 0 | AE22: 102 | AF22: 321 | AG22: =SUMIF('3BL ACTUAL'!B:B,AF22,'3BL ACTUAL'!E:E) -> 0 | AH22: =SUMIF('1 BL anterior'!B:B,AF22,'1 BL anterior'!E:E) -> 0
F23: OTRAS RELACIONADAS | AG23: =SUMIF('3BL ACTUAL'!B:B,AF23,'3BL ACTUAL'!E:E) -> 0 | AH23: =SUMIF('1 BL anterior'!B:B,AF23,'1 BL anterior'!E:E) -> 0
G24: Locales | N24: 322 | O24: + | P24: =SUMIF(AF:AF,N24,AH:AH) -> 0 | Q24: =SUMIF(AF:AF,N24,AG:AG) -> 0 | R24: =+P24-Q24 -> 0 | S24: =+R24 -> 0 | T24: =IF(S24>0,S24,0) -> 0 | U24: =IF(S24>0,0,S24) -> 0 | W24: =IF(V24>0,V24,0) -> 0 | X24: =IF(V24>0,0,V24) -> 0 | Z24: =IF(Y24>0,Y24,0) -> 0 | AA24: =IF(Y24>0,0,Y24) -> 0 | AC24: =+Y24+V24+S24+-AB24 -> 0 | AD24: =+AC24-R24 -> 0 | AE24: 102 | AF24: 322 | AG24: =SUMIF('3BL ACTUAL'!B:B,AF24,'3BL ACTUAL'!E:E) -> 0 | AH24: =SUMIF('1 BL anterior'!B:B,AF24,'1 BL anterior'!E:E) -> 0
G25: Del exterior | N25: 323 | O25: + | P25: =SUMIF(AF:AF,N25,AH:AH) -> 0 | Q25: =SUMIF(AF:AF,N25,AG:AG) -> 0 | R25: =+P25-Q25 -> 0 | S25: =+R25 -> 0 | T25: =IF(S25>0,S25,0) -> 0 | U25: =IF(S25>0,0,S25) -> 0 | W25: =IF(V25>0,V25,0) -> 0 | X25: =IF(V25>0,0,V25) -> 0 | Z25: =IF(Y25>0,Y25,0) -> 0 | AA25: =IF(Y25>0,0,Y25) -> 0 | AC25: =+Y25+V25+S25+-AB25 -> 0 | AD25: =+AC25-R25 -> 0 | AE25: 102 | AF25: 323 | AG25: =SUMIF('3BL ACTUAL'!B:B,AF25,'3BL ACTUAL'!E:E) -> 0 | AH25: =SUMIF('1 BL anterior'!B:B,AF25,'1 BL anterior'!E:E) -> 0
G26: (-) Deterioro acumulado del valor de otras cuentas y documentos por cobrar por incobrabilidad (provisiones para créditos incobrables) | N26: 324 | O26: - | P26: =SUMIF(AF:AF,N26,AH:AH) -> 0 | Q26: =SUMIF(AF:AF,N26,AG:AG) -> 0 | R26: =+P26-Q26 -> 0 | S26: =+R26 -> 0 | T26: =IF(S26>0,S26,0) -> 0 | U26: =IF(S26>0,0,S26) -> 0 | W26: =IF(V26>0,V26,0) -> 0 | X26: =IF(V26>0,0,V26) -> 0 | Z26: =IF(Y26>0,Y26,0) -> 0 | AA26: =IF(Y26>0,0,Y26) -> 0 | AC26: =+Y26+V26+S26+-AB26 -> 0 | AD26: =+AC26-R26 -> 0 | AE26: 102 | AF26: 324 | AG26: =SUMIF('3BL ACTUAL'!B:B,AF26,'3BL ACTUAL'!E:E) -> 0 | AH26: =SUMIF('1 BL anterior'!B:B,AF26,'1 BL anterior'!E:E) -> 0
F27: OTRAS NO RELACIONADAS | AG27: =SUMIF('3BL ACTUAL'!B:B,AF27,'3BL ACTUAL'!E:E) -> 0 | AH27: =SUMIF('1 BL anterior'!B:B,AF27,'1 BL anterior'!E:E) -> 0
G28: Locales | N28: 325 | O28: + | P28: =SUMIF(AF:AF,N28,AH:AH) -> 0 | Q28: =SUMIF(AF:AF,N28,AG:AG) -> 0 | R28: =+P28-Q28 -> 0 | S28: =+R28 -> 0 | T28: =IF(S28>0,S28,0) -> 0 | U28: =IF(S28>0,0,S28) -> 0 | W28: =IF(V28>0,V28,0) -> 0 | X28: =IF(V28>0,0,V28) -> 0 | Z28: =IF(Y28>0,Y28,0) -> 0 | AA28: =IF(Y28>0,0,Y28) -> 0 | AC28: =+Y28+V28+S28+-AB28 -> 0 | AD28: =+AC28-R28 -> 0 | AE28: 102 | AF28: 325 | AG28: =SUMIF('3BL ACTUAL'!B:B,AF28,'3BL ACTUAL'!E:E) -> 0 | AH28: =SUMIF('1 BL anterior'!B:B,AF28,'1 BL anterior'!E:E) -> 0 | AI28: 184
G29: Del exterior | N29: 326 | O29: + | P29: =SUMIF(AF:AF,N29,AH:AH) -> 0 | Q29: =SUMIF(AF:AF,N29,AG:AG) -> 0 | R29: =+P29-Q29 -> 0 | S29: =+R29 -> 0 | T29: =IF(S29>0,S29,0) -> 0 | U29: =IF(S29>0,0,S29) -> 0 | W29: =IF(V29>0,V29,0) -> 0 | X29: =IF(V29>0,0,V29) -> 0 | Z29: =IF(Y29>0,Y29,0) -> 0 | AA29: =IF(Y29>0,0,Y29) -> 0 | AC29: =+Y29+V29+S29+-AB29 -> 0 | AD29: =+AC29-R29 -> 0 | AE29: 102 | AF29: 326 | AG29: =SUMIF('3BL ACTUAL'!B:B,AF29,'3BL ACTUAL'!E:E) -> 0 | AH29: =SUMIF('1 BL anterior'!B:B,AF29,'1 BL anterior'!E:E) -> 0
G30: (-) Deterioro acumulado del valor de otras cuentas y documentos por cobrar por incobrabilidad (provisiones para créditos incobrables) | N30: 327 | O30: - | P30: =SUMIF(AF:AF,N30,AH:AH) -> 0 | Q30: =SUMIF(AF:AF,N30,AG:AG) -> 0 | R30: =+P30-Q30 -> 0 | S30: =+R30+AB30 -> 0 | T30: =IF(S30>0,S30,0) -> 0 | U30: =IF(S30>0,0,S30) -> 0 | W30: =IF(V30>0,V30,0) -> 0 | X30: =IF(V30>0,0,V30) -> 0 | Z30: =IF(Y30>0,Y30,0) -> 0 | AA30: =IF(Y30>0,0,Y30) -> 0 | AC30: =+Y30+V30+S30+-AB30 -> 0 | AD30: =+AC30-R30 -> 0 | AE30: 103 | AF30: 327 | AG30: =SUMIF('3BL ACTUAL'!B:B,AF30,'3BL ACTUAL'!E:E) -> 0 | AH30: =SUMIF('1 BL anterior'!B:B,AF30,'1 BL anterior'!E:E) -> 0
D31: OTROS ACTIVOS FINANCIEROS CORRIENTES | AG31: =SUMIF('3BL ACTUAL'!B:B,AF31,'3BL ACTUAL'!E:E) -> 0 | AH31: =SUMIF('1 BL anterior'!B:B,AF31,'1 BL anterior'!E:E) -> 0
E32: A costo amortizado | N32: 328 | O32: + | P32: =SUMIF(AF:AF,N32,AH:AH) -> 0 | Q32: =SUMIF(AF:AF,N32,AG:AG) -> 0 | R32: =+P32-Q32 -> 0 | S32: =+R32 -> 0 | T32: =IF(S32>0,S32,0) -> 0 | U32: =IF(S32>0,0,S32) -> 0 | W32: =IF(V32>0,V32,0) -> 0 | X32: =IF(V32>0,0,V32) -> 0 | Z32: =IF(Y32>0,Y32,0) -> 0 | AA32: =IF(Y32>0,0,Y32) -> 0 | AC32: =+Y32+V32+S32+-AB32 -> 0 | AD32: =+AC32-R32 -> 0 | AE32: 103 | AF32: 328 | AG32: =SUMIF('3BL ACTUAL'!B:B,AF32,'3BL ACTUAL'!E:E) -> 0 | AH32: =SUMIF('1 BL anterior'!B:B,AF32,'1 BL anterior'!E:E) -> 0
E33: (-) Deterioro acumulado del valor de otros activos financieros corrientes medidos a costo amortizado (provisiones para créditos incobrables) | N33: 329 | O33: - | P33: =SUMIF(AF:AF,N33,AH:AH) -> 0 | Q33: =SUMIF(AF:AF,N33,AG:AG) -> 0 | R33: =+P33-Q33 -> 0 | S33: =+R33 -> 0 | T33: =IF(S33>0,S33,0) -> 0 | U33: =IF(S33>0,0,S33) -> 0 | W33: =IF(V33>0,V33,0) -> 0 | X33: =IF(V33>0,0,V33) -> 0 | Z33: =IF(Y33>0,Y33,0) -> 0 | AA33: =IF(Y33>0,0,Y33) -> 0 | AC33: =+Y33+V33+S33+-AB33 -> 0 | AD33: =+AC33-R33 -> 0 | AE33: 103 | AF33: 329 | AG33: =SUMIF('3BL ACTUAL'!B:B,AF33,'3BL ACTUAL'!E:E) -> 0 | AH33: =SUMIF('1 BL anterior'!B:B,AF33,'1 BL anterior'!E:E) -> 0
E34: A valor razonable | N34: 330 | O34: + | P34: =SUMIF(AF:AF,N34,AH:AH) -> 0 | Q34: =SUMIF(AF:AF,N34,AG:AG) -> 0 | R34: =+P34-Q34 -> 0 | S34: =+R34 -> 0 | T34: =IF(S34>0,S34,0) -> 0 | U34: =IF(S34>0,0,S34) -> 0 | W34: =IF(V34>0,V34,0) -> 0 | X34: =IF(V34>0,0,V34) -> 0 | Z34: =IF(Y34>0,Y34,0) -> 0 | AA34: =IF(Y34>0,0,Y34) -> 0 | AC34: =+Y34+V34+S34+-AB34 -> 0 | AD34: =+AC34-R34 -> 0 | AE34: 103 | AF34: 330 | AG34: =SUMIF('3BL ACTUAL'!B:B,AF34,'3BL ACTUAL'!E:E) -> 0 | AH34: =SUMIF('1 BL anterior'!B:B,AF34,'1 BL anterior'!E:E) -> 0
D35: PORCIÓN CORRIENTE DE ARRENDAMIENTOS FINANCIEROS POR COBRAR | AG35: =SUMIF('3BL ACTUAL'!B:B,AF35,'3BL ACTUAL'!E:E) -> 0 | AH35: =SUMIF('1 BL anterior'!B:B,AF35,'1 BL anterior'!E:E) -> 0
E36: Relacionadas | N36: 331 | O36: + | P36: =SUMIF(AF:AF,N36,AH:AH) -> 0 | Q36: =SUMIF(AF:AF,N36,AG:AG) -> 0 | R36: =+P36-Q36 -> 0 | S36: =+R36 -> 0 | T36: =IF(S36>0,S36,0) -> 0 | U36: =IF(S36>0,0,S36) -> 0 | W36: =IF(V36>0,V36,0) -> 0 | X36: =IF(V36>0,0,V36) -> 0 | Z36: =IF(Y36>0,Y36,0) -> 0 | AA36: =IF(Y36>0,0,Y36) -> 0 | AC36: =+Y36+V36+S36+-AB36 -> 0 | AD36: =+AC36-R36 -> 0 | AE36: 103 | AF36: 331 | AG36: =SUMIF('3BL ACTUAL'!B:B,AF36,'3BL ACTUAL'!E:E) -> 0 | AH36: =SUMIF('1 BL anterior'!B:B,AF36,'1 BL anterior'!E:E) -> 0
E37: No relacionadas | N37: 332 | O37: + | P37: =SUMIF(AF:AF,N37,AH:AH) -> 0 | Q37: =SUMIF(AF:AF,N37,AG:AG) -> 0 | R37: =+P37-Q37 -> 0 | S37: =+R37 -> 0 | T37: =IF(S37>0,S37,0) -> 0 | U37: =IF(S37>0,0,S37) -> 0 | W37: =IF(V37>0,V37,0) -> 0 | X37: =IF(V37>0,0,V37) -> 0 | Z37: =IF(Y37>0,Y37,0) -> 0 | AA37: =IF(Y37>0,0,Y37) -> 0 | AC37: =+Y37+V37+S37+-AB37 -> 0 | AD37: =+AC37-R37 -> 0 | AE37: 103 | AF37: 332 | AG37: =SUMIF('3BL ACTUAL'!B:B,AF37,'3BL ACTUAL'!E:E) -> 0 | AH37: =SUMIF('1 BL anterior'!B:B,AF37,'1 BL anterior'!E:E) -> 0
D38: IMPORTE BRUTO ADEUDADO POR LOS CLIENTES POR EL TRABAJO EJECUTADO EN CONTRATOS DE CONSTRUCCIÓN | AG38: =SUMIF('3BL ACTUAL'!B:B,AF38,'3BL ACTUAL'!E:E) -> 0 | AH38: =SUMIF('1 BL anterior'!B:B,AF38,'1 BL anterior'!E:E) -> 0
E39: Relacionadas | N39: 333 | O39: + | P39: =SUMIF(AF:AF,N39,AH:AH) -> 0 | Q39: =SUMIF(AF:AF,N39,AG:AG) -> 0 | R39: =+P39-Q39 -> 0 | S39: =+R39 -> 0 | T39: =IF(S39>0,S39,0) -> 0 | U39: =IF(S39>0,0,S39) -> 0 | W39: =IF(V39>0,V39,0) -> 0 | X39: =IF(V39>0,0,V39) -> 0 | Z39: =IF(Y39>0,Y39,0) -> 0 | AA39: =IF(Y39>0,0,Y39) -> 0 | AC39: =+Y39+V39+S39+-AB39 -> 0 | AD39: =+AC39-R39 -> 0 | AE39: 103 | AF39: 333 | AG39: =SUMIF('3BL ACTUAL'!B:B,AF39,'3BL ACTUAL'!E:E) -> 0 | AH39: =SUMIF('1 BL anterior'!B:B,AF39,'1 BL anterior'!E:E) -> 0
E40: No relacionadas | N40: 334 | O40: + | P40: =SUMIF(AF:AF,N40,AH:AH) -> 0 | Q40: =SUMIF(AF:AF,N40,AG:AG) -> 0 | R40: =+P40-Q40 -> 0 | S40: =+R40 -> 0 | T40: =IF(S40>0,S40,0) -> 0 | U40: =IF(S40>0,0,S40) -> 0 | W40: =IF(V40>0,V40,0) -> 0 | X40: =IF(V40>0,0,V40) -> 0 | Z40: =IF(Y40>0,Y40,0) -> 0 | AA40: =IF(Y40>0,0,Y40) -> 0 | AC40: =+Y40+V40+S40+-AB40 -> 0 | AD40: =+AC40-R40 -> 0 | AE40: 103 | AF40: 334 | AG40: =SUMIF('3BL ACTUAL'!B:B,AF40,'3BL ACTUAL'!E:E) -> 0 | AH40: =SUMIF('1 BL anterior'!B:B,AF40,'1 BL anterior'!E:E) -> 0
D41: ACTIVOS POR IMPUESTOS CORRIENTES | AG41: =SUMIF('3BL ACTUAL'!B:B,AF41,'3BL ACTUAL'!E:E) -> 0 | AH41: =SUMIF('1 BL anterior'!B:B,AF41,'1 BL anterior'!E:E) -> 0
E42: Crédito tributario a favor del sujeto pasivo (ISD) | N42: 335 | O42: + | P42: =SUMIF(AF:AF,N42,AH:AH) -> 0 | Q42: =SUMIF(AF:AF,N42,AG:AG) -> 0 | R42: =+P42-Q42 -> 0 | S42: =+R42 -> 0 | T42: =IF(S42>0,S42,0) -> 0 | U42: =IF(S42>0,0,S42) -> 0 | W42: =IF(V42>0,V42,0) -> 0 | X42: =IF(V42>0,0,V42) -> 0 | Z42: =IF(Y42>0,Y42,0) -> 0 | AA42: =IF(Y42>0,0,Y42) -> 0 | AC42: =+Y42+V42+S42+-AB42 -> 0 | AD42: =+AC42-R42 -> 0 | AE42: 103 | AF42: 335 | AG42: =SUMIF('3BL ACTUAL'!B:B,AF42,'3BL ACTUAL'!E:E) -> 0 | AH42: =SUMIF('1 BL anterior'!B:B,AF42,'1 BL anterior'!E:E) -> 0
E43: Crédito tributario a favor del sujeto pasivo (IVA) | N43: 336 | O43: + | P43: =SUMIF(AF:AF,N43,AH:AH) -> 0 | Q43: =SUMIF(AF:AF,N43,AG:AG) -> 0 | R43: =+P43-Q43 -> 0 | S43: =+R43 -> 0 | T43: =IF(S43>0,S43,0) -> 0 | U43: =IF(S43>0,0,S43) -> 0 | W43: =IF(V43>0,V43,0) -> 0 | X43: =IF(V43>0,0,V43) -> 0 | Z43: =IF(Y43>0,Y43,0) -> 0 | AA43: =IF(Y43>0,0,Y43) -> 0 | AC43: =+Y43+V43+S43+-AB43 -> 0 | AD43: =+AC43-R43 -> 0 | AE43: 103 | AF43: 336 | AG43: =SUMIF('3BL ACTUAL'!B:B,AF43,'3BL ACTUAL'!E:E) -> 0 | AH43: =SUMIF('1 BL anterior'!B:B,AF43,'1 BL anterior'!E:E) -> 0
E44: Crédito tributario a favor del sujeto pasivo (Impuesto a la Renta) | N44: 337 | O44: + | P44: =SUMIF(AF:AF,N44,AH:AH) -> 0 | Q44: =SUMIF(AF:AF,N44,AG:AG) -> 0 | R44: =+P44-Q44 -> 0 | S44: =+R44 -> 0 | T44: =IF(S44>0,S44,0) -> 0 | U44: =IF(S44>0,0,S44) -> 0 | W44: =IF(V44>0,V44,0) -> 0 | X44: =IF(V44>0,0,V44) -> 0 | Z44: =IF(Y44>0,Y44,0) -> 0 | AA44: =IF(Y44>0,0,Y44) -> 0 | AC44: =+Y44+V44+S44+-AB44 -> 0 | AD44: =+AC44-R44 -> 0 | AE44: 103 | AF44: 337 | AG44: =SUMIF('3BL ACTUAL'!B:B,AF44,'3BL ACTUAL'!E:E) -> 0 | AH44: =SUMIF('1 BL anterior'!B:B,AF44,'1 BL anterior'!E:E) -> 0
E45: Otros | N45: 338 | O45: + | P45: =SUMIF(AF:AF,N45,AH:AH) -> 0 | Q45: =SUMIF(AF:AF,N45,AG:AG) -> 0 | R45: =+P45-Q45 -> 0 | S45: =+R45 -> 0 | T45: =IF(S45>0,S45,0) -> 0 | U45: =IF(S45>0,0,S45) -> 0 | W45: =IF(V45>0,V45,0) -> 0 | X45: =IF(V45>0,0,V45) -> 0 | Z45: =IF(Y45>0,Y45,0) -> 0 | AA45: =IF(Y45>0,0,Y45) -> 0 | AC45: =+Y45+V45+S45+-AB45 -> 0 | AD45: =+AC45-R45 -> 0 | AE45: 103 | AF45: 338 | AG45: =SUMIF('3BL ACTUAL'!B:B,AF45,'3BL ACTUAL'!E:E) -> 0 | AH45: =SUMIF('1 BL anterior'!B:B,AF45,'1 BL anterior'!E:E) -> 0
D46: INVENTARIOS | AG46: =SUMIF('3BL ACTUAL'!B:B,AF46,'3BL ACTUAL'!E:E) -> 0 | AH46: =SUMIF('1 BL anterior'!B:B,AF46,'1 BL anterior'!E:E) -> 0
E47: Mercaderías en tránsito | N47: 339 | O47: + | P47: =SUMIF(AF:AF,N47,AH:AH) -> 0 | Q47: =SUMIF(AF:AF,N47,AG:AG) -> 0 | R47: =+P47-Q47 -> 0 | S47: =+R47 -> 0 | T47: =IF(S47>0,S47,0) -> 0 | U47: =IF(S47>0,0,S47) -> 0 | W47: =IF(V47>0,V47,0) -> 0 | X47: =IF(V47>0,0,V47) -> 0 | Z47: =IF(Y47>0,Y47,0) -> 0 | AA47: =IF(Y47>0,0,Y47) -> 0 | AC47: =+Y47+V47+S47+-AB47 -> 0 | AD47: =+AC47-R47 -> 0 | AE47: 104 | AF47: 339 | AG47: =SUMIF('3BL ACTUAL'!B:B,AF47,'3BL ACTUAL'!E:E) -> 0 | AH47: =SUMIF('1 BL anterior'!B:B,AF47,'1 BL anterior'!E:E) -> 0
E48: Inventario de materia prima (no para la construcción) | N48: 340 | O48: + | P48: =SUMIF(AF:AF,N48,AH:AH) -> 0 | Q48: =SUMIF(AF:AF,N48,AG:AG) -> 0 | R48: =+P48-Q48 -> 0 | S48: =+R48 -> 0 | T48: =IF(S48>0,S48,0) -> 0 | U48: =IF(S48>0,0,S48) -> 0 | W48: =IF(V48>0,V48,0) -> 0 | X48: =IF(V48>0,0,V48) -> 0 | Z48: =IF(Y48>0,Y48,0) -> 0 | AA48: =IF(Y48>0,0,Y48) -> 0 | AC48: =+Y48+V48+S48+-AB48 -> 0 | AD48: =+AC48-R48 -> 0 | AE48: 104 | AF48: 340 | AG48: =SUMIF('3BL ACTUAL'!B:B,AF48,'3BL ACTUAL'!E:E) -> 0 | AH48: =SUMIF('1 BL anterior'!B:B,AF48,'1 BL anterior'!E:E) -> 0
E49: Inventario de productos en proceso (excluyendo obras/inmuebles en construcción para la venta) | N49: 341 | O49: + | P49: =SUMIF(AF:AF,N49,AH:AH) -> 0 | Q49: =SUMIF(AF:AF,N49,AG:AG) -> 0 | R49: =+P49-Q49 -> 0 | S49: =+R49 -> 0 | T49: =IF(S49>0,S49,0) -> 0 | U49: =IF(S49>0,0,S49) -> 0 | W49: =IF(V49>0,V49,0) -> 0 | X49: =IF(V49>0,0,V49) -> 0 | Z49: =IF(Y49>0,Y49,0) -> 0 | AA49: =IF(Y49>0,0,Y49) -> 0 | AC49: =+Y49+V49+S49+-AB49 -> 0 | AD49: =+AC49-R49 -> 0 | AE49: 104 | AF49: 341 | AG49: =SUMIF('3BL ACTUAL'!B:B,AF49,'3BL ACTUAL'!E:E) -> 0 | AH49: =SUMIF('1 BL anterior'!B:B,AF49,'1 BL anterior'!E:E) -> 0
E50: Inventario de prod. term. y mercad. en almacén (excluyendo obras/inmuebles terminados para la venta) | N50: 342 | O50: + | P50: =SUMIF(AF:AF,N50,AH:AH) -> 0 | Q50: =SUMIF(AF:AF,N50,AG:AG) -> 0 | R50: =+P50-Q50 -> 0 | S50: =+R50 -> 0 | T50: =IF(S50>0,S50,0) -> 0 | U50: =IF(S50>0,0,S50) -> 0 | W50: =IF(V50>0,V50,0) -> 0 | X50: =IF(V50>0,0,V50) -> 0 | Z50: =IF(Y50>0,Y50,0) -> 0 | AA50: =IF(Y50>0,0,Y50) -> 0 | AC50: =+Y50+V50+S50+-AB50 -> 0 | AD50: =+AC50-R50 -> 0 | AE50: 104 | AF50: 342 | AG50: =SUMIF('3BL ACTUAL'!B:B,AF50,'3BL ACTUAL'!E:E) -> 0 | AH50: =SUMIF('1 BL anterior'!B:B,AF50,'1 BL anterior'!E:E) -> 0
E51: Inventario de suministros, herramientas, repuestos y materiales (no para la construcción) | N51: 343 | O51: + | P51: =SUMIF(AF:AF,N51,AH:AH) -> 0 | Q51: =SUMIF(AF:AF,N51,AG:AG) -> 0 | R51: =+P51-Q51 -> 0 | S51: =+R51 -> 0 | T51: =IF(S51>0,S51,0) -> 0 | U51: =IF(S51>0,0,S51) -> 0 | W51: =IF(V51>0,V51,0) -> 0 | X51: =IF(V51>0,0,V51) -> 0 | Z51: =IF(Y51>0,Y51,0) -> 0 | AA51: =IF(Y51>0,0,Y51) -> 0 | AC51: =+Y51+V51+S51+-AB51 -> 0 | AD51: =+AC51-R51 -> 0 | AE51: 104 | AF51: 343 | AG51: =SUMIF('3BL ACTUAL'!B:B,AF51,'3BL ACTUAL'!E:E) -> 0 | AH51: =SUMIF('1 BL anterior'!B:B,AF51,'1 BL anterior'!E:E) -> 0
E52: Inventario de materia prima, suministros y materiales para la construcción | N52: 344 | O52: + | P52: =SUMIF(AF:AF,N52,AH:AH) -> 0 | Q52: =SUMIF(AF:AF,N52,AG:AG) -> 0 | R52: =+P52-Q52 -> 0 | S52: =+R52 -> 0 | T52: =IF(S52>0,S52,0) -> 0 | U52: =IF(S52>0,0,S52) -> 0 | W52: =IF(V52>0,V52,0) -> 0 | X52: =IF(V52>0,0,V52) -> 0 | Z52: =IF(Y52>0,Y52,0) -> 0 | AA52: =IF(Y52>0,0,Y52) -> 0 | AC52: =+Y52+V52+S52+-AB52 -> 0 | AD52: =+AC52-R52 -> 0 | AE52: 104 | AF52: 344 | AG52: =SUMIF('3BL ACTUAL'!B:B,AF52,'3BL ACTUAL'!E:E) -> 0 | AH52: =SUMIF('1 BL anterior'!B:B,AF52,'1 BL anterior'!E:E) -> 0
E53: Inventario de obras/inmuebles en construcción para la venta | N53: 345 | O53: + | P53: =SUMIF(AF:AF,N53,AH:AH) -> 0 | Q53: =SUMIF(AF:AF,N53,AG:AG) -> 0 | R53: =+P53-Q53 -> 0 | S53: =+R53 -> 0 | T53: =IF(S53>0,S53,0) -> 0 | U53: =IF(S53>0,0,S53) -> 0 | W53: =IF(V53>0,V53,0) -> 0 | X53: =IF(V53>0,0,V53) -> 0 | Z53: =IF(Y53>0,Y53,0) -> 0 | AA53: =IF(Y53>0,0,Y53) -> 0 | AC53: =+Y53+V53+S53+-AB53 -> 0 | AD53: =+AC53-R53 -> 0 | AE53: 104 | AF53: 345 | AG53: =SUMIF('3BL ACTUAL'!B:B,AF53,'3BL ACTUAL'!E:E) -> 0 | AH53: =SUMIF('1 BL anterior'!B:B,AF53,'1 BL anterior'!E:E) -> 0
E54: Inventario de obras/inmuebles terminados para la venta | N54: 346 | O54: + | P54: =SUMIF(AF:AF,N54,AH:AH) -> 0 | Q54: =SUMIF(AF:AF,N54,AG:AG) -> 0 | R54: =+P54-Q54 -> 0 | S54: =+R54 -> 0 | T54: =IF(S54>0,S54,0) -> 0 | U54: =IF(S54>0,0,S54) -> 0 | W54: =IF(V54>0,V54,0) -> 0 | X54: =IF(V54>0,0,V54) -> 0 | Z54: =IF(Y54>0,Y54,0) -> 0 | AA54: =IF(Y54>0,0,Y54) -> 0 | AC54: =+Y54+V54+S54+-AB54 -> 0 | AD54: =+AC54-R54 -> 0 | AE54: 104 | AF54: 346 | AG54: =SUMIF('3BL ACTUAL'!B:B,AF54,'3BL ACTUAL'!E:E) -> 0 | AH54: =SUMIF('1 BL anterior'!B:B,AF54,'1 BL anterior'!E:E) -> 0
E55: (-) Deterioro acumulado del valor de inventarios por ajuste al valor neto realizable | N55: 347 | O55: - | P55: =SUMIF(AF:AF,N55,AH:AH) -> 0 | Q55: =SUMIF(AF:AF,N55,AG:AG) -> 0 | R55: =+P55-Q55 -> 0 | S55: =+R55 -> 0 | T55: =IF(S55>0,S55,0) -> 0 | U55: =IF(S55>0,0,S55) -> 0 | W55: =IF(V55>0,V55,0) -> 0 | X55: =IF(V55>0,0,V55) -> 0 | Z55: =IF(Y55>0,Y55,0) -> 0 | AA55: =IF(Y55>0,0,Y55) -> 0 | AC55: =+Y55+V55+S55+-AB55 -> 0 | AD55: =+AC55-R55 -> 0 | AE55: 104 | AF55: 347 | AG55: =SUMIF('3BL ACTUAL'!B:B,AF55,'3BL ACTUAL'!E:E) -> 0 | AH55: =SUMIF('1 BL anterior'!B:B,AF55,'1 BL anterior'!E:E) -> 0
D56: ACTIVOS NO CORRIENTES MANTENIDOS PARA LA VENTA | AG56: =SUMIF('3BL ACTUAL'!B:B,AF56,'3BL ACTUAL'!E:E) -> 0 | AH56: =SUMIF('1 BL anterior'!B:B,AF56,'1 BL anterior'!E:E) -> 0
E57: Costo | N57: 348 | O57: + | P57: =SUMIF(AF:AF,N57,AH:AH) -> 0 | Q57: =SUMIF(AF:AF,N57,AG:AG) -> 0 | R57: =+P57-Q57 -> 0 | T57: =IF(S57>0,S57,0) -> 0 | U57: =IF(S57>0,0,S57) -> 0 | V57: =+R57 -> 0 | W57: =IF(V57>0,V57,0) -> 0 | X57: =IF(V57>0,0,V57) -> 0 | Z57: =IF(Y57>0,Y57,0) -> 0 | AA57: =IF(Y57>0,0,Y57) -> 0 | AC57: =+Y57+V57+S57+-AB57 -> 0 | AD57: =+AC57-R57 -> 0 | AE57: 104 | AF57: 348 | AG57: =SUMIF('3BL ACTUAL'!B:B,AF57,'3BL ACTUAL'!E:E) -> 0 | AH57: =SUMIF('1 BL anterior'!B:B,AF57,'1 BL anterior'!E:E) -> 0
E58: (-) Deterioro acumulado del valor de activos no corrientes mantenidos para la venta | N58: 349 | O58: - | P58: =SUMIF(AF:AF,N58,AH:AH) -> 0 | Q58: =SUMIF(AF:AF,N58,AG:AG) -> 0 | R58: =+P58-Q58 -> 0 | S58: =+R58+AB58 -> 0 | T58: =IF(S58>0,S58,0) -> 0 | U58: =IF(S58>0,0,S58) -> 0 | W58: =IF(V58>0,V58,0) -> 0 | X58: =IF(V58>0,0,V58) -> 0 | Z58: =IF(Y58>0,Y58,0) -> 0 | AA58: =IF(Y58>0,0,Y58) -> 0 | AC58: =+Y58+V58+S58+-AB58 -> 0 | AD58: =+AC58-R58 -> 0 | AE58: 104 | AF58: 349 | AG58: =SUMIF('3BL ACTUAL'!B:B,AF58,'3BL ACTUAL'!E:E) -> 0 | AH58: =SUMIF('1 BL anterior'!B:B,AF58,'1 BL anterior'!E:E) -> 0
D59: ACTIVOS BIOLÓGICOS | AG59: =SUMIF('3BL ACTUAL'!B:B,AF59,'3BL ACTUAL'!E:E) -> 0 | AH59: =SUMIF('1 BL anterior'!B:B,AF59,'1 BL anterior'!E:E) -> 0
E60: PLANTAS VIVAS Y FRUTOS EN CRECIMIENTO | AG60: =SUMIF('3BL ACTUAL'!B:B,AF60,'3BL ACTUAL'!E:E) -> 0 | AH60: =SUMIF('1 BL anterior'!B:B,AF60,'1 BL anterior'!E:E) -> 0
F61: A costo | N61: 350 | O61: + | P61: =SUMIF(AF:AF,N61,AH:AH) -> 0 | Q61: =SUMIF(AF:AF,N61,AG:AG) -> 0 | R61: =+P61-Q61 -> 0 | T61: =IF(S61>0,S61,0) -> 0 | U61: =IF(S61>0,0,S61) -> 0 | V61: =+R61 -> 0 | W61: =IF(V61>0,V61,0) -> 0 | X61: =IF(V61>0,0,V61) -> 0 | Z61: =IF(Y61>0,Y61,0) -> 0 | AA61: =IF(Y61>0,0,Y61) -> 0 | AC61: =+Y61+V61+S61+-AB61 -> 0 | AD61: =+AC61-R61 -> 0 | AE61: 104 | AF61: 350 | AG61: =SUMIF('3BL ACTUAL'!B:B,AF61,'3BL ACTUAL'!E:E) -> 0 | AH61: =SUMIF('1 BL anterior'!B:B,AF61,'1 BL anterior'!E:E) -> 0
F62: (-) Deterioro acumulado del valor de activos biológicos medidos a costo | N62: 351 | O62: - | P62: =SUMIF(AF:AF,N62,AH:AH) -> 0 | Q62: =SUMIF(AF:AF,N62,AG:AG) -> 0 | R62: =+P62-Q62 -> 0 | S62: =+R62 -> 0 | T62: =IF(S62>0,S62,0) -> 0 | U62: =IF(S62>0,0,S62) -> 0 | W62: =IF(V62>0,V62,0) -> 0 | X62: =IF(V62>0,0,V62) -> 0 | Z62: =IF(Y62>0,Y62,0) -> 0 | AA62: =IF(Y62>0,0,Y62) -> 0 | AC62: =+Y62+V62+S62+-AB62 -> 0 | AD62: =+AC62-R62 -> 0 | AE62: 104 | AF62: 351 | AG62: =SUMIF('3BL ACTUAL'!B:B,AF62,'3BL ACTUAL'!E:E) -> 0 | AH62: =SUMIF('1 BL anterior'!B:B,AF62,'1 BL anterior'!E:E) -> 0
F63: A valor razonable menos los costos de venta | N63: 352 | O63: + | P63: =SUMIF(AF:AF,N63,AH:AH) -> 0 | Q63: =SUMIF(AF:AF,N63,AG:AG) -> 0 | R63: =+P63-Q63 -> 0 | T63: =IF(S63>0,S63,0) -> 0 | U63: =IF(S63>0,0,S63) -> 0 | V63: =+R63 -> 0 | W63: =IF(V63>0,V63,0) -> 0 | X63: =IF(V63>0,0,V63) -> 0 | Z63: =IF(Y63>0,Y63,0) -> 0 | AA63: =IF(Y63>0,0,Y63) -> 0 | AC63: =+Y63+V63+S63+-AB63 -> 0 | AD63: =+AC63-R63 -> 0 | AE63: 104 | AF63: 352 | AG63: =SUMIF('3BL ACTUAL'!B:B,AF63,'3BL ACTUAL'!E:E) -> 0 | AH63: =SUMIF('1 BL anterior'!B:B,AF63,'1 BL anterior'!E:E) -> 0
E64: ANIMALES VIVOS | AG64: =SUMIF('3BL ACTUAL'!B:B,AF64,'3BL ACTUAL'!E:E) -> 0 | AH64: =SUMIF('1 BL anterior'!B:B,AF64,'1 BL anterior'!E:E) -> 0
F65: A costo | N65: 353 | O65: + | P65: =SUMIF(AF:AF,N65,AH:AH) -> 0 | Q65: =SUMIF(AF:AF,N65,AG:AG) -> 0 | R65: =+P65-Q65 -> 0 | T65: =IF(S65>0,S65,0) -> 0 | U65: =IF(S65>0,0,S65) -> 0 | V65: =+R65 -> 0 | W65: =IF(V65>0,V65,0) -> 0 | X65: =IF(V65>0,0,V65) -> 0 | Z65: =IF(Y65>0,Y65,0) -> 0 | AA65: =IF(Y65>0,0,Y65) -> 0 | AC65: =+Y65+V65+S65+-AB65 -> 0 | AD65: =+AC65-R65 -> 0 | AE65: 104 | AF65: 353 | AG65: =SUMIF('3BL ACTUAL'!B:B,AF65,'3BL ACTUAL'!E:E) -> 0 | AH65: =SUMIF('1 BL anterior'!B:B,AF65,'1 BL anterior'!E:E) -> 0
F66: (-) Deterioro acumulado del valor de activos biológicos medidos a costo | N66: 354 | O66: - | P66: =SUMIF(AF:AF,N66,AH:AH) -> 0 | Q66: =SUMIF(AF:AF,N66,AG:AG) -> 0 | R66: =+P66-Q66 -> 0 | S66: =+R66 -> 0 | T66: =IF(S66>0,S66,0) -> 0 | U66: =IF(S66>0,0,S66) -> 0 | W66: =IF(V66>0,V66,0) -> 0 | X66: =IF(V66>0,0,V66) -> 0 | Z66: =IF(Y66>0,Y66,0) -> 0 | AA66: =IF(Y66>0,0,Y66) -> 0 | AC66: =+Y66+V66+S66+-AB66 -> 0 | AD66: =+AC66-R66 -> 0 | AE66: 104 | AF66: 354 | AG66: =SUMIF('3BL ACTUAL'!B:B,AF66,'3BL ACTUAL'!E:E) -> 0 | AH66: =SUMIF('1 BL anterior'!B:B,AF66,'1 BL anterior'!E:E) -> 0
F67: A valor razonable menos los costos de venta | N67: 355 | O67: + | P67: =SUMIF(AF:AF,N67,AH:AH) -> 0 | Q67: =SUMIF(AF:AF,N67,AG:AG) -> 0 | R67: =+P67-Q67 -> 0 | T67: =IF(S67>0,S67,0) -> 0 | U67: =IF(S67>0,0,S67) -> 0 | V67: =+R67 -> 0 | W67: =IF(V67>0,V67,0) -> 0 | X67: =IF(V67>0,0,V67) -> 0 | Z67: =IF(Y67>0,Y67,0) -> 0 | AA67: =IF(Y67>0,0,Y67) -> 0 | AC67: =+Y67+V67+S67+-AB67 -> 0 | AD67: =+AC67-R67 -> 0 | AE67: 104 | AF67: 355 | AG67: =SUMIF('3BL ACTUAL'!B:B,AF67,'3BL ACTUAL'!E:E) -> 0 | AH67: =SUMIF('1 BL anterior'!B:B,AF67,'1 BL anterior'!E:E) -> 0
D68: GASTOS PAGADOS POR ANTICIPADO (PREPAGADOS) | AG68: =SUMIF('3BL ACTUAL'!B:B,AF68,'3BL ACTUAL'!E:E) -> 0 | AH68: =SUMIF('1 BL anterior'!B:B,AF68,'1 BL anterior'!E:E) -> 0
E69: Propaganda y publicidad prepagada | N69: 356 | O69: + | P69: =SUMIF(AF:AF,N69,AH:AH) -> 0 | Q69: =SUMIF(AF:AF,N69,AG:AG) -> 0 | R69: =+P69-Q69 -> 0 | S69: =+R69 -> 0 | T69: =IF(S69>0,S69,0) -> 0 | U69: =IF(S69>0,0,S69) -> 0 | W69: =IF(V69>0,V69,0) -> 0 | X69: =IF(V69>0,0,V69) -> 0 | Z69: =IF(Y69>0,Y69,0) -> 0 | AA69: =IF(Y69>0,0,Y69) -> 0 | AC69: =+Y69+V69+S69+-AB69 -> 0 | AD69: =+AC69-R69 -> 0 | AE69: 105 | AF69: 356 | AG69: =SUMIF('3BL ACTUAL'!B:B,AF69,'3BL ACTUAL'!E:E) -> 0 | AH69: =SUMIF('1 BL anterior'!B:B,AF69,'1 BL anterior'!E:E) -> 0
E70: Arrendamientos operativos pagados por anticipado | N70: 357 | O70: + | P70: =SUMIF(AF:AF,N70,AH:AH) -> 0 | Q70: =SUMIF(AF:AF,N70,AG:AG) -> 0 | R70: =+P70-Q70 -> 0 | S70: =+R70 -> 0 | T70: =IF(S70>0,S70,0) -> 0 | U70: =IF(S70>0,0,S70) -> 0 | W70: =IF(V70>0,V70,0) -> 0 | X70: =IF(V70>0,0,V70) -> 0 | Z70: =IF(Y70>0,Y70,0) -> 0 | AA70: =IF(Y70>0,0,Y70) -> 0 | AC70: =+Y70+V70+S70+-AB70 -> 0 | AD70: =+AC70-R70 -> 0 | AE70: 105 | AF70: 357 | AG70: =SUMIF('3BL ACTUAL'!B:B,AF70,'3BL ACTUAL'!E:E) -> 0 | AH70: =SUMIF('1 BL anterior'!B:B,AF70,'1 BL anterior'!E:E) -> 0
E71: Primas de seguro pagadas por anticipado | N71: 358 | O71: + | P71: =SUMIF(AF:AF,N71,AH:AH) -> 0 | Q71: =SUMIF(AF:AF,N71,AG:AG) -> 0 | R71: =+P71-Q71 -> 0 | S71: =+R71 -> 0 | T71: =IF(S71>0,S71,0) -> 0 | U71: =IF(S71>0,0,S71) -> 0 | W71: =IF(V71>0,V71,0) -> 0 | X71: =IF(V71>0,0,V71) -> 0 | Z71: =IF(Y71>0,Y71,0) -> 0 | AA71: =IF(Y71>0,0,Y71) -> 0 | AC71: =+Y71+V71+S71+-AB71 -> 0 | AD71: =+AC71-R71 -> 0 | AE71: 105 | AF71: 358 | AG71: =SUMIF('3BL ACTUAL'!B:B,AF71,'3BL ACTUAL'!E:E) -> 0 | AH71: =SUMIF('1 BL anterior'!B:B,AF71,'1 BL anterior'!E:E) -> 0
E72: Otros | N72: 359 | O72: + | P72: =SUMIF(AF:AF,N72,AH:AH) -> 0 | Q72: =SUMIF(AF:AF,N72,AG:AG) -> 0 | R72: =+P72-Q72 -> 0 | S72: =+R72 -> 0 | T72: =IF(S72>0,S72,0) -> 0 | U72: =IF(S72>0,0,S72) -> 0 | W72: =IF(V72>0,V72,0) -> 0 | X72: =IF(V72>0,0,V72) -> 0 | Z72: =IF(Y72>0,Y72,0) -> 0 | AA72: =IF(Y72>0,0,Y72) -> 0 | AC72: =+Y72+V72+S72+-AB72 -> 0 | AD72: =+AC72-R72 -> 0 | AE72: 105 | AF72: 359 | AG72: =SUMIF('3BL ACTUAL'!B:B,AF72,'3BL ACTUAL'!E:E) -> 0 | AH72: =SUMIF('1 BL anterior'!B:B,AF72,'1 BL anterior'!E:E) -> 0
D73: Otros Activos Corrientes | N73: 360 | O73: + | P73: =SUMIF(AF:AF,N73,AH:AH) -> 0 | Q73: =SUMIF(AF:AF,N73,AG:AG) -> 0 | R73: =+P73-Q73 -> 0 | S73: =+R73 -> 0 | T73: =IF(S73>0,S73,0) -> 0 | U73: =IF(S73>0,0,S73) -> 0 | W73: =IF(V73>0,V73,0) -> 0 | X73: =IF(V73>0,0,V73) -> 0 | Z73: =IF(Y73>0,Y73,0) -> 0 | AA73: =IF(Y73>0,0,Y73) -> 0 | AC73: =+Y73+V73+S73+-AB73 -> 0 | AD73: =+AC73-R73 -> 0 | AE73: 105 | AF73: 360 | AG73: =SUMIF('3BL ACTUAL'!B:B,AF73,'3BL ACTUAL'!E:E) -> 0 | AH73: =SUMIF('1 BL anterior'!B:B,AF73,'1 BL anterior'!E:E) -> 0
C74: TOTAL ACTIVOS CORRIENTES | N74: 361 | R74: =+P74-Q74 -> 0 | S74: =+R74 -> 0 | T74: =IF(S74>0,S74,0) -> 0 | U74: =IF(S74>0,0,S74) -> 0 | W74: =IF(V74>0,V74,0) -> 0 | X74: =IF(V74>0,0,V74) -> 0 | Z74: =IF(Y74>0,Y74,0) -> 0 | AA74: =IF(Y74>0,0,Y74) -> 0 | AC74: =+Y74+V74+S74+-AB74 -> 0 | AD74: =+AC74-R74 -> 0 | AE74: 105 | AF74: 361 | AG74: =SUMIF('3BL ACTUAL'!B:B,AF74,'3BL ACTUAL'!E:E) -> 0 | AH74: =SUMIF('1 BL anterior'!B:B,AF74,'1 BL anterior'!E:E) -> 0
C75: ACTIVOS NO CORRIENTES | R75: =+P75-Q75 -> 0 | T75: =IF(S75>0,S75,0) -> 0 | U75: =IF(S75>0,0,S75) -> 0 | W75: =IF(V75>0,V75,0) -> 0 | X75: =IF(V75>0,0,V75) -> 0 | Z75: =IF(Y75>0,Y75,0) -> 0 | AA75: =IF(Y75>0,0,Y75) -> 0 | AC75: =+Y75+V75+S75+-AB75 -> 0 | AD75: =+AC75-R75 -> 0 | AG75: =SUMIF('3BL ACTUAL'!B:B,AF75,'3BL ACTUAL'!E:E) -> 0 | AH75: =SUMIF('1 BL anterior'!B:B,AF75,'1 BL anterior'!E:E) -> 0
D76: PROPIEDADES, PLANTA Y EQUIPO | AG76: =SUMIF('3BL ACTUAL'!B:B,AF76,'3BL ACTUAL'!E:E) -> 0 | AH76: =SUMIF('1 BL anterior'!B:B,AF76,'1 BL anterior'!E:E) -> 0
E77: TERRENOS | AG77: =SUMIF('3BL ACTUAL'!B:B,AF77,'3BL ACTUAL'!E:E) -> 0 | AH77: =SUMIF('1 BL anterior'!B:B,AF77,'1 BL anterior'!E:E) -> 0
F78: Costo histórico antes de reexpresiones o revaluaciones | N78: 362 | O78: + | P78: =SUMIF(AF:AF,N78,AH:AH) -> 0 | Q78: =SUMIF(AF:AF,N78,AG:AG) -> 0 | R78: =+P78-Q78 -> 0 | T78: =IF(S78>0,S78,0) -> 0 | U78: =IF(S78>0,0,S78) -> 0 | V78: =+R78 -> 0 | W78: =IF(V78>0,V78,0) -> 0 | X78: =IF(V78>0,0,V78) -> 0 | Z78: =IF(Y78>0,Y78,0) -> 0 | AA78: =IF(Y78>0,0,Y78) -> 0 | AC78: =+Y78+V78+S78+-AB78 -> 0 | AD78: =+AC78-R78 -> 0 | AE78: 111 | AF78: 362 | AG78: =SUMIF('3BL ACTUAL'!B:B,AF78,'3BL ACTUAL'!E:E) -> 0 | AH78: =SUMIF('1 BL anterior'!B:B,AF78,'1 BL anterior'!E:E) -> 0
F79: Ajuste acumulado por reexpresiones o revaluaciones | G79: ajuste acumulado por reexpresiones o revaluaciones | K79: ajuste acumulado por reexpresiones o revaluaciones | L79: ajuste acumulado por reexpresiones o revaluaciones | M79: ajuste acumulado por reexpresiones o revaluaciones | N79: 363 | O79: + | P79: =SUMIF(AF:AF,N79,AH:AH) -> 0 | Q79: =SUMIF(AF:AF,N79,AG:AG) -> 0 | R79: =+P79-Q79 -> 0 | T79: =IF(S79>0,S79,0) -> 0 | U79: =IF(S79>0,0,S79) -> 0 | V79: =+R79 -> 0 | W79: =IF(V79>0,V79,0) -> 0 | X79: =IF(V79>0,0,V79) -> 0 | Z79: =IF(Y79>0,Y79,0) -> 0 | AA79: =IF(Y79>0,0,Y79) -> 0 | AB79: =+V79 -> 0 | AC79: =+Y79+V79+S79+-AB79 -> 0 | AD79: =+AC79-R79 -> 0 | AE79: 111 | AF79: 363 | AG79: =SUMIF('3BL ACTUAL'!B:B,AF79,'3BL ACTUAL'!E:E) -> 0 | AH79: =SUMIF('1 BL anterior'!B:B,AF79,'1 BL anterior'!E:E) -> 0
E80: EDIFICIOS Y OTROS INMUEBLES (EXCEPTO TERRENOS) | AG80: =SUMIF('3BL ACTUAL'!B:B,AF80,'3BL ACTUAL'!E:E) -> 0 | AH80: =SUMIF('1 BL anterior'!B:B,AF80,'1 BL anterior'!E:E) -> 0
F81: Costo histórico antes de reexpresiones o revaluaciones | N81: 364 | O81: + | P81: =SUMIF(AF:AF,N81,AH:AH) -> 0 | Q81: =SUMIF(AF:AF,N81,AG:AG) -> 0 | R81: =+P81-Q81 -> 0 | T81: =IF(S81>0,S81,0) -> 0 | U81: =IF(S81>0,0,S81) -> 0 | V81: =+R81 -> 0 | W81: =IF(V81>0,V81,0) -> 0 | X81: =IF(V81>0,0,V81) -> 0 | Z81: =IF(Y81>0,Y81,0) -> 0 | AA81: =IF(Y81>0,0,Y81) -> 0 | AC81: =+Y81+V81+S81+-AB81 -> 0 | AD81: =+AC81-R81 -> 0 | AE81: 111 | AF81: 364 | AG81: =SUMIF('3BL ACTUAL'!B:B,AF81,'3BL ACTUAL'!E:E) -> 0 | AH81: =SUMIF('1 BL anterior'!B:B,AF81,'1 BL anterior'!E:E) -> 0
F82: Ajuste acumulado por reexpresiones o revaluaciones | G82: ajuste acumulado por reexpresiones o revaluaciones | K82: ajuste acumulado por reexpresiones o revaluaciones | L82: ajuste acumulado por reexpresiones o revaluaciones | M82: ajuste acumulado por reexpresiones o revaluaciones | N82: 365 | O82: + | P82: =SUMIF(AF:AF,N82,AH:AH) -> 0 | Q82: =SUMIF(AF:AF,N82,AG:AG) -> 0 | R82: =+P82-Q82 -> 0 | T82: =IF(S82>0,S82,0) -> 0 | U82: =IF(S82>0,0,S82) -> 0 | V82: =+R82 -> 0 | W82: =IF(V82>0,V82,0) -> 0 | X82: =IF(V82>0,0,V82) -> 0 | Z82: =IF(Y82>0,Y82,0) -> 0 | AA82: =IF(Y82>0,0,Y82) -> 0 | AB82: =+V82 -> 0 | AC82: =+Y82+V82+S82+-AB82 -> 0 | AD82: =+AC82-R82 -> 0 | AE82: 111 | AF82: 365 | AG82: =SUMIF('3BL ACTUAL'!B:B,AF82,'3BL ACTUAL'!E:E) -> 0 | AH82: =SUMIF('1 BL anterior'!B:B,AF82,'1 BL anterior'!E:E) -> 0
E83: NAVES, AERONAVES, BARCAZAS Y SIMILARES | AG83: =SUMIF('3BL ACTUAL'!B:B,AF83,'3BL ACTUAL'!E:E) -> 0 | AH83: =SUMIF('1 BL anterior'!B:B,AF83,'1 BL anterior'!E:E) -> 0
F84: Costo histórico antes de reexpresiones o revaluaciones | N84: 366 | O84: + | P84: =SUMIF(AF:AF,N84,AH:AH) -> 0 | Q84: =SUMIF(AF:AF,N84,AG:AG) -> 0 | R84: =+P84-Q84 -> 0 | T84: =IF(S84>0,S84,0) -> 0 | U84: =IF(S84>0,0,S84) -> 0 | V84: =+R84 -> 0 | W84: =IF(V84>0,V84,0) -> 0 | X84: =IF(V84>0,0,V84) -> 0 | Z84: =IF(Y84>0,Y84,0) -> 0 | AA84: =IF(Y84>0,0,Y84) -> 0 | AC84: =+Y84+V84+S84+-AB84 -> 0 | AD84: =+AC84-R84 -> 0 | AE84: 111 | AF84: 366 | AG84: =SUMIF('3BL ACTUAL'!B:B,AF84,'3BL ACTUAL'!E:E) -> 0 | AH84: =SUMIF('1 BL anterior'!B:B,AF84,'1 BL anterior'!E:E) -> 0
F85: Ajuste acumulado por reexpresiones o revaluaciones | G85: ajuste acumulado por reexpresiones o revaluaciones | K85: ajuste acumulado por reexpresiones o revaluaciones | L85: ajuste acumulado por reexpresiones o revaluaciones | M85: ajuste acumulado por reexpresiones o revaluaciones | N85: 367 | O85: + | P85: =SUMIF(AF:AF,N85,AH:AH) -> 0 | Q85: =SUMIF(AF:AF,N85,AG:AG) -> 0 | R85: =+P85-Q85 -> 0 | T85: =IF(S85>0,S85,0) -> 0 | U85: =IF(S85>0,0,S85) -> 0 | V85: =+R85 -> 0 | W85: =IF(V85>0,V85,0) -> 0 | X85: =IF(V85>0,0,V85) -> 0 | Z85: =IF(Y85>0,Y85,0) -> 0 | AA85: =IF(Y85>0,0,Y85) -> 0 | AC85: =+Y85+V85+S85+-AB85 -> 0 | AD85: =+AC85-R85 -> 0 | AE85: 111 | AF85: 367 | AG85: =SUMIF('3BL ACTUAL'!B:B,AF85,'3BL ACTUAL'!E:E) -> 0 | AH85: =SUMIF('1 BL anterior'!B:B,AF85,'1 BL anterior'!E:E) -> 0
E86: MAQUINARIA, EQUIPO, INSTALACIONES Y ADECUACIONES | AG86: =SUMIF('3BL ACTUAL'!B:B,AF86,'3BL ACTUAL'!E:E) -> 0 | AH86: =SUMIF('1 BL anterior'!B:B,AF86,'1 BL anterior'!E:E) -> 0
F87: Costo histórico antes de reexpresiones o revaluaciones | N87: 368 | O87: + | P87: =SUMIF(AF:AF,N87,AH:AH) -> 408105.13 | Q87: =SUMIF(AF:AF,N87,AG:AG) -> 0 | R87: =+P87-Q87 -> 408105.13 | T87: =IF(S87>0,S87,0) -> 0 | U87: =IF(S87>0,0,S87) -> 0 | V87: =+R87 -> 408105.13 | W87: =IF(V87>0,V87,0) -> 408105.13 | X87: =IF(V87>0,0,V87) -> 0 | Z87: =IF(Y87>0,Y87,0) -> 0 | AA87: =IF(Y87>0,0,Y87) -> 0 | AC87: =+Y87+V87+S87+-AB87 -> 408105.13 | AD87: =+AC87-R87 -> 0 | AE87: 111 | AF87: 368 | AG87: =SUMIF('3BL ACTUAL'!B:B,AF87,'3BL ACTUAL'!E:E) -> 0 | AH87: =SUMIF('1 BL anterior'!B:B,AF87,'1 BL anterior'!E:E) -> 408105.13
F88: Ajuste acumulado por reexpresiones o revaluaciones | G88: ajuste acumulado por reexpresiones o revaluaciones | N88: 369 | O88: + | P88: =SUMIF(AF:AF,N88,AH:AH) -> 0 | Q88: =SUMIF(AF:AF,N88,AG:AG) -> 0 | R88: =+P88-Q88 -> 0 | T88: =IF(S88>0,S88,0) -> 0 | U88: =IF(S88>0,0,S88) -> 0 | V88: =+R88 -> 0 | W88: =IF(V88>0,V88,0) -> 0 | X88: =IF(V88>0,0,V88) -> 0 | Z88: =IF(Y88>0,Y88,0) -> 0 | AA88: =IF(Y88>0,0,Y88) -> 0 | AC88: =+Y88+V88+S88+-AB88 -> 0 | AD88: =+AC88-R88 -> 0 | AE88: 111 | AF88: 369 | AG88: =SUMIF('3BL ACTUAL'!B:B,AF88,'3BL ACTUAL'!E:E) -> 0 | AH88: =SUMIF('1 BL anterior'!B:B,AF88,'1 BL anterior'!E:E) -> 0
E89: PLANTAS PRODUCTORAS (AGRICULTURA) | AG89: =SUMIF('3BL ACTUAL'!B:B,AF89,'3BL ACTUAL'!E:E) -> 0 | AH89: =SUMIF('1 BL anterior'!B:B,AF89,'1 BL anterior'!E:E) -> 0
F90: Costo histórico antes de reexpresiones o revaluaciones | N90: 370 | O90: + | P90: =SUMIF(AF:AF,N90,AH:AH) -> 0 | Q90: =SUMIF(AF:AF,N90,AG:AG) -> 0 | R90: =+P90-Q90 -> 0 | T90: =IF(S90>0,S90,0) -> 0 | U90: =IF(S90>0,0,S90) -> 0 | V90: =+R90 -> 0 | W90: =IF(V90>0,V90,0) -> 0 | X90: =IF(V90>0,0,V90) -> 0 | Z90: =IF(Y90>0,Y90,0) -> 0 | AA90: =IF(Y90>0,0,Y90) -> 0 | AC90: =+Y90+V90+S90+-AB90 -> 0 | AD90: =+AC90-R90 -> 0 | AE90: 111 | AF90: 370 | AG90: =SUMIF('3BL ACTUAL'!B:B,AF90,'3BL ACTUAL'!E:E) -> 0 | AH90: =SUMIF('1 BL anterior'!B:B,AF90,'1 BL anterior'!E:E) -> 0
F91: Ajuste acumulado por reexpresiones o revaluaciones | N91: 371 | O91: + | P91: =SUMIF(AF:AF,N91,AH:AH) -> 0 | Q91: =SUMIF(AF:AF,N91,AG:AG) -> 0 | R91: =+P91-Q91 -> 0 | T91: =IF(S91>0,S91,0) -> 0 | U91: =IF(S91>0,0,S91) -> 0 | V91: =+R91 -> 0 | W91: =IF(V91>0,V91,0) -> 0 | X91: =IF(V91>0,0,V91) -> 0 | Z91: =IF(Y91>0,Y91,0) -> 0 | AA91: =IF(Y91>0,0,Y91) -> 0 | AC91: =+Y91+V91+S91+-AB91 -> 0 | AD91: =+AC91-R91 -> 0 | AE91: 111 | AF91: 371 | AG91: =SUMIF('3BL ACTUAL'!B:B,AF91,'3BL ACTUAL'!E:E) -> 0 | AH91: =SUMIF('1 BL anterior'!B:B,AF91,'1 BL anterior'!E:E) -> 0
E92: Construcciones en Curso y Otros Activos en Tránsito | N92: 372 | O92: + | P92: =SUMIF(AF:AF,N92,AH:AH) -> 454254.09 | Q92: =SUMIF(AF:AF,N92,AG:AG) -> 0 | R92: =+P92-Q92 -> 454254.09 | T92: =IF(S92>0,S92,0) -> 0 | U92: =IF(S92>0,0,S92) -> 0 | V92: =+R92 -> 454254.09 | W92: =IF(V92>0,V92,0) -> 454254.09 | X92: =IF(V92>0,0,V92) -> 0 | Z92: =IF(Y92>0,Y92,0) -> 0 | AA92: =IF(Y92>0,0,Y92) -> 0 | AC92: =+Y92+V92+S92+-AB92 -> 454254.09 | AD92: =+AC92-R92 -> 0 | AE92: 111 | AF92: 372 | AG92: =SUMIF('3BL ACTUAL'!B:B,AF92,'3BL ACTUAL'!E:E) -> 0 | AH92: =SUMIF('1 BL anterior'!B:B,AF92,'1 BL anterior'!E:E) -> 454254.09
E93: Muebles y enseres | N93: 373 | O93: + | P93: =SUMIF(AF:AF,N93,AH:AH) -> 0 | Q93: =SUMIF(AF:AF,N93,AG:AG) -> 0 | R93: =+P93-Q93 -> 0 | T93: =IF(S93>0,S93,0) -> 0 | U93: =IF(S93>0,0,S93) -> 0 | V93: =+R93 -> 0 | W93: =IF(V93>0,V93,0) -> 0 | X93: =IF(V93>0,0,V93) -> 0 | Z93: =IF(Y93>0,Y93,0) -> 0 | AA93: =IF(Y93>0,0,Y93) -> 0 | AC93: =+Y93+V93+S93+-AB93 -> 0 | AD93: =+AC93-R93 -> 0 | AE93: 111 | AF93: 373 | AG93: =SUMIF('3BL ACTUAL'!B:B,AF93,'3BL ACTUAL'!E:E) -> 0 | AH93: =SUMIF('1 BL anterior'!B:B,AF93,'1 BL anterior'!E:E) -> 0
E94: Equipo de Computación | N94: 374 | O94: + | P94: =SUMIF(AF:AF,N94,AH:AH) -> 500 | Q94: =SUMIF(AF:AF,N94,AG:AG) -> 0 | R94: =+P94-Q94 -> 500 | T94: =IF(S94>0,S94,0) -> 0 | U94: =IF(S94>0,0,S94) -> 0 | V94: =+R94 -> 500 | W94: =IF(V94>0,V94,0) -> 500 | X94: =IF(V94>0,0,V94) -> 0 | Z94: =IF(Y94>0,Y94,0) -> 0 | AA94: =IF(Y94>0,0,Y94) -> 0 | AC94: =+Y94+V94+S94+-AB94 -> 500 | AD94: =+AC94-R94 -> 0 | AE94: 111 | AF94: 374 | AG94: =SUMIF('3BL ACTUAL'!B:B,AF94,'3BL ACTUAL'!E:E) -> 0 | AH94: =SUMIF('1 BL anterior'!B:B,AF94,'1 BL anterior'!E:E) -> 500
E95: Vehículos, Equipo de Transporte y Caminero Móvil | N95: 375 | O95: + | P95: =SUMIF(AF:AF,N95,AH:AH) -> 26500 | Q95: =SUMIF(AF:AF,N95,AG:AG) -> 0 | R95: =+P95-Q95 -> 26500 | T95: =IF(S95>0,S95,0) -> 0 | U95: =IF(S95>0,0,S95) -> 0 | V95: =+R95 -> 26500 | W95: =IF(V95>0,V95,0) -> 26500 | X95: =IF(V95>0,0,V95) -> 0 | Z95: =IF(Y95>0,Y95,0) -> 0 | AA95: =IF(Y95>0,0,Y95) -> 0 | AC95: =+Y95+V95+S95+-AB95 -> 26500 | AD95: =+AC95-R95 -> 0 | AE95: 111 | AF95: 375 | AG95: =SUMIF('3BL ACTUAL'!B:B,AF95,'3BL ACTUAL'!E:E) -> 0 | AH95: =SUMIF('1 BL anterior'!B:B,AF95,'1 BL anterior'!E:E) -> 26500
E96: PROPIEDADES, PLANTA Y EQUIPO POR CONTRATOS DE ARRENDAMIENTO FINANCIERO | AG96: =SUMIF('3BL ACTUAL'!B:B,AF96,'3BL ACTUAL'!E:E) -> 0 | AH96: =SUMIF('1 BL anterior'!B:B,AF96,'1 BL anterior'!E:E) -> 0
F97: Terrenos | N97: 376 | O97: + | P97: =SUMIF(AF:AF,N97,AH:AH) -> 0 | Q97: =SUMIF(AF:AF,N97,AG:AG) -> 0 | R97: =+P97-Q97 -> 0 | T97: =IF(S97>0,S97,0) -> 0 | U97: =IF(S97>0,0,S97) -> 0 | V97: =+R97 -> 0 | W97: =IF(V97>0,V97,0) -> 0 | X97: =IF(V97>0,0,V97) -> 0 | Z97: =IF(Y97>0,Y97,0) -> 0 | AA97: =IF(Y97>0,0,Y97) -> 0 | AC97: =+Y97+V97+S97+-AB97 -> 0 | AD97: =+AC97-R97 -> 0 | AE97: 111 | AF97: 376 | AG97: =SUMIF('3BL ACTUAL'!B:B,AF97,'3BL ACTUAL'!E:E) -> 0 | AH97: =SUMIF('1 BL anterior'!B:B,AF97,'1 BL anterior'!E:E) -> 0
F98: Edificios y otros inmuebles (excepto terrenos) | G98: edificios y otros inmuebles (excepto terrenos) | K98: edificios y otros inmuebles (excepto terrenos) | L98: edificios y otros inmuebles (excepto terrenos) | M98: edificios y otros inmuebles (excepto terrenos) | N98: 377 | O98: + | P98: =SUMIF(AF:AF,N98,AH:AH) -> 0 | Q98: =SUMIF(AF:AF,N98,AG:AG) -> 0 | R98: =+P98-Q98 -> 0 | T98: =IF(S98>0,S98,0) -> 0 | U98: =IF(S98>0,0,S98) -> 0 | V98: =+R98 -> 0 | W98: =IF(V98>0,V98,0) -> 0 | X98: =IF(V98>0,0,V98) -> 0 | Z98: =IF(Y98>0,Y98,0) -> 0 | AA98: =IF(Y98>0,0,Y98) -> 0 | AC98: =+Y98+V98+S98+-AB98 -> 0 | AD98: =+AC98-R98 -> 0 | AE98: 111 | AF98: 377 | AG98: =SUMIF('3BL ACTUAL'!B:B,AF98,'3BL ACTUAL'!E:E) -> 0 | AH98: =SUMIF('1 BL anterior'!B:B,AF98,'1 BL anterior'!E:E) -> 0
F99: Naves, aeronaves, barcazas y similares | G99: naves, aeronaves, barcazas y similares | K99: naves, aeronaves, barcazas y similares | L99: naves, aeronaves, barcazas y similares | M99: naves, aeronaves, barcazas y similares | N99: 378 | O99: + | P99: =SUMIF(AF:AF,N99,AH:AH) -> 0 | Q99: =SUMIF(AF:AF,N99,AG:AG) -> 0 | R99: =+P99-Q99 -> 0 | T99: =IF(S99>0,S99,0) -> 0 | U99: =IF(S99>0,0,S99) -> 0 | V99: =+R99 -> 0 | W99: =IF(V99>0,V99,0) -> 0 | X99: =IF(V99>0,0,V99) -> 0 | Z99: =IF(Y99>0,Y99,0) -> 0 | AA99: =IF(Y99>0,0,Y99) -> 0 | AC99: =+Y99+V99+S99+-AB99 -> 0 | AD99: =+AC99-R99 -> 0 | AE99: 111 | AF99: 378 | AG99: =SUMIF('3BL ACTUAL'!B:B,AF99,'3BL ACTUAL'!E:E) -> 0 | AH99: =SUMIF('1 BL anterior'!B:B,AF99,'1 BL anterior'!E:E) -> 0
F100: Maquinaria, equipo, instalaciones y adecuaciones | G100: maquinaria, equipo, instalaciones y adecuaciones | K100: maquinaria, equipo, instalaciones y adecuaciones | L100: maquinaria, equipo, instalaciones y adecuaciones | M100: maquinaria, equipo, instalaciones y adecuaciones | N100: 379 | O100: + | P100: =SUMIF(AF:AF,N100,AH:AH) -> 0 | Q100: =SUMIF(AF:AF,N100,AG:AG) -> 0 | R100: =+P100-Q100 -> 0 | T100: =IF(S100>0,S100,0) -> 0 | U100: =IF(S100>0,0,S100) -> 0 | V100: =+R100 -> 0 | W100: =IF(V100>0,V100,0) -> 0 | X100: =IF(V100>0,0,V100) -> 0 | Z100: =IF(Y100>0,Y100,0) -> 0 | AA100: =IF(Y100>0,0,Y100) -> 0 | AC100: =+Y100+V100+S100+-AB100 -> 0 | AD100: =+AC100-R100 -> 0 | AE100: 111 | AF100: 379 | AG100: =SUMIF('3BL ACTUAL'!B:B,AF100,'3BL ACTUAL'!E:E) -> 0 | AH100: =SUMIF('1 BL anterior'!B:B,AF100,'1 BL anterior'!E:E) -> 0
...

Sheet 1 BL anterior
S1: hoja sumaria | T1: repetidos periodo siguiente | U1: codig año actual
P2: 0
P3: 0
P4: 0
C5: CUENTA | D5: NOMBRE | E5: TOTAL | F5: según 101 | P5: 0 | Q5: =CONCATENATE(B5,P5) -> 0 | S5: =SUMIF('FLUJO ACTUAL'!AF:AF,B5,'FLUJO ACTUAL'!AE:AE) -> 0 | T5: =SUMIF('3BL ACTUAL'!C:C,C5,'3BL ACTUAL'!P:P) -> 4 | U5: =SUMIF('3BL ACTUAL'!C:C,C5,'3BL ACTUAL'!B:B) -> 0
C6: 1 | D6: Activos | P6: 0 | Q6: =CONCATENATE(B6,P6) -> 0 | S6: =SUMIF('FLUJO ACTUAL'!AF:AF,B6,'FLUJO ACTUAL'!AE:AE) -> 0 | T6: =SUMIF('3BL ACTUAL'!C:C,C6,'3BL ACTUAL'!P:P) -> 0 | U6: =SUMIF('3BL ACTUAL'!C:C,C6,'3BL ACTUAL'!B:B) -> 0
C7: 1.01 | D7: activo corriente | P7: 0 | Q7: =CONCATENATE(B7,P7) -> 0 | S7: =SUMIF('FLUJO ACTUAL'!AF:AF,B7,'FLUJO ACTUAL'!AE:AE) -> 0 | T7: =SUMIF('3BL ACTUAL'!C:C,C7,'3BL ACTUAL'!P:P) -> 0 | U7: =SUMIF('3BL ACTUAL'!C:C,C7,'3BL ACTUAL'!B:B) -> 0
C8: 1.01.01 | D8: efectivo y equivalentes a efectivo | P8: 0 | Q8: =CONCATENATE(B8,P8) -> 0 | S8: =SUMIF('FLUJO ACTUAL'!AF:AF,B8,'FLUJO ACTUAL'!AE:AE) -> 0 | T8: =SUMIF('3BL ACTUAL'!C:C,C8,'3BL ACTUAL'!P:P) -> 0 | U8: =SUMIF('3BL ACTUAL'!C:C,C8,'3BL ACTUAL'!B:B) -> 0
C9: 1.01.01.01 | D9: Caja efectivo | G9: -57520.44 | H9: 57520.44 | P9: 0 | Q9: =CONCATENATE(B9,P9) -> 0 | S9: =SUMIF('FLUJO ACTUAL'!AF:AF,B9,'FLUJO ACTUAL'!AE:AE) -> 0 | T9: =SUMIF('3BL ACTUAL'!C:C,C9,'3BL ACTUAL'!P:P) -> 0 | U9: =SUMIF('3BL ACTUAL'!C:C,C9,'3BL ACTUAL'!B:B) -> 0
C10: 1.01.01.01.01 | D10: Caja recaudaciones | P10: 0 | Q10: =CONCATENATE(B10,P10) -> 0 | S10: =SUMIF('FLUJO ACTUAL'!AF:AF,B10,'FLUJO ACTUAL'!AE:AE) -> 0 | T10: =SUMIF('3BL ACTUAL'!C:C,C10,'3BL ACTUAL'!P:P) -> 0 | U10: =SUMIF('3BL ACTUAL'!C:C,C10,'3BL ACTUAL'!B:B) -> 0
B11: 311 | C11: 1.01.01.01.01.05 | D11: Caja 4 | E11: 0 | P11: 0 | Q11: =CONCATENATE(B11,P11) -> 3110 | S11: =SUMIF('FLUJO ACTUAL'!AF:AF,B11,'FLUJO ACTUAL'!AE:AE) -> 101 | T11: =SUMIF('3BL ACTUAL'!C:C,C11,'3BL ACTUAL'!P:P) -> 0 | U11: =SUMIF('3BL ACTUAL'!C:C,C11,'3BL ACTUAL'!B:B) -> 311
B12: 0 | C12: 1.01.01.02 | D12: Bancos | E12: 0 | P12: 0 | Q12: =CONCATENATE(B12,P12) -> 00 | S12: =SUMIF('FLUJO ACTUAL'!AF:AF,B12,'FLUJO ACTUAL'!AE:AE) -> 0 | T12: =SUMIF('3BL ACTUAL'!C:C,C12,'3BL ACTUAL'!P:P) -> 0 | U12: =SUMIF('3BL ACTUAL'!C:C,C12,'3BL ACTUAL'!B:B) -> 0
B13: 0 | C13: 1.01.01.02.01 | D13: Bancos Locales | E13: 0 | P13: 0 | Q13: =CONCATENATE(B13,P13) -> 00 | S13: =SUMIF('FLUJO ACTUAL'!AF:AF,B13,'FLUJO ACTUAL'!AE:AE) -> 0 | T13: =SUMIF('3BL ACTUAL'!C:C,C13,'3BL ACTUAL'!P:P) -> 0 | U13: =SUMIF('3BL ACTUAL'!C:C,C13,'3BL ACTUAL'!B:B) -> 0
B14: 311 | C14: 1.01.01.02.01.01 | D14: Banco del Pichincha 2100224986 | E14: 21075.33 | F14: 19813.35 | P14: 0 | Q14: =CONCATENATE(B14,P14) -> 3110 | S14: =SUMIF('FLUJO ACTUAL'!AF:AF,B14,'FLUJO ACTUAL'!AE:AE) -> 101 | T14: =SUMIF('3BL ACTUAL'!C:C,C14,'3BL ACTUAL'!P:P) -> 0 | U14: =SUMIF('3BL ACTUAL'!C:C,C14,'3BL ACTUAL'!B:B) -> 311
B15: 0 | C15: 1.01.02 | D15: Activos financieros corrientes | E15: 0 | I15: 70000 | P15: 0 | Q15: =CONCATENATE(B15,P15) -> 00 | S15: =SUMIF('FLUJO ACTUAL'!AF:AF,B15,'FLUJO ACTUAL'!AE:AE) -> 0 | T15: =SUMIF('3BL ACTUAL'!C:C,C15,'3BL ACTUAL'!P:P) -> 0 | U15: =SUMIF('3BL ACTUAL'!C:C,C15,'3BL ACTUAL'!B:B) -> 0
B16: 0 | C16: 1.01.02.05 | D16: Cuentas por cobrar | E16: 0 | I16: =+I15/4000 -> 17.5 | P16: 0 | Q16: =CONCATENATE(B16,P16) -> 00 | S16: =SUMIF('FLUJO ACTUAL'!AF:AF,B16,'FLUJO ACTUAL'!AE:AE) -> 0 | T16: =SUMIF('3BL ACTUAL'!C:C,C16,'3BL ACTUAL'!P:P) -> 0 | U16: =SUMIF('3BL ACTUAL'!C:C,C16,'3BL ACTUAL'!B:B) -> 0
B17: 0 | C17: 1.01.02.05.01 | D17: Clientes por cobrar | E17: 0 | P17: 0 | Q17: =CONCATENATE(B17,P17) -> 00 | S17: =SUMIF('FLUJO ACTUAL'!AF:AF,B17,'FLUJO ACTUAL'!AE:AE) -> 0 | T17: =SUMIF('3BL ACTUAL'!C:C,C17,'3BL ACTUAL'!P:P) -> 0 | U17: =SUMIF('3BL ACTUAL'!C:C,C17,'3BL ACTUAL'!B:B) -> 0
B18: 312 | C18: 1.01.02.05.01.01 | D18: Clientes por cobrar nacionales | E18: 0 | P18: 0 | Q18: =CONCATENATE(B18,P18) -> 3120 | S18: =SUMIF('FLUJO ACTUAL'!AF:AF,B18,'FLUJO ACTUAL'!AE:AE) -> 102 | T18: =SUMIF('3BL ACTUAL'!C:C,C18,'3BL ACTUAL'!P:P) -> 0 | U18: =SUMIF('3BL ACTUAL'!C:C,C18,'3BL ACTUAL'!B:B) -> 312
B19: 0 | C19: 1.01.02.05.03 | D19: Cuentas por cobrar socios o accionistas | E19: 0 | G19: -265951.03 | H19: 396198 | P19: 0 | Q19: =CONCATENATE(B19,P19) -> 00 | S19: =SUMIF('FLUJO ACTUAL'!AF:AF,B19,'FLUJO ACTUAL'!AE:AE) -> 0 | T19: =SUMIF('3BL ACTUAL'!C:C,C19,'3BL ACTUAL'!P:P) -> 0 | U19: =SUMIF('3BL ACTUAL'!C:C,C19,'3BL ACTUAL'!B:B) -> 0
B20: 315 | C20: 1.01.02.05.03.01 | D20: Cuentas por cobrar socios o accionistas nacionales | E20: 0 | P20: 0 | Q20: =CONCATENATE(B20,P20) -> 3150 | S20: =SUMIF('FLUJO ACTUAL'!AF:AF,B20,'FLUJO ACTUAL'!AE:AE) -> 102 | T20: =SUMIF('3BL ACTUAL'!C:C,C20,'3BL ACTUAL'!P:P) -> 0 | U20: =SUMIF('3BL ACTUAL'!C:C,C20,'3BL ACTUAL'!B:B) -> 315
B21: 0 | C21: 1.01.03 | D21: Inventario | E21: 0 | F21: 251470.34 | G21: -7384.3 | H21: 10009.3 | P21: 0 | Q21: =CONCATENATE(B21,P21) -> 00 | S21: =SUMIF('FLUJO ACTUAL'!AF:AF,B21,'FLUJO ACTUAL'!AE:AE) -> 0 | T21: =SUMIF('3BL ACTUAL'!C:C,C21,'3BL ACTUAL'!P:P) -> 0 | U21: =SUMIF('3BL ACTUAL'!C:C,C21,'3BL ACTUAL'!B:B) -> 0
B22: 0 | C22: 1.01.03.01 | D22: Inventarios para la venta | E22: 0 | P22: 0 | Q22: =CONCATENATE(B22,P22) -> 00 | S22: =SUMIF('FLUJO ACTUAL'!AF:AF,B22,'FLUJO ACTUAL'!AE:AE) -> 0 | T22: =SUMIF('3BL ACTUAL'!C:C,C22,'3BL ACTUAL'!P:P) -> 0 | U22: =SUMIF('3BL ACTUAL'!C:C,C22,'3BL ACTUAL'!B:B) -> 0
B23: 0 | C23: 1.01.03.01.04 | D23: Inventario de prod. term. y mercad. en almacén (excluyendo obras/inmuebles terminados para la venta) | E23: 0 | P23: 0 | Q23: =CONCATENATE(B23,P23) -> 00 | S23: =SUMIF('FLUJO ACTUAL'!AF:AF,B23,'FLUJO ACTUAL'!AE:AE) -> 0 | T23: =SUMIF('3BL ACTUAL'!C:C,C23,'3BL ACTUAL'!P:P) -> 0 | U23: =SUMIF('3BL ACTUAL'!C:C,C23,'3BL ACTUAL'!B:B) -> 0
B24: 0 | C24: 1.01.03.01.04.01 | D24: Mercaderia en bodegas | E24: 0 | G24: 2320 | H24: -240 | P24: 0 | Q24: =CONCATENATE(B24,P24) -> 00 | S24: =SUMIF('FLUJO ACTUAL'!AF:AF,B24,'FLUJO ACTUAL'!AE:AE) -> 0 | T24: =SUMIF('3BL ACTUAL'!C:C,C24,'3BL ACTUAL'!P:P) -> 0 | U24: =SUMIF('3BL ACTUAL'!C:C,C24,'3BL ACTUAL'!B:B) -> 0
B25: 341 | C25: 1.01.03.01.04.01.01 | D25: Bodega principal 12 % | E25: 0 | G25: -3805.27 | H25: 4755.52 | P25: 0 | Q25: =CONCATENATE(B25,P25) -> 3410 | S25: =SUMIF('FLUJO ACTUAL'!AF:AF,B25,'FLUJO ACTUAL'!AE:AE) -> 104 | T25: =SUMIF('3BL ACTUAL'!C:C,C25,'3BL ACTUAL'!P:P) -> 0 | U25: =SUMIF('3BL ACTUAL'!C:C,C25,'3BL ACTUAL'!B:B) -> 341
B26: 0 | C26: 1.01.03.03 | D26: Activos biologicos | E26: 0 | P26: 0 | Q26: =CONCATENATE(B26,P26) -> 00 | S26: =SUMIF('FLUJO ACTUAL'!AF:AF,B26,'FLUJO ACTUAL'!AE:AE) -> 0 | T26: =SUMIF('3BL ACTUAL'!C:C,C26,'3BL ACTUAL'!P:P) -> 0 | U26: =SUMIF('3BL ACTUAL'!C:C,C26,'3BL ACTUAL'!B:B) -> 0
B27: 0 | C27: 1.01.03.03.01 | D27: Plantas vivas y frutos en crecimiento | E27: 0 | P27: 0 | Q27: =CONCATENATE(B27,P27) -> 00 | S27: =SUMIF('FLUJO ACTUAL'!AF:AF,B27,'FLUJO ACTUAL'!AE:AE) -> 0 | T27: =SUMIF('3BL ACTUAL'!C:C,C27,'3BL ACTUAL'!P:P) -> 0 | U27: =SUMIF('3BL ACTUAL'!C:C,C27,'3BL ACTUAL'!B:B) -> 0
B28: 0 | C28: 1.01.03.03.01.01 | D28: Sector 1 | E28: 0 | P28: 0 | Q28: =CONCATENATE(B28,P28) -> 00 | S28: =SUMIF('FLUJO ACTUAL'!AF:AF,B28,'FLUJO ACTUAL'!AE:AE) -> 0 | T28: =SUMIF('3BL ACTUAL'!C:C,C28,'3BL ACTUAL'!P:P) -> 0 | U28: =SUMIF('3BL ACTUAL'!C:C,C28,'3BL ACTUAL'!B:B) -> 0
B29: 341 | C29: 1.01.03.03.01.01.01 | D29: Productos quimicos | E29: 0 | P29: 0 | Q29: =CONCATENATE(B29,P29) -> 3410 | S29: =SUMIF('FLUJO ACTUAL'!AF:AF,B29,'FLUJO ACTUAL'!AE:AE) -> 104 | T29: =SUMIF('3BL ACTUAL'!C:C,C29,'3BL ACTUAL'!P:P) -> 0 | U29: =SUMIF('3BL ACTUAL'!C:C,C29,'3BL ACTUAL'!B:B) -> 341
B30: 341 | C30: 1.01.03.03.01.01.02 | D30: GLP industrial | E30: 0 | G30: -249470.34 | H30: 251470.34 | I30: 251470.34 | P30: 0 | Q30: =CONCATENATE(B30,P30) -> 3410 | S30: =SUMIF('FLUJO ACTUAL'!AF:AF,B30,'FLUJO ACTUAL'!AE:AE) -> 104 | T30: =SUMIF('3BL ACTUAL'!C:C,C30,'3BL ACTUAL'!P:P) -> 0 | U30: =SUMIF('3BL ACTUAL'!C:C,C30,'3BL ACTUAL'!B:B) -> 341
B31: 341 | C31: 1.01.03.03.01.01.03 | D31: Mant y Rep equipos | E31: 0 | I31: 142027.67 | P31: 0 | Q31: =CONCATENATE(B31,P31) -> 3410 | S31: =SUMIF('FLUJO ACTUAL'!AF:AF,B31,'FLUJO ACTUAL'!AE:AE) -> 104 | T31: =SUMIF('3BL ACTUAL'!C:C,C31,'3BL ACTUAL'!P:P) -> 0 | U31: =SUMIF('3BL ACTUAL'!C:C,C31,'3BL ACTUAL'!B:B) -> 341
B32: 341 | C32: 1.01.03.03.01.01.04 | D32: Suministros de Oficina Inventario Cultivo | E32: 0 | P32: 0 | Q32: =CONCATENATE(B32,P32) -> 3410 | S32: =SUMIF('FLUJO ACTUAL'!AF:AF,B32,'FLUJO ACTUAL'!AE:AE) -> 104 | T32: =SUMIF('3BL ACTUAL'!C:C,C32,'3BL ACTUAL'!P:P) -> 0 | U32: =SUMIF('3BL ACTUAL'!C:C,C32,'3BL ACTUAL'!B:B) -> 341
B33: 341 | C33: 1.01.03.03.01.01.05 | D33: transporte de personal | E33: 0 | P33: 0 | Q33: =CONCATENATE(B33,P33) -> 3410 | S33: =SUMIF('FLUJO ACTUAL'!AF:AF,B33,'FLUJO ACTUAL'!AE:AE) -> 104 | T33: =SUMIF('3BL ACTUAL'!C:C,C33,'3BL ACTUAL'!P:P) -> 0 | U33: =SUMIF('3BL ACTUAL'!C:C,C33,'3BL ACTUAL'!B:B) -> 341
B34: 341 | C34: 1.01.03.03.01.01.06 | D34: Repuestos | E34: 0 | G34: -129453.04 | H34: 130246.97 | P34: 0 | Q34: =CONCATENATE(B34,P34) -> 3410 | S34: =SUMIF('FLUJO ACTUAL'!AF:AF,B34,'FLUJO ACTUAL'!AE:AE) -> 104 | T34: =SUMIF('3BL ACTUAL'!C:C,C34,'3BL ACTUAL'!P:P) -> 0 | U34: =SUMIF('3BL ACTUAL'!C:C,C34,'3BL ACTUAL'!B:B) -> 341
B35: 341 | C35: 1.01.03.03.01.01.07 | D35: Compra de agua | E35: 0 | G35: -153634.16 | H35: 154283.96 | P35: 0 | Q35: =CONCATENATE(B35,P35) -> 3410 | S35: =SUMIF('FLUJO ACTUAL'!AF:AF,B35,'FLUJO ACTUAL'!AE:AE) -> 104 | T35: =SUMIF('3BL ACTUAL'!C:C,C35,'3BL ACTUAL'!P:P) -> 0 | U35: =SUMIF('3BL ACTUAL'!C:C,C35,'3BL ACTUAL'!B:B) -> 341
B36: 341 | C36: 1.01.03.03.01.01.08 | D36: compra de cañas | E36: 0 | G36: -2135 | H36: 2625 | P36: 0 | Q36: =CONCATENATE(B36,P36) -> 3410 | S36: =SUMIF('FLUJO ACTUAL'!AF:AF,B36,'FLUJO ACTUAL'!AE:AE) -> 104 | T36: =SUMIF('3BL ACTUAL'!C:C,C36,'3BL ACTUAL'!P:P) -> 0 | U36: =SUMIF('3BL ACTUAL'!C:C,C36,'3BL ACTUAL'!B:B) -> 341
